Workbook

Sheet ToDo
B2: Check blue tabs - all others are from BIM Landscape - for reference and further validation. Calculations not yet working!
B4: GIS-Standards | C4: Following "BIM Landscape" columns with some additions/clarifications (check column comments)
C6: ToDo-s | M6: Responsible | N6: Status
D7: EN/ISO standards included (Geographic information), ca 90 standards | M7: Raido | N7: Done
D8: EN/ISO standards ("BIM"+"GIS"), +25 standards | M8: Raido | N8: Done
D9: Suggest additional GIS related sources to be included? | M9: ???
E10: Source #1 | M10: ???
E11: Source #2 | M11: ???
D12: Keywords/subdomain extractions from abstract/scope? | M12: ???
B17: GIS-Relationships | C17: Following "BIM Landscape" columns with some additions/clarifications (check column comments)
C19: ToDo-s | M19: Responsible | N19: Status
D20: EN/ISO standards references (Geographic information) (normative/informative) | M20: Raido | N20: Done
D21: EN/ISO standards ("BIM"+"GIS") (normative/informative) | M21: Raido | N21: Done
M22: ???
M23: ???
M24: ???
B26: Deliverable | C26: Article structure, data visualization possibilities
C28: ToDo-s | M28: Responsible | N28: Status
D29: Structure and introductory parts for a future article (How BIM and GIS standards interrelates with each other) | M29: Raido | N29: Not started
D30: Data visualization (ex. | F30: https://gephi.org/ - is it good enough for our workflows?) | M30: ???
E31: neo4j - commerical? (if someone has access?)
E32: Any other tool for visualization?
E33: What additional columns are needed in this Excel?
D34: Building up tables with calculated key values (currently most of them are N/A) | M34: Raido | N34: Not started
E35: To use BIM Landscape values or …
D36: How to find connections to BIM Landscape Explorer - in terms of standards
E37: ISO ICS groups | M37: Raido | N37: Not started
E38: ???
D39: BIM (Level of Information need - apperance etc) vs GIS

Sheet GIS-Standards
A1: ID | B1: Standard Number | C1: Title | D1: Scope/Abstract | E1: Comment | F1: Web Links | G1: First Year | H1: Current Year | I1: AC Year | J1: ICS | K1: Type | L1: Is CEN? | M1: CEN Committee | N1: Is ISO? | O1: ISO Committee | P1: Colour_Type_calculation | Q1: Degree Centrality | R1: In-Degree Centrality | S1: Out-Degree Centrality | T1: Eigencentrality
A2: 1 | B2: CEN/TR 15449-1 | C2: Geographic information - Spatial data infrastructures - Part 1: Reference model | D2: This part of the Technical Report provides a reference model for a Spatial Data Infrastructure (SDI). It covers framework standards and identifies the relevant standards, technical specifications, technical reports and guidelines. This part of the Technical Report provides a context model for the other parts of this Technical Report applying general architecture standards. The intended readership of this Technical Report are those people who are responsible for creating frameworks for SDIs, experts contributing to INSPIRE, experts in information and communication technologies and e-government that need to familiarise themselves with geographic information and SDI concepts, and standards developers and writers. | F2: https://www.en-standard.eu/pd-cen-tr-15449-1-2012-geographic-information-spatial-data-infrastructures-reference-model/ | G2: 2012.10 | H2: 2012.10 | J2: 35.240.70; 07.040 | L2: Yes | M2: CEN/TC 287 | N2: No | P2: =INDEX(Colours!$C$2:$C$14,MATCH(K2,Colours!$A$2:$A$14,0)) -> #N/A | T2: =3+TableStandards11[[#This Row],[Degree Centrality]]*17 -> 3
A3: 2 | B3: CEN/TR 15449-2 | C3: Geographic information - Spatial data infrastructures - Part 2: Best practices | D3: This part of the Technical Report provides best practices regarding Spatial Data Infrastructures (SDIs), referencing to the outcomes of the projects in the frame of the European Union funding programmes. It summarises the deliverables of projects, structured according to the reference model defined in Part 1 of this Technical Report, to be made available in an on-line repository where the relevant outcomes are collected and classified in order to provide a structured sets of recommendations for implementing SDIs at the European, national and sub-national levels. This collection refers mainly to the projects funded by the European Union funding programmes: this choice is driven by the wide vision and analysis which such kind of projects can provide and the wide numbers of stakeholders which have been involved. The outcomes delivered by these relevant practices are collected into a document registry available through the CEN/TC 287 web site. This part of the Technical Report defines the processes and the content of these projects and documents registries, which will help making them more accessible and re-usable. It provides the relevant project deliverables addressing the main SDI issues as described in the other parts of this Technical Report. The intended readership of this Technical Report are those people who are responsible for creating frameworks for SDI, experts contributing to INSPIRE, experts in information and communication technologies and e-government that need to familiarize themselves with geographic information and SDI concepts, and standards developers and writers. | F3: https://www.en-standard.eu/pd-cen-tr-15449-2-2012-geographic-information-spatial-data-infrastructures-best-practices/ | G3: 2012.10 | H3: 2012.10 | J3: 35.240.70; 07.040 | L3: Yes | M3: CEN/TC 287 | N3: No | P3: =INDEX(Colours!$C$2:$C$14,MATCH(K3,Colours!$A$2:$A$14,0)) -> #N/A | T3: =3+TableStandards11[[#This Row],[Degree Centrality]]*17 -> 3
A4: 3 | B4: CEN/TR 15449-3 | C4: Geographic information - Spatial data infrastructures - Part 3: Data centric view | D4: Part 3 of the Technical Report describes a data-centric view of a Spatial Data Infrastructure (SDI). The Data Centric view addresses the concepts of semantic interoperability, the methodology for developing data specifications through the application of the relevant International Standards, and the content of such specifications including Application Schemas, Feature Catalogues, General Feature Model, Data Lifecycle Management and Data Quality, Data Access and Data Transformation. The intended readership of this Technical Report are those people who are responsible for creating frameworks for SDI, experts contributing to INSPIRE, experts in information and communication technologies and e-government that need to familiarise themselves with geographic information and SDI concepts, and standards developers and writers. | F4: https://www.en-standard.eu/pd-cen-tr-15449-3-2012-geographic-information-spatial-data-infrastructures-data-centric-view/ | G4: 2012.10 | H4: 2012.10 | J4: 35.240.70; 07.040 | L4: Yes | M4: CEN/TC 287 | N4: No | P4: =INDEX(Colours!$C$2:$C$14,MATCH(K4,Colours!$A$2:$A$14,0)) -> #N/A | T4: =3+TableStandards11[[#This Row],[Degree Centrality]]*17 -> 3
A5: 4 | B5: CEN/TR 15449-4 | C5: Geographic information - Spatial Data Infrastructure - Service centric view | D5: This Technical Report describes a service-centric view of a Spatial Data Infrastructure (SDI). The Service Centric view addresses the concepts of service specifications, the methodology for developing service specifications through the application of the relevant International Standards, and the content of such service specifications described from the perspective of the five Reference Model of Open Distributed Processing (RM-ODP) viewpoints: the enterprise viewpoint addresses service aspects from an organisational, business and user perspective; the computational viewpoint addresses service aspects from a system architect perspective; the information viewpoint addresses service aspects from a geospatial information expert perspective; the engineering viewpoint addresses service aspects from a system designer perspective; the technology viewpoint addresses service aspects from a system builder and implementer perspective. The intended readership of this Technical Report is those people who are responsible for creating frameworks for SDI, experts contributing to INSPIRE experts in information and communication technologies and e-government that need to familiarise themselves with geographic information and SDI concepts, and standards developers and writers. | F5: https://www.en-standard.eu/pd-cen-tr-15449-4-2013-geographic-information-spatial-data-infrastructure-service-centric-view/ | G5: 2013.07 | H5: 2013.07 | J5: 35.240.70 | L5: Yes | M5: CEN/TC 287 | N5: No | P5: =INDEX(Colours!$C$2:$C$14,MATCH(K5,Colours!$A$2:$A$14,0)) -> #N/A | T5: =3+TableStandards11[[#This Row],[Degree Centrality]]*17 -> 3
A6: 5 | B6: CEN/TR 15449-5 | C6: Geographic information - Spatial data infrastructures - Part 5: Validation and testing | D6: This part of the Technical Report provides guidance for validation and testing of data, metadata and services, as the main Spatial Data Infrastructure (SDI) components defined in other parts of CEN/TR 15449. The guidance is given by means of examples of the validation and testing process required to assure conformance with the requirements existing in the relevant standards and guidelines. | F6: n/a | G6: 2015.04 | H6: 2015.04 | J6: 35.240.70; 07.040 | L6: Yes | M6: CEN/TC 287 | N6: No | P6: =INDEX(Colours!$C$2:$C$14,MATCH(K6,Colours!$A$2:$A$14,0)) -> #N/A | T6: =3+TableStandards11[[#This Row],[Degree Centrality]]*17 -> 3
A7: 6 | B7: ISO 15686-1 | C7: Buildings and constructed assets -- Service life planning -- Part 1: General principles and framework | D7: This part of ISO 15686 identifies and establishes general principles for service life planning and a systematic framework for undertaking service life planning of a planned building or construction work throughout its life cycle (or remaining life cycle for existing buildings or construction works). The life cycle incorporates initiation, project definition, design, construction, commissioning, operation, maintenance, refurbishment, replacement, deconstruction and ultimate disposal, recycling or re-use of the asset (or parts thereof), including its components, systems and building services. This part of ISO 15686 is applicable to the service life planning of individual buildings. NOTE A series of service life plans can be used as input data to the strategic property management of a number of buildings. | E7: BIM + GIS | F7: https://www.iso.org/standard/45798.html | G7: 2000.09 | H7: 2011.05 | J7: 91.040.01 | L7: No | M7: n/a | N7: Yes | O7: ISO/TC 59 | P7: =INDEX(Colours!$C$2:$C$14,MATCH(K7,Colours!$A$2:$A$14,0)) -> #N/A | T7: =3+TableStandards11[[#This Row],[Degree Centrality]]*17 -> 3
A8: 7 | B8: ISO 15686-10 | C8: Buildings and constructed assets -- Service life planning -- Part 10: When to assess functional performance | D8: This part of ISO 15686 establishes when to specify or verify functional performance requirements during the service life of buildings and building-related facilities, and when to check the capability of buildings and facilities to meet identified requirements.1) This part of ISO 15686 is applicable to any scope of holdings, whether a set (or portfolio) of buildings, a single building (large or small) or a facility which is part of a building (such as one group of spaces, one floor or several floors). It is applicable to the range of roles of stakeholders, from the owners and managers to the occupants, tenants or other users. It is intended to be used with ISO 15686-1, ISO 15686-2, ISO 15686-3, ISO 15686-5, ISO 15686-6, ISO 15686-7, ISO 15686-8 and ISO 15686-9. NOTE 1 The principles and methods can be applied to a single-family residence, but this part of ISO 15686 calls for greater frequency and extent of assessing demand and supply than is typically appropriate.2) NOTE 2 The application of this part of ISO 15686 can be required by the client or by any entity having authority, including regulatory authority. NOTE 3 In Table 2, the column entitled “Outputs called for by other parts of ISO 15686” is provided to show how outputs from other parts of ISO 15686 occur at each phase, whether or not this part of ISO 15686 requires action or output. | E8: BIM + GIS | F8: https://www.iso.org/standard/44859.html | G8: 2010.06 | H8: 2010.06 | J8: 91.040.01 | L8: No | M8: n/a | N8: Yes | O8: ISO/TC 59/SC 14 | P8: =INDEX(Colours!$C$2:$C$14,MATCH(K8,Colours!$A$2:$A$14,0)) -> #N/A | T8: =3+TableStandards11[[#This Row],[Degree Centrality]]*17 -> 3
A9: 8 | B9: ISO 15686-4 | C9: Building Construction -- Service Life Planning -- Part 4: Service Life Planning using Building Information Modelling | D9: This part of ISO 15686 provides information and guidance on the use of standards for information exchange for service life planning of buildings and constructed assets and their components as well as the required supporting data. It provides guidance on structuring information from existing data sources to enable delivery of their information content in a structure that conforms to international standards for information exchange. In particular, reference is made to ISO 16739. The Construction Operations Building Information Exchange (COBie) standard for the exchange of facility information in tabular data are used as an alternative representation. COBie is a tabular representation of a handover view of the IFC schema. It is also applicable to the exchange of service life information between categories of design and information management software applications that have standards-based information exchange interfaces including: a) Building construction Information Modelling (BIM); b) Computer Aided Facilities Management (CAFM). Excluded from this part of the standard are — information exchange using proprietary methods, and — processing and analysis of data within individual software applications, though examples are provided. The main target audience is the Information manager who will use the framework to assist in structuring the International, national or project/facility level BIM guidance document. This Standard specifies the structure and representation of service life data. It is focused on key exchange requirements underlying the common transactions. This document may be used for a variety of purposes a) to achieve and maintain a common understanding within the national and project contexts; b) to establish the desired outcomes and to define appropriate quality; c) to identify appropriate management effort and tools; d) to identify necessary effort and resourcing. Service life planning involves the application of data about elements within a building or constructed assets to enable their design, predicted or estimated service life to be determined and communicated. Buildings are increasingly designed using Building Information Modelling (BIM), an approach that can provide a specification of all the objects in building and how they are aggregated into parts, assemblies and systems. An architect or engineer can define the objects using BIM; it is anticipated that the actor having the service life planning role will apply service life data to these objects and make the data available for other purposes through the use of data exchange standards. Using information exchange standards to describe the structure of service life planning information is important because it normalizes the way in which service life information should be delivered from source to user so that relevant different attributes can be exchanged and a range of software applications can be used to capture the information. | E9: BIM + GIS | F9: https://www.iso.org/standard/59150.html | G9: 2014.01 | H9: 2014.01 | J9: 91.040.01 | L9: No | M9: n/a | N9: Yes | O9: ISO/TC 59/SC 14 | P9: =INDEX(Colours!$C$2:$C$14,MATCH(K9,Colours!$A$2:$A$14,0)) -> #N/A | T9: =3+TableStandards11[[#This Row],[Degree Centrality]]*17 -> 3
A10: 9 | B10: ISO 15686-7 | C10: Buildings and constructed assets -- Service life planning -- Part 7: Performance evaluation for feedback of service life data from practice | D10: This document provides a generic basis for performance evaluation for feedback of service life data from existing buildings and constructed assets, including a definition of the terms to be used and the description of how the (technical) performance can be described and documented to ensure consistencies. The purpose of this document is to describe the principles for service life performance surveys and evaluation with an emphasis on technical recommendations. It describes a generic methodology, including the terms to be used, that provides guidance on the planning, documentation and inspection phases, as well as on analysis and interpretation of performance evaluations, both on the object (single building) and network (stock of buildings) level. While maintenance planning is outside the scope of this document, maintenance-driven inspections and subsequent recommended actions could have significant effects upon service life and performance. | E10: BIM + GIS | F10: https://www.iso.org/standard/61149.html | G10: 2006.03 | H10: 2017.04 | J10: 91.040.01 | L10: No | M10: n/a | N10: Yes | O10: ISO/TC 59/SC 14 | P10: =INDEX(Colours!$C$2:$C$14,MATCH(K10,Colours!$A$2:$A$14,0)) -> #N/A | T10: =3+TableStandards11[[#This Row],[Degree Centrality]]*17 -> 3
A11: 10 | B11: ISO 19101-1 | C11: Geographic information - Reference model - Part 1: Fundamentals | D11: This part of ISO 19101 defines the reference model for standardization in the field of geographic information. This reference model describes the notion of interoperability and sets forth the fundamentals by which this standardization takes place. Although structured in the context of information technology and information technology standards, this part of ISO 19101 is independent of any application development method or technology implementation approach. | F11: https://www.iso.org/standard/59164.html | G11: 2005.01 | H11: 2014.11 | J11: 35.240.70 | L11: Yes | M11: CEN/TC 287 | N11: Yes | O11: ISO/TC 211 | P11: =INDEX(Colours!$C$2:$C$14,MATCH(K11,Colours!$A$2:$A$14,0)) -> #N/A | T11: =3+TableStandards11[[#This Row],[Degree Centrality]]*17 -> 3
A12: 11 | B12: ISO 19101-2 | C12: Geographic information -- Reference model -- Part 2: Imagery | D12: This document defines a reference model for standardization in the field of geographic imagery processing. This reference model identifies the scope of the standardization activity being undertaken and the context in which it takes place. The reference model includes gridded data with an emphasis on imagery. Although structured in the context of information technology and information technology standards, this document is independent of any application development method or technology implementation approach. | F12: https://www.iso.org/standard/69325.html | G12: 2008.06 | H12: 2018.05 | J12: 35.240.70 | L12: No | M12: n/a | N12: Yes | O12: ISO/TC 211 | P12: =INDEX(Colours!$C$2:$C$14,MATCH(K12,Colours!$A$2:$A$14,0)) -> #N/A | T12: =3+TableStandards11[[#This Row],[Degree Centrality]]*17 -> 3
A13: 12 | B13: ISO 19103 | C13: Geographic information - Conceptual schema language | D13: This document specifies provisions for the use of a conceptual schema language within the context of modelling geographic information. The chosen conceptual schema language is a subset of the Unified Modeling Language (UML). This document specifies a UML profile for modelling geographic information. This document specifies a set of core data types for use in conceptual schemas. The standardization target type of this document is conceptual schemas describing geographic information. | F13: https://www.iso.org/standard/83454.html | G13: 2024.10 | H13: 2024.10 | J13: 35.240.70 | L13: Yes | M13: CEN/TC 287 | N13: Yes | O13: ISO/TC 211 | P13: =INDEX(Colours!$C$2:$C$14,MATCH(K13,Colours!$A$2:$A$14,0)) -> #N/A | T13: =3+TableStandards11[[#This Row],[Degree Centrality]]*17 -> 3
A14: 13 | B14: ISO 19104 | C14: Geographic information -- Terminology | D14: ISO 19104:2016 specifies requirements for the collection, management and publication of terminology in the field of geographic information. The scope of this document includes - selection of concepts, harmonization of concepts and development of concept systems, - structure and content of terminological entries, - term selection, - definition preparation, - cultural and linguistic adaptation, - layout and formatting requirements in rendered documents, and - establishment and management of terminology registers. ISO 19104:2016 is applicable to International Standards and Technical Specifications in the field of geographic information. | F14: https://www.iso.org/standard/63541.html | G14: 2008.11 | H14: 2016.10 | J14: 35.240.70; 01.040.35 | L14: No | M14: n/a | N14: Yes | O14: ISO/TC 211 | P14: =INDEX(Colours!$C$2:$C$14,MATCH(K14,Colours!$A$2:$A$14,0)) -> #N/A | T14: =3+TableStandards11[[#This Row],[Degree Centrality]]*17 -> 3
A15: 14 | B15: ISO 19105 | C15: Geographic information - Conformance and testing | D15: This document specifies the framework, concepts and methodology for conformance testing and criteria to be achieved to claim conformance to the family of applicable standardization documents regarding geographic information and relevant application domains. This document provides a framework for specifying abstract test suites composed of abstract test cases grouped in conformance classes and for defining the procedures to be followed during conformance testing. Conformance can be claimed for data or software products or services or by specifications including any profile or functional standard. The structure of, and relationships between, conformance classes as defined in this document underly a systematic approach to configuration management involving managing dependencies within and between modules. | F15: https://www.iso.org/standard/76457.html | G15: 2005.01 | H15: 2022.07 | J15: 35.240.70 | L15: Yes | M15: CEN/TC 287 | N15: Yes | O15: ISO/TC 211 | P15: =INDEX(Colours!$C$2:$C$14,MATCH(K15,Colours!$A$2:$A$14,0)) -> #N/A | T15: =3+TableStandards11[[#This Row],[Degree Centrality]]*17 -> 3
A16: 15 | B16: ISO 19106 | C16: Geographic information - Profiles | D16: This International Standard is intended to define the concept of a profile of the ISO geographic information standards developed by ISO/TC 211 and to provide guidance for the creation of such profiles. Only those components of specifications that meet the definition of a profile contained herein can be established and managed through the mechanisms described in this International Standard. | F16: https://www.iso.org/standard/26011.html | G16: 2006.03 | H16: 2006.03 | J16: 35.240.70 | L16: Yes | M16: CEN/TC 287 | N16: Yes | O16: ISO/TC 211 | P16: =INDEX(Colours!$C$2:$C$14,MATCH(K16,Colours!$A$2:$A$14,0)) -> #N/A | T16: =3+TableStandards11[[#This Row],[Degree Centrality]]*17 -> 3
A17: 16 | B17: ISO 19107 | C17: Geographic information - Spatial schema | D17: This document specifies conceptual schemas for describing the spatial characteristics of geographic entities, and a set of spatial operations consistent with these schemas. It treats "vector" geometry and topology. It defines standard spatial operations for use in access, query, management, processing and data exchange of geographic information for spatial (geometric and topological) objects. Because of the nature of geographic information, these geometric coordinate spaces will normally have up to three spatial dimensions, one temporal dimension and any number of other spatially dependent parameters as needed by the applications. In general, the topological dimension of the spatial projections of the geometric objects will be at most three. | F17: https://www.iso.org/standard/66175.html | G17: 2005.01 | H17: 2019.12 | J17: 35.240.70 | L17: Yes | M17: CEN/TC 287 | N17: Yes | O17: ISO/TC 211 | P17: =INDEX(Colours!$C$2:$C$14,MATCH(K17,Colours!$A$2:$A$14,0)) -> #N/A | T17: =3+TableStandards11[[#This Row],[Degree Centrality]]*17 -> 3
A18: 17 | B18: ISO 19108 | C18: Geographic information - Temporal schema | D18: This International Standard defines concepts for describing temporal characteristics of geographic information. It depends upon existing information technology standards for the interchange of temporal information. It provides a basis for defining temporal feature attributes, feature operations, and feature associations, and for defining the temporal aspects of metadata about geographic information. Since this International Standard is concerned with the temporal characteristics of geographic information as they are abstracted from the real world, it emphasizes valid time rather than transaction time. | F18: https://www.iso.org/standard/26013.html | G18: 2005.01 | H18: 2005.01 | I18: 06.2008 | J18: 35.240.70 | L18: Yes | M18: CEN/TC 287 | N18: Yes | O18: ISO/TC 211 | P18: =INDEX(Colours!$C$2:$C$14,MATCH(K18,Colours!$A$2:$A$14,0)) -> #N/A | T18: =3+TableStandards11[[#This Row],[Degree Centrality]]*17 -> 3
A19: 18 | B19: ISO 19109 | C19: Geographic information - General feature model and rules for application schema | D19: This document defines the General Feature Model (GFM) as the metamodel for creating application schemas in the context of geo-information modelling. The GFM is explained and implemented as rules for creating and documenting application schemas, including principles for the definition of features. This document is applicable to: — conceptual modelling of features and their properties from a universe of discourse; — definition of application schemas; — general rules for using a conceptual schema language for application schemas; — rules for application schemas using UML as the conceptual schema language; — transition from the concepts in the conceptual model to the data types in the application schema; — integration of standardized schemas from other ISO geographic information standards with the application schema. This document does not apply to: — choice of one particular conceptual schema language for application schemas; — definition of any particular application schemas; — representation of feature types and their properties in a feature catalogue; — representation of metadata; — rules for mapping one application schema to another; — implementation of the application schema in a computer environment; — computer system and application software design; — programming. | F19: https://www.iso.org/standard/84700.html | G19: 2015.12 | H19: 2025.07 | J19: 35.240.70 | L19: Yes | M19: CEN/TC 287 | N19: Yes | O19: ISO/TC 211 | P19: =INDEX(Colours!$C$2:$C$14,MATCH(K19,Colours!$A$2:$A$14,0)) -> #N/A | T19: =3+TableStandards11[[#This Row],[Degree Centrality]]*17 -> 3
A20: 19 | B20: ISO 19110 | C20: Geographic information - Methodology for feature cataloguing | D20: ISO 19110:2016 defines the methodology for cataloguing feature types. This document specifies how feature types can be organized into a feature catalogue and presented to the users of a set of geographic data. This document is applicable to creating catalogues of feature types in previously uncatalogued domains and to revising existing feature catalogues to comply with standard practice. This document applies to the cataloguing of feature types that are represented in digital form. Its principles can be extended to the cataloguing of other forms of geographic data. Feature catalogues are independent of feature concept dictionaries defined in ISO 19126 and can be specified without having to use or create a Feature Concept Dictionary. ISO 19110:2016 is applicable to the definition of geographic features at the type level. This document is not applicable to the representation of individual instances of each type. This document excludes portrayal schemas as specified in ISO 19117. ISO 19110:2016 may be used as a basis for defining the universe of discourse being modelled in a particular application, or to standardize general aspects of real world features being modelled in more than one application. | F20: https://www.iso.org/standard/57303.html | G20: 2006.07 | H20: 2016.07 | J20: 35.240.70 | L20: Yes | M20: CEN/TC 287 | N20: Yes | O20: ISO/TC 211 | P20: =INDEX(Colours!$C$2:$C$14,MATCH(K20,Colours!$A$2:$A$14,0)) -> #N/A | T20: =3+TableStandards11[[#This Row],[Degree Centrality]]*17 -> 3
A21: 20 | B21: ISO 19111 | C21: Geographic information - Referencing by coordinates | D21: This document defines the conceptual schema for the description of referencing by coordinates. It describes the minimum data required to define coordinate reference systems. This document supports the definition of: — spatial coordinate reference systems where coordinate values do not change with time. The system may: — be geodetic and apply on a national or regional basis, or — apply locally such as for a building or construction site, or — apply locally to an image or image sensor; — be referenced to a moving platform such as a car, a ship, an aircraft or a spacecraft. Such a coordinate reference system can be related to a second coordinate reference system which is referenced to the Earth through a transformation that includes a time element; — spatial coordinate reference systems in which coordinate values of points on or near the surface of the earth change with time due to tectonic plate motion or other crustal deformation. Such dynamic systems include time evolution, however they remain spatial in nature; — parametric coordinate reference systems which use a non-spatial parameter that varies monotonically with height or depth; — temporal coordinate reference systems which use dateTime, temporal count or temporal measure quantities that vary monotonically with time; — mixed spatial, parametric or temporal coordinate reference systems. The definition of a coordinate reference system does not change with time, although in some cases some of the defining parameters can include a rate of change of the parameter. The coordinate values within a dynamic and in a temporal coordinate reference system can change with time. This document also describes the conceptual schema for defining the information required to describe operations that change coordinate values. In addition to the minimum data required for the definition of the coordinate reference system or coordinate operation, the conceptual schema allows additional descriptive information - coordinate reference system metadata - to be provided. This document is applicable to producers and users of geographic information. Although it is applicable to digital geographic data, the principles described in this document can be extended to many other forms of spatial data such as maps, charts and text documents. | F21: https://www.iso.org/standard/74039.html | G21: 2007.07 | H21: 2020.03 | I21: 08.2023 | J21: 35.240.70 | L21: Yes | M21: CEN/TC 287 | N21: Yes | O21: ISO/TC 211 | P21: =INDEX(Colours!$C$2:$C$14,MATCH(K21,Colours!$A$2:$A$14,0)) -> #N/A | T21: =3+TableStandards11[[#This Row],[Degree Centrality]]*17 -> 3
A22: 21 | B22: ISO 19112 | C22: Geographic information - Spatial referencing by geographic identifiers | D22: This document defines the conceptual schema for spatial references based on geographic identifiers. It establishes a general model for spatial referencing using geographic identifiers and defines the components of a spatial reference system. It also specifies a conceptual scheme for a gazetteer. Spatial referencing by coordinates is addressed in ISO 19111. However, a mechanism for recording complementary coordinate references is included in this document. This document enables producers of data to define spatial reference systems using geographic identifiers and assists users in understanding the spatial references used in datasets. It enables gazetteers to be constructed in a consistent manner and supports the development of other standards in the field of geographic information. This document is applicable to digital geographic data, and its principles may be extended to other forms of geographic data such as maps, charts and textual documents. | F22: https://www.iso.org/standard/70742.html | G22: 2005.01 | H22: 2019.03 | J22: 35.240.70 | L22: Yes | M22: CEN/TC 287 | N22: Yes | O22: ISO/TC 211 | P22: =INDEX(Colours!$C$2:$C$14,MATCH(K22,Colours!$A$2:$A$14,0)) -> #N/A | T22: =3+TableStandards11[[#This Row],[Degree Centrality]]*17 -> 3
A23: 22 | B23: ISO 19115-1 | C23: Geographic information - Metadata - Part 1: Fundamentals | D23: This International Standard defines the schema required for describing geographic information and services by means of metadata. It provides information about the identification, the extent, the quality, the spatial and temporal aspects, the content, the spatial reference, the portrayal, distribution, and other properties of digital geographic data and services. This International Standard is applicable to: - the cataloguing of all types of resources, clearinghouse activities, and the full description of datasets and services; - geographic services, geographic datasets, dataset series, and individual geographic features and feature properties. This International Standard defines: - mandatory and conditional metadata sections, metadata entities, and metadata elements; - the minimum set of metadata required to serve the full range of metadata applications (data discovery, determining data fitness for use, data access, data transfer, and use of digital data and services); - optional metadata elements – to allow for a more extensive standard description of resources, if required; - a method for extending metadata to fit specialized needs. Though this International Standard is applicable to digital data and services, its principles can be extended to many other types of resources such as maps, charts, and textual documents as well as non-geographic data. Certain conditional metadata elements may not apply to these other forms of data. | F23: https://www.iso.org/standard/53798.html | G23: 2005.01 | H23: 2014.04 | I23: 12.2020 | J23: 35.240.70 | L23: Yes | M23: CEN/TC 287 | N23: Yes | O23: ISO/TC 211 | P23: =INDEX(Colours!$C$2:$C$14,MATCH(K23,Colours!$A$2:$A$14,0)) -> #N/A | T23: =3+TableStandards11[[#This Row],[Degree Centrality]]*17 -> 3
A24: 23 | B24: ISO 19115-2 | C24: Geographic information - Metadata - Part 2: Extensions for acquisition and processing | D24: This document extends ISO 19115-1:2014 by defining the schema required for an enhanced description of the acquisition and processing of geographic information, including imagery. Included are the properties of measuring systems and the numerical methods and computational procedures used to derive geographic information from the data acquired by them. This document also provides the XML encoding for acquisition and processing metadata thereby extending the XML schemas defined in ISO/TS 19115-3. | F24: https://www.iso.org/standard/67039.html | G24: 2010.01 | H24: 2019.02 | I24: 03.2022 | J24: 35.240.70 | L24: Yes | M24: CEN/TC 287 | N24: Yes | O24: ISO/TC 211 | P24: =INDEX(Colours!$C$2:$C$14,MATCH(K24,Colours!$A$2:$A$14,0)) -> #N/A | T24: =3+TableStandards11[[#This Row],[Degree Centrality]]*17 -> 3
A25: 24 | B25: ISO 19115-3 | C25: Geographic information - Metadata - Part 3: XML schema implementation for fundamental concepts | D25: This document defines an integrated XML implementation of ISO 19115-1 and ISO 19115-2 by defining the following artefacts: — a set of XML schema required to validate metadata instance documents conforming to conceptual model elements defined in ISO 19115-1 and ISO 19115-2; and — a set of ISO/IEC 19757-3 (Schematron) rules that implement validation constraints in the ISO 19115-1 and ISO 19115-2 UML models that are not validated by the XML schema. This document describes the procedure used to generate XML schemas from ISO geographic information conceptual models related to metadata. The XML schemas are generated directly from the conceptual UML model (8.5). | F25: https://www.iso.org/standard/80874.html | G25: 2023.08 | H25: 2023.08 | J25: 35.240.70 | L25: Yes | M25: CEN/TC 287 | N25: Yes | O25: ISO/TC 211 | P25: =INDEX(Colours!$C$2:$C$14,MATCH(K25,Colours!$A$2:$A$14,0)) -> #N/A | T25: =3+TableStandards11[[#This Row],[Degree Centrality]]*17 -> 3
A26: 25 | B26: ISO 19116 | C26: Geographic information - Positioning services | D26: This document specifies the data structure and content of an interface that permits communication between position-providing device(s) and position-using device(s) enabling the position-using device(s) to obtain and unambiguously interpret position information and determine, based on a measure of the degree of reliability, whether the resulting position information meets the requirements of the intended use. A standardized interface for positioning allows the integration of reliable position information obtained from non-specific positioning technologies and is useful in various location-focused information applications, such as surveying, navigation, intelligent transportation systems (ITS) and location-based services (LBS). | F26: https://www.iso.org/standard/87480.html | G26: 2019.12 | H26: 2025.04 | J26: 35.240.70 | L26: Yes | M26: CEN/TC 287 | N26: Yes | O26: ISO/TC 211 | P26: =INDEX(Colours!$C$2:$C$14,MATCH(K26,Colours!$A$2:$A$14,0)) -> #N/A | T26: =3+TableStandards11[[#This Row],[Degree Centrality]]*17 -> 3
A27: 26 | B27: ISO 19117 | C27: Geographic information - Portrayal | D27: ISO 19117:2012 specifies a conceptual schema for describing symbols, portrayal functions that map geospatial features to symbols, and the collection of symbols and portrayal functions into portrayal catalogues. This conceptual schema can be used in the design of portrayal systems. It allows feature data to be separate from portrayal data, permitting data to be portrayed in a dataset independent manner. | F27: https://www.iso.org/standard/46226.html | G27: 2006.07 | H27: 2014.03 | J27: 35.240.70 | L27: Yes | M27: CEN/TC 287 | N27: Yes | O27: ISO/TC 211 | P27: =INDEX(Colours!$C$2:$C$14,MATCH(K27,Colours!$A$2:$A$14,0)) -> #N/A | T27: =3+TableStandards11[[#This Row],[Degree Centrality]]*17 -> 3
A28: 27 | B28: ISO 19118 | C28: Geographic information - Encoding | D28: This International Standard specifies the requirements for defining encoding rules for use for the interchange of data that conform to the geographic information in the set of International Standards known as the “ISO 19100 series”. This International Standard specifies - requirements for creating encoding rules based on UML schemas, - requirements for creating encoding services, and - requirements for XML-based encoding rules for neutral interchange of data. This International Standard does not specify any digital media, does not define any transfer services or transfer protocols, nor does it specify how to encode inline large images. | F28: https://www.iso.org/standard/44212.html | G28: 2006.07 | H28: 2011.10 | J28: 35.240.70 | L28: Yes | M28: CEN/TC 287 | N28: Yes | O28: ISO/TC 211 | P28: =INDEX(Colours!$C$2:$C$14,MATCH(K28,Colours!$A$2:$A$14,0)) -> #N/A | T28: =3+TableStandards11[[#This Row],[Degree Centrality]]*17 -> 3
A29: 28 | B29: ISO 19119 | C29: Geographic information - Services | D29: This International Standard defines requirements for how platform neutral and platform specific specification of services shall be created, in order to allow for one service to be specified independently of one or more underlying distributed computing platforms. This International Standard defines requirements for a further mapping from platform neutral to platform specific service specifications, in order to enable conformant and interoperable service implementations. This International Standard addresses the Meta:Service foundation of the ISO geographic information reference model described in ISO 19101-1:2014, Clause 6 and Clause 8, respectively. This International Standard defines how geographic services shall be categorised according to a service taxonomy based on architectural areas and allows also for services to be categorised according to a usage life cycle perspective, as well as according to domain specific and user defined service taxonomies, providing support for easier publication and discovery of services. | F29: https://www.iso.org/standard/59221.html | G29: 2006.06 | H29: 2016.02 | J29: 35.240.70 | L29: Yes | M29: CEN/TC 287 | N29: Yes | O29: ISO/TC 211 | P29: =INDEX(Colours!$C$2:$C$14,MATCH(K29,Colours!$A$2:$A$14,0)) -> #N/A | T29: =3+TableStandards11[[#This Row],[Degree Centrality]]*17 -> 3
A30: 29 | B30: ISO 19123-1 | C30: Geographic information - Schema for coverage geometry and functions - Part 1: Fundamentals | D30: This document defines a conceptual schema for coverages. A coverage is a mapping from a spatial, temporal or spatiotemporal domain to attribute values sharing the same attribute type. A coverage domain consists of a collection of direct positions in a coordinate space that can be defined in terms of spatial and/or temporal dimensions, as well as non-spatiotemporal (in ISO 19111:2019, “parametric”) dimensions. Examples of coverages include point clouds, grids, meshes, triangulated irregular networks, and polygon sets. Coverages are the prevailing data structures in a number of application areas, such as remote sensing, meteorology and mapping of depth, elevation, soil and vegetation. This document defines the coverage concept including the relationship between the domain of a coverage and its associated attribute range. This document defines the characteristics of the domain. The characteristics of the attribute range are not defined in this document, but are defined in implementation standards. Consequently, the standardization target of this document consists of implementation standards, not concrete implementations themselves. | F30: https://www.iso.org/standard/70743.html | G30: 2007.03 | H30: 2023.07 | J30: 35.240.70 | L30: Yes | M30: CEN/TC 287 | N30: Yes | O30: ISO/TC 211 | P30: =INDEX(Colours!$C$2:$C$14,MATCH(K30,Colours!$A$2:$A$14,0)) -> #N/A | T30: =3+TableStandards11[[#This Row],[Degree Centrality]]*17 -> 3
A31: 30 | B31: ISO 19123-2 | C31: Geographic information -- Schema for coverage geometry and functions -- Part 2: Coverage implementation schema | D31: This document specifies a concrete[1] implementable, conformance-testable coverage structure based on the abstract schema for coverages defined in the ISO 19123 schema for coverage geometry. This document defines a structure that is suitable for encoding in many encoding formats. [1] "concrete" is used here as a contrast to "abstract" in the sense described in the Introduction. | F31: https://www.iso.org/standard/70948.html | G31: 2018.10 | H31: 2018.10 | J31: 35.240.70 | L31: No | M31: n/a | N31: Yes | O31: ISO/TC 211 | P31: =INDEX(Colours!$C$2:$C$14,MATCH(K31,Colours!$A$2:$A$14,0)) -> #N/A | T31: =3+TableStandards11[[#This Row],[Degree Centrality]]*17 -> 3
A32: 31 | B32: ISO 19123-3 | C32: Geographic information - Schema for coverage geometry and functions - Part 3: Processing fundamentals | D32: This document defines a coverage processing language for server-side extraction, filtering, processing, analytics, and fusion of multi-dimensional geospatial coverages representing, for example, spatio-temporal sensor, image, simulation, or statistics datacubes. Services implementing this language provide access to original or derived sets of coverage information, in forms that are useful for client-side consumption. This document relies on the ISO 19123-1 abstract coverage model. In this edition, regular and irregular multi-dimensional grids are supported for axes that can carry spatial, temporal or any other semantics. Future editions will additionally support further axis types as well as further coverage types from ISO 19123-1, specifically, point clouds and meshes. | F32: https://www.iso.org/standard/83611.html | G32: 2023.07 | H32: 2023.07 | J32: 35.240.70 | L32: Yes | M32: CEN/TC 287 | N32: Yes | O32: ISO/TC 211 | P32: =INDEX(Colours!$C$2:$C$14,MATCH(K32,Colours!$A$2:$A$14,0)) -> #N/A | T32: =3+TableStandards11[[#This Row],[Degree Centrality]]*17 -> 3
A33: 32 | B33: ISO 19125-1 | C33: Geographic information - Simple feature access - Part 1: Common architecture | D33: This part of ISO 19125 establishes a common architecture and defines terms to use within the architecture.This part of ISO 19125 does not attempt to standardize and does not depend upon any part of the mechanism by which Types are added and maintained, including the following: a) syntax and functionality provided for defining types; b) syntax and functionality provided for defining functions; | F33: https://www.iso.org/standard/40114.html | G33: 2006.03 | H33: 2006.03 | J33: 35.240.70 | L33: Yes | M33: CEN/TC 287 | N33: Yes | O33: ISO/TC 211 | P33: =INDEX(Colours!$C$2:$C$14,MATCH(K33,Colours!$A$2:$A$14,0)) -> #N/A | T33: =3+TableStandards11[[#This Row],[Degree Centrality]]*17 -> 3
A34: 33 | B34: ISO 19126 | C34: Geographic information - Feature concept dictionaries and registers | D34: This document specifies a schema for feature concept dictionaries to be established and managed as registers. It does not specify schemas for feature catalogues or for the management of feature catalogues as registers. However, as feature catalogues are often derived from feature concept dictionaries, this document does specify a schema for a hierarchical register of feature concept dictionaries and feature catalogues. These registers are in accordance with ISO 19135‑1. | F34: https://www.iso.org/standard/78898.html | G34: 2009.11 | H34: 2021.06 | J34: 35.240.70 | L34: Yes | M34: CEN/TC 287 | N34: Yes | O34: ISO/TC 211 | P34: =INDEX(Colours!$C$2:$C$14,MATCH(K34,Colours!$A$2:$A$14,0)) -> #N/A | T34: =3+TableStandards11[[#This Row],[Degree Centrality]]*17 -> 3
A35: 34 | B35: ISO 19127 | C35: Geographic information -- Geodetic register | D35: This document defines the management and operations of the ISO geodetic register and identifies the data elements, in accordance with ISO 19111:2007 and the core schema within ISO 19135-1:2015, required within the geodetic register. | F35: https://www.iso.org/standard/67252.html | G35: 2005.06 | H35: 2019.02 | J35: 35.240.70; 07.040 | L35: No | M35: n/a | N35: Yes | O35: ISO/TC 211 | P35: =INDEX(Colours!$C$2:$C$14,MATCH(K35,Colours!$A$2:$A$14,0)) -> #N/A | T35: =3+TableStandards11[[#This Row],[Degree Centrality]]*17 -> 3
A36: 35 | B36: ISO 19128 | C36: Geographic information - Web map server interface | D36: This International Standard specifies the behaviour of a service that produces spatially referenced maps dynamically from geographic information. It specifies operations to retrieve a description of the maps offered by a server to retrieve a map, and to query a server about features displayed on a map. This International Standard is applicable to pictorial renderings of maps in a graphical format; it is not applicable to retrieval of actual feature data or coverage data values. | F36: https://www.iso.org/standard/32546.html | G36: 2008.01 | H36: 2008.01 | J36: 35.240.70 | L36: Yes | M36: CEN/TC 287 | N36: Yes | O36: ISO/TC 211 | P36: =INDEX(Colours!$C$2:$C$14,MATCH(K36,Colours!$A$2:$A$14,0)) -> #N/A | T36: =3+TableStandards11[[#This Row],[Degree Centrality]]*17 -> 3
... A41: 40 | B41: ISO 19134 | C41: Geographic information - Location-based services - Multimodal routing and navigation | D41: This International Standard specifies the data types and their associated operations for the implementation of multimodal location-based services for routing and navigation. It is designed to specify web services that may be made available to wireless devices through web-resident proxy applications, but is not limited to that environment. | F41: https://www.iso.org/standard/32552.html | G41: 2008.08 | H41: 2008.08 | J41: 35.240.70 | L41: Yes | M41: CEN/TC 287 | N41: Yes | O41: ISO/TC 211 | P41: =INDEX(Colours!$C$2:$C$14,MATCH(K41,Colours!$A$2:$A$14,0)) -> #N/A | T41: =3+TableStandards11[[#This Row],[Degree Centrality]]*17 -> 3
A42: 41 | B42: ISO 19135-1 | C42: Geographic information - Procedures for item registration - Part 1: Fundamentals | D42: This part of ISO 19135 specifies procedures to be followed in establishing, maintaining, and publishing registers of unique, unambiguous, and permanent identifiers and meanings that are assigned to items of geographic information. In order to accomplish this purpose, this part of ISO 19135 specifies elements that are necessary to manage the registration of these items. | F42: https://www.iso.org/standard/54721.html | G42: 2007.03 | H42: 2015.11 | I42: 03.2021 | J42: 35.240.70 | L42: Yes | M42: CEN/TC 287 | N42: Yes | O42: ISO/TC 211 | P42: =INDEX(Colours!$C$2:$C$14,MATCH(K42,Colours!$A$2:$A$14,0)) -> #N/A | T42: =3+TableStandards11[[#This Row],[Degree Centrality]]*17 -> 3
A43: 42 | B43: ISO 19136-1 | C43: Geographic information - Geography Markup Language (GML) - Part 1: Fundamentals | D43: The Geography Markup Language (GML) is an XML encoding in accordance with ISO 19118 for the transport and storage of geographic information modelled in accordance with the conceptual modelling framework used in the ISO 19100 series of International Standards and including both the spatial and non-spatial properties of geographic features. This document defines the XML Schema syntax, mechanisms and conventions that: — provide an open, vendor-neutral framework for the description of geospatial application schemas for the transport and storage of geographic information in XML; — allow profiles that support proper subsets of GML framework descriptive capabilities; — support the description of geospatial application schemas for specialized domains and information communities; — enable the creation and maintenance of linked geographic application schemas and datasets; — support the storage and transport of application schemas and datasets; — increase the ability of organizations to share geographic application schemas and the information they describe. Implementers can decide to store geographic application schemas and information in GML, or they can decide to convert from some other storage format on demand and use GML only for schema and data transport. NOTE If an ISO 19109 conformant application schema described in UML is used as the basis for the storage and transportation of geographic information, this document provides normative rules for the mapping of such an application schema to a GML application schema in XML Schema and, as such, to an XML encoding for data with a logical structure in accordance with the ISO 19109 conformant application schema. | F43: https://www.iso.org/standard/75676.html | G43: 2009.03 | H43: 2020.04 | J43: 35.240.70 | L43: Yes | M43: CEN/TC 287 | N43: Yes | O43: ISO/TC 211 | P43: =INDEX(Colours!$C$2:$C$14,MATCH(K43,Colours!$A$2:$A$14,0)) -> #N/A | T43: =3+TableStandards11[[#This Row],[Degree Centrality]]*17 -> 3
A44: 43 | B44: ISO 19136-2 | C44: Geographic information - Geography Markup Language (GML) - Part 2: Extended schemas and encoding rules | D44: The Geography Markup Language (GML) is an XML encoding in compliance with ISO 19118 for the transport and storage of geographic information modelled in accordance with the conceptual modelling framework used in the ISO 19100‑ series of International Standards and including both the spatial and non-spatial properties of geographic features. ISO 19136-2:2015 defines the XML Schema syntax, mechanisms and conventions that: -provide an open, vendor-neutral framework for the description of geospatial application schemas for the transport and storage of geographic information in XML; -allow profiles that support proper subsets of GML framework descriptive capabilities; -support the description of geospatial application schemas for specialized domains and information communities; -enable the creation and maintenance of linked geographic application schemas and datasets; -support the storage and transport of application schemas and datasets; -increase the ability of organizations to share geographic application schemas and the information they describe. Implementers may decide to store geographic application schemas and information in GML, or they may decide to convert from some other storage format on demand and use GML only for schema and data transport. ISO 19136-2:2015 builds on ISO 19136:2007 (GML 3.2), and extends it with additional schema components and requirements. NOTE If an ISO 19109 conformant application schema described in UML is used as the basis for the storage and transportation of geographic information, this part of ISO 19136 provides normative rules for the mapping of such an application schema to a GML application schema in XML Schema and, as such, to an XML encoding for data with a logical structure in accordance with the ISO 19109 conformant application schema. | F44: https://www.iso.org/standard/61585.html | G44: 2009.03 | H44: 2018.09 | J44: 35.240.70 | L44: Yes | M44: CEN/TC 287 | N44: Yes | O44: ISO/TC 211 | P44: =INDEX(Colours!$C$2:$C$14,MATCH(K44,Colours!$A$2:$A$14,0)) -> #N/A | T44: =3+TableStandards11[[#This Row],[Degree Centrality]]*17 -> 3
A45: 44 | B45: ISO 19137 | C45: Geographic information - Core profile of the spatial schema | D45: This International Standard defines a core profile of the spatial schema specified in ISO 19107 that specifies, in accordance with ISO 19106, a minimal set of geometric elements necessary for the efficient creation of application schemata. This International Standard supports many of the spatial data formats and description languages already developed and in broad use within several nations or liaison organizations. | F45: https://www.iso.org/standard/32555.html | G45: 2008.04 | H45: 2008.04 | J45: 35.240.70 | L45: Yes | M45: CEN/TC 287 | N45: Yes | O45: ISO/TC 211 | P45: =INDEX(Colours!$C$2:$C$14,MATCH(K45,Colours!$A$2:$A$14,0)) -> #N/A | T45: =3+TableStandards11[[#This Row],[Degree Centrality]]*17 -> 3
A46: 45 | B46: ISO 19141 | C46: Geographic information - Schema for moving features | D46: This International Standard defines a method to describe the geometry of a feature that moves as a rigid body. Such movement has the following characteristics. a) The feature moves within any domain composed of spatial objects as specified in ISO 19107. b) The feature may move along a planned route, but it may deviate from the planned route. c) Motion may be influenced by physical forces, such as orbital, gravitational, or inertial forces. d) Motion of a feature may influence or be influenced by other features, for example: 1) The moving feature might follow a predefined route (e.g. road), perhaps part of a network, and might change routes at known points (e.g. bus stops, waypoints). 2) Two or more moving features may be “pulled” together or pushed apart (e.g. an airplane will be refuelled during flight, a predator detects and tracks a prey, refugee groups join forces). 3) Two or more moving features may be constrained to maintain a given spatial relationship for some period (e.g. tractor and trailer, convoy). | F46: https://www.iso.org/standard/41445.html | G46: 2009.08 | H46: 2009.08 | J46: 35.240.70 | L46: Yes | M46: CEN/TC 287 | N46: Yes | O46: ISO/TC 211 | P46: =INDEX(Colours!$C$2:$C$14,MATCH(K46,Colours!$A$2:$A$14,0)) -> #N/A | T46: =3+TableStandards11[[#This Row],[Degree Centrality]]*17 -> 3
A47: 46 | B47: ISO 19142 | C47: Geographic information - Web Feature Service | D47: This International Standard specifies the behaviour of a web feature service that provides transactions on and access to geographic features in a manner independent of the underlying data store. It specifies discovery operations, query operations, locking operations, transaction operations and operations to manage stored parameterized query expressions. Discovery operations allow the service to be interrogated to determine its capabilities and to retrieve the application schema that defines the feature types that the service offers. Query operations allow features or values of feature properties to be retrieved from the underlying data store based upon constraints, defined by the client, on feature properties. Locking operations allow exclusive access to features for the purpose of modifying or deleting features. Transaction operations allow features to be created, changed, replaced and deleted from the underlying data store. Stored query operations allow clients to create, drop, list and describe parameterized query expressions that are stored by the server and can be repeatedly invoked using different parameter values. | F47: https://www.iso.org/standard/42136.html | G47: 2010.12 | H47: 2010.12 | J47: 35.240.70 | L47: Yes | M47: CEN/TC 287 | N47: Yes | O47: ISO/TC 211 | P47: =INDEX(Colours!$C$2:$C$14,MATCH(K47,Colours!$A$2:$A$14,0)) -> #N/A | T47: =3+TableStandards11[[#This Row],[Degree Centrality]]*17 -> 3
A48: 47 | B48: ISO 19143 | C48: Geographic information - Filter encoding | D48: This International Standard describes an XML and KVP encoding of a system neutral syntax for expressing projections, selection and sorting clauses collectively called a query expression. These components are modular and intended to be used together or individually by other standards which reference this International Standard. EXAMPLE 1 ISO 19142 makes use of some or all of these components. This International Standard defines an abstract component, named AbstractQueryExpression, from which other specifications can subclass concrete query elements to implement query operations. This International Standard also defines an additional abstract query component, named AbstractAdhocQueryExpresison, which is derived from AbstractQueryExpression and from which other specifications can subclass concrete query elements which follow the following query pattern: An abstract query element from which service specifications can subclass a concrete query element that implements a query operation that allows a client to specify a list of resource types, an optional projection clause, an optional selection clause, and an optional sorting clause to query a subset of resources that satisfy the selection clause. This pattern is referred to as an ad hoc query pattern since the server is not aware of the query until it is submitted for processing. This is in contrast to a stored query expression, which is stored and can be invoked by name or identifier. This International Standard also describes an XML and KVP encoding of a system-neutral representation of a select clause. The XML representation is easily validated, parsed and transformed into a server-specific language required to retrieve or modify object instances stored in some persistent object store. | F48: https://www.iso.org/standard/42137.html | G48: 2012.04 | H48: 2012.04 | J48: 35.240.70 | L48: Yes | M48: CEN/TC 287 | N48: Yes | O48: ISO/TC 211 | P48: =INDEX(Colours!$C$2:$C$14,MATCH(K48,Colours!$A$2:$A$14,0)) -> #N/A | T48: =3+TableStandards11[[#This Row],[Degree Centrality]]*17 -> 3
A49: 48 | B49: ISO 19144-1 | C49: Geographic information - Classification systems - Part 1: Classification system structure | D49: This part of ISO 19144 establishes the structure of a geographic information classification system, together with the mechanism for defining and registering the classifiers for such a system. It specifies the use of discrete coverages to represent the result of applying the classification system to a particular area and defines the technical structure of a register of classifiers in accordance with ISO 19135. The structure can be used to develop specific classification systems that address particular application areas, specified in other parts of ISO 19144. | F49: https://www.iso.org/standard/32562.html | G49: 2012.04 | H49: 2012.04 | I49: 08.2012 | J49: 35.240.70 | L49: Yes | M49: CEN/TC 287 | N49: Yes | O49: ISO/TC 211 | P49: =INDEX(Colours!$C$2:$C$14,MATCH(K49,Colours!$A$2:$A$14,0)) -> #N/A | T49: =3+TableStandards11[[#This Row],[Degree Centrality]]*17 -> 3
A50: 49 | B50: ISO 19144-2 | C50: Geographic information - Classification systems - Part 2: Land Cover Meta Language (LCML) | D50: This document specifies a Land Cover Meta Language (LCML) expressed as a UML metamodel that allows different Land Cover classification systems to be described based on physiognomic aspects. This document recognizes that a number of Land Cover classification systems exist. It provides a common reference structure for the comparison and integration of data for any generic Land Cover classification system, but does not intend to replace those classification systems. | F50: https://www.iso.org/standard/81259.html | G50: 2023.12 | H50: 2023.12 | J50: 35.240.70 | L50: Yes | M50: CEN/TC 287 | N50: Yes | O50: ISO/TC 211 | P50: =INDEX(Colours!$C$2:$C$14,MATCH(K50,Colours!$A$2:$A$14,0)) -> #N/A | T50: =3+TableStandards11[[#This Row],[Degree Centrality]]*17 -> 3
A51: 50 | B51: ISO 19145 | C51: Geographic information -- Registry of representations of geographic point location | D51: ISO 19145:2013 specifies the process for establishing, maintaining and publishing registers of representation of geographic point location in compliance with ISO 19135. It identifies and describes the information elements and the structure of a register of representations of geographic point location including the elements for the conversion of one representation to another. ISO 19145:2013 also specifies the XML implementation of the required XML extension to ISO/TS 19135-2, for the implementation of a register of geographic point location representations. | F51: https://www.iso.org/standard/32563.html | G51: 2013.02 | H51: 2013.02 | J51: 35.240.70 | L51: No | M51: n/a | N51: Yes | O51: ISO/TC 211 | P51: =INDEX(Colours!$C$2:$C$14,MATCH(K51,Colours!$A$2:$A$14,0)) -> #N/A | T51: =3+TableStandards11[[#This Row],[Degree Centrality]]*17 -> 3
A52: 51 | B52: ISO 19146 | C52: Geographic information - Cross-domain vocabularies | D52: This document establishes a methodology for cross-mapping vocabularies. It also specifies an implementation of ISO 19135-1:2015 for the purpose of registering cross-mapped vocabulary entries. Methodologies for the development of ontologies and taxonomies that relate to geographic information and geomatics are not within the scope of this document. | F52: https://www.iso.org/standard/72217.html | G52: 2010.11 | H52: 2018.06 | J52: 35.240.70 | L52: Yes | M52: CEN/TC 287 | N52: Yes | O52: ISO/TC 211 | P52: =INDEX(Colours!$C$2:$C$14,MATCH(K52,Colours!$A$2:$A$14,0)) -> #N/A | T52: =3+TableStandards11[[#This Row],[Degree Centrality]]*17 -> 3
A53: 52 | B53: ISO 19147 | C53: Geographic information -- Transfer Nodes | D53: ISO 19147:2015 specifies the data types and code lists associated with those types for the implementation of transfer nodes and their services in transport modelling and location based services. It includes the following: ? defines transfer nodes in a multimodal way so that the definition is general and valid for all types of transport means and modes; ? links transfer nodes to a location; ? focuses on the attributes defining the transfer node in relation to nodes in mode-specific networks; ? defines the attributes of transfer nodes that are relevant for travel planning and modelling of interoperable transport systems by transport planners; ? defines a set of services and facilities that may be related to transfer nodes and a way to provide information on accessibility, deviations and restrictions related to these services and facilities. ISO 19147:2015 is applicable for transport infrastructure owners and operators when defining and/or describing their transport infrastructure and for transport-related Service Providers when providing information to travellers and others. It is limited to the transport of persons and is also limited to the static getting-on and getting-off points. The main focus is on transfer nodes being part of public transport networks, that are located in road networks, but this International Standard is also applicable for transfer nodes in rail networks and in air and sea transport networks. | F53: https://www.iso.org/standard/44874.html | G53: 2015.06 | H53: 2015.06 | J53: 35.240.70 | L53: No | M53: n/a | N53: Yes | O53: ISO/TC 211 | P53: =INDEX(Colours!$C$2:$C$14,MATCH(K53,Colours!$A$2:$A$14,0)) -> #N/A | T53: =3+TableStandards11[[#This Row],[Degree Centrality]]*17 -> 3
A54: 53 | B54: ISO 19148 | C54: Geographic information - Linear referencing | D54: This document specifies a conceptual schema for locations relative to a one-dimensional object as measurement along (and optionally offset from) that object. It defines a description of the data and operations required to use and support linear referencing. This document is applicable to transportation, utilities, environmental protection, location-based services and other applications which define locations relative to linear objects. For ease of reading, most examples discussed in this document come from the transportation domain. | F54: https://www.iso.org/standard/75150.html | G54: 2012.02 | H54: 2021.04 | J54: 35.240.70 | L54: Yes | M54: CEN/TC 287 | N54: Yes | O54: ISO/TC 211 | P54: =INDEX(Colours!$C$2:$C$14,MATCH(K54,Colours!$A$2:$A$14,0)) -> #N/A | T54: =3+TableStandards11[[#This Row],[Degree Centrality]]*17 -> 3
A55: 54 | B55: ISO 19150-2 | C55: Geographic information -- Ontology -- Part 2: Rules for developing ontologies in the Web Ontology Language (OWL) | D55: ISO 19150-2:2015 defines rules and guidelines for the development of ontologies to support better the interoperability of geographic information over the Semantic Web. The Web Ontology Language (OWL) is the language adopted for ontologies. It defines the conversion of the UML static view modeling elements used in the ISO geographic information standards into OWL. It further defines conversion rules for describing application schemas based on the General Feature Model defined in ISO 19109 into OWL. It does not define semantics operators, rules for service ontologies, and does not develop any ontology. | F55: https://www.iso.org/standard/57466.html | G55: 2015.07 | H55: 2015.07 | I55: 01.2019 | J55: 35.240.70 | L55: No | M55: n/a | N55: Yes | O55: ISO/TC 211 | P55: =INDEX(Colours!$C$2:$C$14,MATCH(K55,Colours!$A$2:$A$14,0)) -> #N/A | T55: =3+TableStandards11[[#This Row],[Degree Centrality]]*17 -> 3
A56: 55 | B56: ISO 19150-4 | C56: Geographic information -- Ontology -- Part 4: Service ontology | D56: This document sets a framework for geographic information service ontology and the description of geographic information Web services in Web Ontology Language (OWL). OWL is the language adopted for ontologies. This document makes use of service metadata (ISO 19115-1) and service definitions (ISO 19119) whenever appropriate. This document does not define semantics operators, rules for ontologies, and does not develop any application ontology. In relation to ISO 19101-1:2014, 6.2, this document defines and formalizes the following purpose of the ISO geographic information reference model: - geographic information service components and their behaviour for data processing purposes over the Web, and - OWL ontologies to cast ISO/TC 211 standards to benefit from and support the Semantic Web. In relation to ISO 19101-1:2014, 8.3, this document addresses the Meta:Service foundation of the ISO geographic information reference model. | F56: https://www.iso.org/standard/72177.html | G56: 2019.05 | H56: 2019.05 | J56: 35.240.70 | L56: No | M56: n/a | N56: Yes | O56: ISO/TC 211 | P56: =INDEX(Colours!$C$2:$C$14,MATCH(K56,Colours!$A$2:$A$14,0)) -> #N/A | T56: =3+TableStandards11[[#This Row],[Degree Centrality]]*17 -> 3
A57: 56 | B57: ISO 19150-6 | C57: Geographic information - Ontology - Part 6: Service ontology register | D57: This document establishes a standard registration and maintenance mechanism for the registration of ISO 19150-4-conformant geographic information service ontologies. This document makes use of ISO 19135-1 whenever appropriate. This document does not define semantics operators or rules for ontologies, and does not develop any application ontology. In relation to ISO 19101-1:2014, 6.2, this document defines and formalizes the following purposes of the ISO geographic information reference model: — geographic information service components and their behaviour for data processing purposes over the Web; and — OWL ontologies to cast ISO/TC 211 International Standards to benefit from and support the Semantic Web. In relation to ISO 19101-1:2014, 8.3, this document addresses the Application:Procedural foundation of the ISO geographic information reference model. | F57: https://www.iso.org/standard/80867.html | G57: 2023.07 | H57: 2023.07 | J57: 35.240.70 | L57: Yes | M57: CEN/TC 287 | N57: Yes | O57: ISO/TC 211 | P57: =INDEX(Colours!$C$2:$C$14,MATCH(K57,Colours!$A$2:$A$14,0)) -> #N/A | T57: =3+TableStandards11[[#This Row],[Degree Centrality]]*17 -> 3
A58: 57 | B58: ISO 19152-1 | C58: Geographic information - Land Administration Domain Model (LADM) - Part 1: Generic conceptual model | D58: This document: — defines a reference Land Administration Domain Model (LADM) covering basic information-related components of land administration/georegulation; — provides an abstract, conceptual model with packages related to: — parties (people and organizations), — basic administrative units, rights, responsibilities and restrictions (RRRs), — spatial units, — a generic conceptual model (sources and versioned object); — provides terminology for land administration/georegulation, based on various national and international systems, that is as simple as possible in order to be useful in practice. The terminology allows a shared description of different formal or informal practices and procedures in various jurisdictions; — provides a content model independent of encoding, allowing for the support of various encodings; — provides a basis for national and regional profiles; — enables the combining of land administration/georegulation information from different sources in a coherent manner. The following are outside the scope of this document: — interference with (national) land administration/georegulation laws with potentially legal implications due to the possibility of describing different types of systems but in the same notation; — construction of external databases with party data, address data, land cover data, physical utility network data, archive data and taxation data. However, the LADM provides stereotype classes for these data sets to indicate which data set elements the LADM expects from these external sources, if available. This document provides the concepts and basic structure for standardization in the land administration/georegulation domain. It defines a general schema that permits regulatory information to be described. It also allows for the relationship to multiple parties and groups to be expressed together with a referencing structure so that sourcing of all information systems can be maintained. This document establishes the common elements and basic schema upon which more detailed schema can be established. | F58: https://www.iso.org/standard/81263.html | G58: 2012.11 | H58: 2024.01 | J58: 35.240.70 | L58: Yes | M58: CEN/TC 287 | N58: Yes | O58: ISO/TC 211 | P58: =INDEX(Colours!$C$2:$C$14,MATCH(K58,Colours!$A$2:$A$14,0)) -> #N/A | T58: =3+TableStandards11[[#This Row],[Degree Centrality]]*17 -> 3
A59: 58 | B59: ISO 19152-2 | C59: Geographic information - Land Administration Domain Model (LADM) - Part 2: Land registration | D59: This document: — defines a reference land administration domain model (LADM) covering basic information-related components of land registration (including elements above and below the surface of the Earth); — provides an abstract, conceptual model with three packages and one sub-package related to: — parties (people and organizations); — basic administrative units, rights, responsibilities and restrictions (RRRs); — spatial units (parcels, and the legal space of buildings and utility networks and other geometry) with a sub-package on surveying and spatial representation (geometry and topology); — provides terminology for land administration (LA), based on various national and international systems, that is as simple as possible in order to be useful in practice. The terminology allows a shared description of different formal or informal practices and procedures in various jurisdictions; — provides a platform for comparison and monitoring that is based on indicators; — provides a basis for national and regional profiles; and — enables the combination of land administration information from different sources in a coherent manner. The following is outside the scope of this document: — interference with (national) land administration laws with potentially legal implications; and — construction of external databases with party data, address data, land cover data, physical utility network data, archive data and taxation data. However, the LADM provides stereotype classes for these data sets to indicate which data set elements the LADM expects from these external sources, if available. This document provides the concepts and the detailed structure for standardization in the land administration domain. | E59: BIM + GIS | F59: https://www.iso.org/standard/81264.html | G59: 2012.11 | H59: 2025.06 | J59: 35.240.70 | L59: Yes | M59: CEN/TC 287 | N59: Yes | O59: ISO/TC 211 | P59: =INDEX(Colours!$C$2:$C$14,MATCH(K59,Colours!$A$2:$A$14,0)) -> #N/A | T59: =3+TableStandards11[[#This Row],[Degree Centrality]]*17 -> 3
A60: 59 | B60: ISO 19152-3 | C60: Geographic information - Land Administration Domain Model (LADM) - Part 3: Marine georegulation | D60: This document specifies the concepts and structure for standardization for georegulation in the marine space. This document addresses the information structures related to management of legal spaces (such as the international maritime limits and boundaries, marine living and non-living resources management areas, marine conservation areas, etc.) and their related rights and obligations. This document establishes the common elements and basic schema to structure marine georegulation information system. It builds upon the common components defined in ISO 19152-1. | F60: https://www.iso.org/standard/81265.html | G60: 2012.11 | H60: 2024.07 | J60: 35.240.70 | L60: Yes | M60: CEN/TC 287 | N60: Yes | O60: ISO/TC 211 | P60: =INDEX(Colours!$C$2:$C$14,MATCH(K60,Colours!$A$2:$A$14,0)) -> #N/A | T60: =3+TableStandards11[[#This Row],[Degree Centrality]]*17 -> 3
A61: 60 | B61: ISO 19152-4 | C61: Geographic information — Land Administration Domain Model (LADM) — Part 4: Valuation information | D61: This document: a) builds on the models established in ISO 19152-1 and ISO 19152-2 to cover the valuation aspect of the Land Administration Domain Model (LADM); b) provides an abstract conceptual model covering: 1) values (assessed values, valuation procedures, mass valuation); 2) transaction prices; 3) sales statistics; 4) valuation units (parcel (legal space parcel), building, condominium unit, valuation unit group). c) provides terminology for the valuation component of land administration/georegulation, based on various national and international systems, that is as simple as possible in order to be useful in practice. The terminology allows a shared description of different formal or informal practices and procedures in various jurisdictions; d) specifies a content model independent of encoding that can be employed as a basis for local, national and regional profiles for valuation processes; and e) enables the combining of valuation information from different sources in a coherent manner. NOTE This document does not interfere with national property valuation-related regulations with potential legal implications. | F61: https://www.iso.org/standard/81266.html | G61: 2012.11 | H61: 2025.07 | J61: 35.240.70 | L61: Yes | M61: CEN/TC 287 | N61: Yes | O61: ISO/TC 211 | P61: =INDEX(Colours!$C$2:$C$14,MATCH(K61,Colours!$A$2:$A$14,0)) -> #N/A | T61: =3+TableStandards11[[#This Row],[Degree Centrality]]*17 -> 3
A62: 61 | B62: ISO 19152-5 | C62: Geographic information — Land Administration Domain Model (LADM) | D62: This document: — specifies a reference land administration domain model (LADM) covering basic information-related components of spatial plan information on land/water and elements below/on/above the surface of the Earth with 2D/3D/4D (3D + time) geometric representation; — provides an abstract, conceptual model with packages related to: — plan unit, i.e. the smallest homogenous area/space (2D/3D/4D) with assigned function/purpose, e.g. office, education, retail; — plan block, i.e. a set of neighbouring plan units decided on by planning authorities, e.g. high-density residential area, nature area, heavy industry area; — plan group unit, i.e. areas corresponding to the higher planning levels; — plan group, i.e. hierarchy in spatial plans consisting of multiple plan blocks, e.g.: — continent/regional-wide (e.g. European regions), — country-wide (e.g. Indonesia, the Netherlands), — island, — state or region province, — municipality or city, and — urban or rural; — permit, i.e. something that is granted to a party which gives the party permission to undertake an activity which would otherwise be restricted; — defines terminology for spatial plan information as part of land administration, based on various national and international systems, that is as simple as possible in order to be useful in practice. The terminology allows a shared description of different formal or informal practices and procedures in various jurisdictions; — provides a platform for comparison and monitoring of spatial planning information based on Sustainable Development Goal (SDG) indicators; — provides an approach to modelling the integration of spatial plan information (outputs of spatial plans) into land administration; — provides a basis for national and regional profiles; — enables the combining of land-use planning and land development planning in land administration information from different sources in a coherent manner; — allows for the relationship to multiple parties and groups to be expressed together with a referencing structure so that the sourcing of all information systems can be maintained. It reuses core LADM classes so that sourcing of all information systems can be maintained; — establishes the common elements and basic schema for spatial plan information upon which a more detailed schema can be established. NOTE This document does not interfere with (national) and sub-national spatial planning laws. | F62: https://www.iso.org/standard/81267.html | G62: 2012.11 | H62: 2025.08 | J62: 35.240.70 | L62: Yes | M62: CEN/TC 287 | N62: Yes | O62: ISO/TC 211 | P62: =INDEX(Colours!$C$2:$C$14,MATCH(K62,Colours!$A$2:$A$14,0)) -> #N/A | T62: =3+TableStandards11[[#This Row],[Degree Centrality]]*17 -> 3
A63: 62 | B63: ISO 19154 | C63: Geographic information -- Ubiquitous public access -- Reference model | D63: ISO 19154:2014 defines a reference model for ubiquitous public access (UPA) to geographic information. This reference model uses standard concepts from both the Open distributed processing — Reference model (RM-ODP) in ISO/IEC 10746-1 and ISO 19101. The reference model specified in this International Standard defines the following: — conceptual models for ubiquitous public access (UPA) to geographic information; — a reference model and framework to support current and future specification development in this area; — the semantics of information and processing within systems and services for the UPA of geographic information; — the architectural relationship between this International Standard and other ISO geographic information standards. This International Standard is applicable to location-based services (LBS), ubiquitous computing environments, linked open data, and other domains that require a seamless public access to geographic information. Although structured in the context of information technology and information technology standards, this International Standard is independent of any application development method or technology implementation approach. | F63: https://www.iso.org/standard/32572.html | G63: 2014.11 | H63: 2014.11 | J63: 35.240.70 | L63: No | M63: n/a | N63: Yes | O63: ISO/TC 211 | P63: =INDEX(Colours!$C$2:$C$14,MATCH(K63,Colours!$A$2:$A$14,0)) -> #N/A | T63: =3+TableStandards11[[#This Row],[Degree Centrality]]*17 -> 3
A64: 63 | B64: ISO 19155 | C64: Geographic information -- Place Identifier (PI) architecture | D64: ISO 19155:2012 specifies an architecture that defines a reference model with an encoding method for an identifier of a place. The concept of "place" within ISO 19155:2012 includes "places" not only in the real world but also those in the virtual world. These "places" are identified using either coordinate identifiers, geographic identifiers, or virtual world identifiers such as URI. In ISO 19155:2012, an identifier of a place is referred to as a Place Identifier (PI). The reference model defines a mechanism to match multiple Place Identifiers to the same place. In addition, a data structure and set of service interfaces are also defined in this reference model. ISO 19155:2012 is applicable to location based services, emergency management services and other application domains that require a common architecture, across specific domains, for the representation of place descriptions using coordinate, geographic, or virtual world identifiers. | F64: https://www.iso.org/standard/32573.html | G64: 2012.11 | H64: 2012.11 | J64: 35.240.70 | L64: No | M64: n/a | N64: Yes | O64: ISO/TC 211 | P64: =INDEX(Colours!$C$2:$C$14,MATCH(K64,Colours!$A$2:$A$14,0)) -> #N/A | T64: =3+TableStandards11[[#This Row],[Degree Centrality]]*17 -> 3
A65: 64 | B65: ISO 19155-2 | C65: Geographic information -- Place Identifier (PI) architecture -- Part 2: Place Identifier (PI) linking | D65: ISO 19155-2:2017 defines the following three mechanisms for linking Place Identifiers (PIs) (see ISO 19155) to features or objects existing in other encodings: - Id attribute of a GML object (gml:id) as defined in ISO 19136; - Universally Unique Identifier (UUID) as defined in IETF RFC 4122; - Uniform Resource Locator (URL) as defined in IETF RFC 1738. These PI linking mechanisms are enabled using xlink:href as defined in W3C XML Linking Language (XLink). While the identifiers of these features or objects can sometimes identify a place, within the scope of this document, the identifiers of features or objects existing in other encoding domains are referred to conceptually as other identifiers. This document further defines that when PIs are encoded, as specified in ISO 19155, using the Geography Markup Language (GML) (ISO 19136), they are linked using gml:id to other GML encoded features. The details of encoding GML instances using gml:id are specified in a normative annex. Additional normative annexes define encodings for linking Place Identifiers to other identifiers using UUID and URL and present examples for their use. ISO 19155-2:2017 is applicable to location-based services, linked open data, robotic assisted services and other application domains that require a relationship between PIs and objects in either the real or virtual world. ISO 19155-2:2017 is not about creating a registry of Place Identifiers linked to specific features or objects, and support of linking mechanisms other than gml:id, UUID, and URL is out of the scope of this document. | F65: https://www.iso.org/standard/63593.html | G65: 2017.08 | H65: 2017.08 | J65: 35.240.70 | L65: No | M65: n/a | N65: Yes | O65: ISO/TC 211 | P65: =INDEX(Colours!$C$2:$C$14,MATCH(K65,Colours!$A$2:$A$14,0)) -> #N/A | T65: =3+TableStandards11[[#This Row],[Degree Centrality]]*17 -> 3
A66: 65 | B66: ISO 19156 | C66: Geographic information - Observations, measurements and samples | D66: This document defines a conceptual schema for observations, for features involved in the observation process, and for features involved in sampling when making observations. These provide models for the exchange of information describing observation acts and their results, both within and between different scientific and technical communities. Observations commonly involve sampling of an ultimate feature-of-interest. This document defines a common set of sample types according to their spatial, material (for ex situ observations) or statistical nature. The schema includes relationships between sample features (sub-sampling, derived samples). This document concerns only externally visible interfaces and places no restriction on the underlying implementations other than what is needed to satisfy the interface specifications in the actual situation. | F66: https://www.iso.org/standard/82463.html | G66: 2013.07 | H66: 2023.05 | J66: 35.240.70 | L66: Yes | M66: CEN/TC 287 | N66: Yes | O66: ISO/TC 211 | P66: =INDEX(Colours!$C$2:$C$14,MATCH(K66,Colours!$A$2:$A$14,0)) -> #N/A | T66: =3+TableStandards11[[#This Row],[Degree Centrality]]*17 -> 3
A67: 66 | B67: ISO 19157-1 | C67: Geographic information - Data quality - Part 1: General requirements | D67: This document establishes the principles for describing the quality of geographic data. It: — defines a well-considered system of components for describing data quality; — defines the process for defining additional, domain-specific components for describing data quality; — specifies components and the content structure of data quality measures; — describes general procedures for evaluating the quality of geographic data; — establishes principles for reporting data quality. This document is applicable to data producers providing quality information to describe and assess how well a dataset conforms to its product specification and to data users attempting to determine whether or not specific geographic data are of sufficient quality for their particular application. This document does not attempt to define minimum acceptable levels of quality for geographic data. Such information is usually present as a requirement in a data product specification, defined in accordance with ISO 19131, for example. | F67: https://www.iso.org/standard/78900.html | G67: 2013.12 | H67: 2023.04 | J67: 35.240.70 | L67: Yes | M67: CEN/TC 287 | N67: Yes | O67: ISO/TC 211 | P67: =INDEX(Colours!$C$2:$C$14,MATCH(K67,Colours!$A$2:$A$14,0)) -> #N/A | T67: =3+TableStandards11[[#This Row],[Degree Centrality]]*17 -> 3
A68: 67 | B68: ISO 19161-1 | C68: Geographic information -- Geodetic references -- Part 1: International terrestrial reference system (ITRS) | D68: This document provides the basic information and the requirements related to the International Terrestrial Reference System (ITRS), its definition, its realizations and how to access and use these realizations. This document: - describes ITRS following the definitions and terminology adopted by the International Union of Geodesy and Geophysics (IUGG), the International Association of Geodesy (IAG) and the International Astronomical Union (IAU); - describes different categories of ITRS realizations: its primary realization, labelled the International Terrestrial Reference Frame (ITRF), other existing realizations of reference systems that are mathematically derived from the ITRS, and realizations that are aligned to the ITRF, such as GNSS-specific reference frames; - categorizes procedures for realizing the ITRS. | F68: https://www.iso.org/standard/70655.html | G68: 2020.01 | H68: 2020.01 | J68: 35.240.70; 07.040 | L68: No | M68: n/a | N68: Yes | O68: ISO/TC 211 | P68: =INDEX(Colours!$C$2:$C$14,MATCH(K68,Colours!$A$2:$A$14,0)) -> #N/A | T68: =3+TableStandards11[[#This Row],[Degree Centrality]]*17 -> 3
A69: 68 | B69: ISO 19162 | C69: Geographic information -- Well-known text representation of coordinate reference systems | D69: This document defines the structure and content of a text string implementation of the abstract model for coordinate reference systems described in ISO 19111. The string defines frequently needed types of coordinate reference systems and coordinate operations in a self-contained form that is easily readable by machines and by humans. The essence is its simplicity; as a consequence there are some constraints upon the more open content allowed in ISO 19111. To retain simplicity in the well-known text (WKT) description of coordinate reference systems and coordinate operations, the scope of this document excludes parameter grouping and pass-through coordinate operations. The text string provides a means for humans and machines to correctly and unambiguously interpret and utilise a coordinate reference system definition with look-ups or cross references only to define coordinate operation mathematics. A WKT string is not suitable for the storage of definitions of coordinate reference systems or coordinate operations because it omits metadata about the source of the data and may omit metadata about the applicability of the information. | F69: https://www.iso.org/standard/76496.html | G69: 2015.08 | H69: 2019.07 | I69: 08.2023 | J69: 35.240.70 | L69: No | M69: n/a | N69: Yes | O69: ISO/TC 211 | P69: =INDEX(Colours!$C$2:$C$14,MATCH(K69,Colours!$A$2:$A$14,0)) -> #N/A | T69: =3+TableStandards11[[#This Row],[Degree Centrality]]*17 -> 3
A70: 69 | B70: ISO 19164 | C70: Geographic information - Indoor feature model | D70: This document specifies a core semantic classification system of essential indoor features to describe indoor environments required commonly in various location-based indoor applications of buildings. The scope includes the following: — semantic description of indoor features and their attributes; — feature association between indoor features. The semantic classification system in this document is compatible with the building model defined in existing related standards. Geometric and topological descriptions of indoor features are not considered in this document. This document does not apply to other architectural structures, such as tunnels. | F70: https://www.iso.org/standard/83153.html | G70: 2024.08 | H70: 2024.08 | J70: 35.240.70 | L70: Yes | M70: CEN/TC 287 | N70: Yes | O70: ISO/TC 211 | P70: =INDEX(Colours!$C$2:$C$14,MATCH(K70,Colours!$A$2:$A$14,0)) -> #N/A | T70: =3+TableStandards11[[#This Row],[Degree Centrality]]*17 -> 3
A71: 70 | B71: ISO 19165-1 | C71: Geographic information -- Preservation of digital data and metadata -- Part 1: Fundamentals | D71: ISO 19165-1:2018 defines a preservation metadata extension of ISO 19115-1. ISO 19165-1:2018 defines the requirements for the long-term preservation of digital geospatial data. These data also include metadata, representation information, provenance, context and any other content items that capture the knowledge that are necessary to fully understand and reuse the archived data. This document also refers to characteristics of data formats that are useful for the purpose of archiving. Geospatial data are preserved as a geospatial information package (IP). This document defines the requirements of the geospatial archival IP and details of the geospatial submission and the dissemination IPs. A geospatial archival IP is fully self-describing and allows a future reconstruction of the dataset without external documentation. The functional requirements for a preservation archive are defined in Annex D. ISO 19165-1:2018 complements standards developed by ISO/TC 211 as well as other ISO standards such as ISO 14721. | F71: https://www.iso.org/standard/67325.html | G71: 2018.05 | H71: 2018.05 | J71: 35.240.70 | L71: No | M71: n/a | N71: Yes | O71: ISO/TC 211 | P71: =INDEX(Colours!$C$2:$C$14,MATCH(K71,Colours!$A$2:$A$14,0)) -> #N/A | T71: =3+TableStandards11[[#This Row],[Degree Centrality]]*17 -> 3
A72: 71 | B72: ISO 19165-2 | C72: Geographic information -- Preservation of digital data and metadata -- Part 2: Content specifications for Earth observation data and derived digital products | D72: This document aims to extend the long-term preservation of digital geospatial data to provide details about content describing the provenance and context specific to data from missions that observe the Earth using spaceborne, airborne or in situ instruments. | F72: https://www.iso.org/standard/73810.html | G72: 2020.07 | H72: 2020.07 | J72: 35.240.70 | L72: No | M72: n/a | N72: Yes | O72: ISO/TC 211 | P72: =INDEX(Colours!$C$2:$C$14,MATCH(K72,Colours!$A$2:$A$14,0)) -> #N/A | T72: =3+TableStandards11[[#This Row],[Degree Centrality]]*17 -> 3
A73: 72 | B73: ISO 19168-1 | C73: Geographic information - Geospatial API for features - Part 1: Core | D73: This document specifies the behaviour of Web APIs that provide access to features in a dataset independently of the underlying data store. This document defines discovery and query operations. Discovery operations enable clients to interrogate the API, including the API definition and metadata about the feature collections provided by the API, to determine the capabilities of the API and retrieve information about available distributions of the dataset. Query operations enable clients to retrieve features from the underlying data store based upon simple selection criteria, defined by the client. | F73: https://www.iso.org/standard/86508.html | G73: 2021.06 | H73: 2025.01 | J73: 35.240.70 | L73: Yes | M73: CEN/TC 287 | N73: Yes | O73: ISO/TC 211 | P73: =INDEX(Colours!$C$2:$C$14,MATCH(K73,Colours!$A$2:$A$14,0)) -> #N/A | T73: =3+TableStandards11[[#This Row],[Degree Centrality]]*17 -> 3
A74: 73 | B74: ISO 19168-2 | C74: Geographic information - Geospatial API for features - Part 2: Coordinate Reference Systems by Reference | D74: This document specifies an extension to the Geospatial API for Features — Part 1: Core standard that defines the behaviour of a server that supports the ability to present geometry valued properties in a response document in one from a list of supported Coordinates Reference Systems (CRS). Each supported CRS is specified by reference using a uniform resource identifier (URI). This document specifies: — how, for each offered feature collection, a server advertises the list of supported CRS identifiers; — how the coordinates of geometry valued feature properties can be accessed in one of the supported CRSs; — how features can be accessed from the server using a bounding box specified in one of the supported CRSs; and — how a server can declare the CRS used to present feature resources. | F74: https://www.iso.org/standard/82464.html | G74: 2022.10 | H74: 2022.10 | J74: 35.240.70 | L74: Yes | M74: CEN/TC 287 | N74: Yes | O74: ISO/TC 211 | P74: =INDEX(Colours!$C$2:$C$14,MATCH(K74,Colours!$A$2:$A$14,0)) -> #N/A | T74: =3+TableStandards11[[#This Row],[Degree Centrality]]*17 -> 3
A75: 74 | B75: ISO 19170-1 | C75: Geographic information — Discrete Global Grid Systems Specifications — Part 1: Core Reference System and Operations, and Equal Area Earth Reference System | D75: This document supports the definition of: - A Discrete Global Grid Systems (DGGS) core comprising: - an RS using zonal identifiers with structured geometry, and - functions providing import, export and topological query, - Common spatio-temporal classes for geometry, topology, RS using zonal identifiers, zonal identifiers and zones, based on ISO 19111 CRS. The spatio-temporal scope is constrained to: - spatial elements that are invariant through all time, and - temporal elements that are invariant across all space. - Equal-Area Earth Reference Systems (EAERSs) for Equal-Area Earth DGGS. | F75: https://www.iso.org/standard/32588.html | G75: 2021.05 | H75: 2021.05 | J75: 35.240.70 | L75: No | M75: n/a | N75: Yes | O75: ISO/TC 211 | P75: =INDEX(Colours!$C$2:$C$14,MATCH(K75,Colours!$A$2:$A$14,0)) -> #N/A | T75: =3+TableStandards11[[#This Row],[Degree Centrality]]*17 -> 3
A76: 75 | B76: ISO 21597-1 | C76: Information container for linked document delivery -- Exchange specification -- Part 1: Container | D76: This document defines an open and stable container format to exchange files of a heterogeneous nature to deliver, store and archive documents that describe an asset throughout its entire lifecycle. It is suitable for all parties dealing with information concerning the built environment, where there is a need to exchange multiple documents and their interrelationships, either as part of the process or as contracted deliverables. The format is intended to use resources either included in the container (such as documents) or referenced remotely (such as web resources). A key feature is that the container can include information about the relationships between the documents. Relevant use-cases reflect the need for information exchange during the entire life cycle of any built asset and can include, but are not limited to, the handover of 1. a published bidding package, 2. required project deliverables at a specific project stage (e.g. when proposing different design scenarios), 3. shared information as background or for further development, 4. published approval packages, or 5. information about versions between partners to provide a means to reference particular states of the information and track changes. | E76: BIM + GIS | F76: https://www.iso.org/standard/74389.html | G76: 2020.04 | H76: 2020.04 | J76: 35.240.67; 91.010.01 | L76: No | M76: n/a | N76: Yes | O76: ISO/TC 59/SC 13 | P76: =INDEX(Colours!$C$2:$C$14,MATCH(K76,Colours!$A$2:$A$14,0)) -> #N/A | T76: =3+TableStandards11[[#This Row],[Degree Centrality]]*17 -> 3
A77: 76 | B77: ISO 37104 | C77: Sustainable cities and communities -- Transforming our cities -- Guidance for practical local implementation of ISO 37101 | D77: This document provides guidance on how to implement and maintain a management system for sustainable development based on ISO 37101 principles, specifically in the context of cities, but applicable to other forms of settlement. This document: — provides guidance for practical implementation of a management system for sustainable development in cities and other settlements, based on ISO 37101; — establishes a methodological framework for the systematic evaluation of the sustainable development schemes and achievements in the city or other settlements, based on the cross-analysis of the six purposes of sustainability and the 12 areas of action of ISO 37101; — illustrates how other International Standards can be used to support successful implementation of ISO 37101, including, in particular, ISO 37120 (which recommends a suite of city indicators mapped against the six purposes of ISO 37101) and ISO 37106 (which provides practical guidance on how to implement joined-up delivery and innovation across organizational boundaries within the city or settlement). This document is intended for organizing bodies, decision-makers, executive officers and managers in cities – usually, in the first instance, the relevant local governments. This document is intended to help cities become more sustainable, through the implementation at city level of strategies, programmes, projects, plans and services referred to in this document as schemes (see Note 1 and 3.7). It also provides a platform to help demonstrate and communicate their commitment, progress and achievements. NOTE 1 In this document, the term “scheme” is used to cover strategies, programs, projects, plans and services. NOTE 2 The guidance can be used for city-wide strategies, but also, potentially, for some sector-specific schemes at a city level. This document is applicable to a range of types and scales of communities: cities, towns, villages or other kinds of human settlements with defined boundaries. NOTE 3 In this document, the term “city” refers to cities, towns, villages or other kind of human settlements with defined territorial boundaries and administrative authority. The approach is in line with other deliverables developed by ISO/TC 268 and ISO/TC 268/SC 1 that could be identified as the ISO 371XX family. This document can be used in whole or in part to establish or systematically improve a community-based sustainable development management system. It provides additional operational instructions and examples regarding ways of meeting the 37101 requirements. | E77: BIM + GIS | F77: https://www.iso.org/standard/69895.html | G77: 2019.04 | H77: 2019.04 | J77: 13.020.20 | L77: No | M77: n/a | N77: Yes | O77: ISO/TC 268 | P77: =INDEX(Colours!$C$2:$C$14,MATCH(K77,Colours!$A$2:$A$14,0)) -> #N/A | T77: =3+TableStandards11[[#This Row],[Degree Centrality]]*17 -> 3
A78: 77 | B78: ISO 37108 | C78: Sustainable cities and communities — Business districts — Guidance for practical local implementation of ISO 37101 | D78: This document provides guidance on how to implement and maintain a management system for sustainable development in cities and communities according to ISO 37101 in the context of a business district. This document defines the business district and presents the procedure to follow to establish and implement a sustainable development policy and continuous improvement initiative for the duration of the business district’s lifecycle. This document identifies the general principles of sustainable development management and how to apply them in a business district, within both new developments and in operations to upgrade and renovate existing ones. It relates to all interested parties and all stages of the business district lifecycle, including planning, design, construction, operation, maintenance and renovation. This document is intended to serve as the basis for assessing and improving economic, social, environmental, infrastructure, and governance outcomes and to provide guidance for conducting comparative analyses for business districts. | E78: BIM + GIS | F78: https://www.iso.org/standard/62067.html | G78: 2022.09 | H78: 2022.09 | J78: 13.020.20 | L78: No | M78: n/a | N78: Yes | O78: ISO/TC 268 | P78: =INDEX(Colours!$C$2:$C$14,MATCH(K78,Colours!$A$2:$A$14,0)) -> #N/A | T78: =3+TableStandards11[[#This Row],[Degree Centrality]]*17 -> 3
A79: 78 | B79: ISO 37166 | C79: Smart community infrastructures — Urban data integration framework for smart city planning (SCP) | D79: This document establishes a data framework that involves possible multi-source common data through standardized data integration and sharing mechanisms. It includes recommendations for: — precision, dimensions of the data, data collection, updates and storing mechanisms; — a data model for data integration, data standardization and data fusion approaches for heterogeneous smart city infrastructure data; — a data security level and sharable attributes for all involved data, principles on data sharing or exchange. This document focuses on the integration and application of heterogeneous data from urban infrastructure systems, such as water, transport, energy, drainage and waste, so as to support smart city planning (SCP). It contains case studies, in Annex A, of various smart city projects. | E79: BIM + GIS | F79: https://www.iso.org/standard/69252.html | G79: 2022.02 | H79: 2022.02 | J79: 13.020.20 | L79: No | M79: n/a | N79: Yes | O79: ISO/TC 268/SC 1 | P79: =INDEX(Colours!$C$2:$C$14,MATCH(K79,Colours!$A$2:$A$14,0)) -> #N/A | T79: =3+TableStandards11[[#This Row],[Degree Centrality]]*17 -> 3
A80: 79 | B80: ISO 37175 | C80: Smart community infrastructures — Operation and maintenance of utility tunnels | D80: This document specifies requirements and recommendations for the operation and maintenance of utility tunnels in terms of application, safety, energy conservation, advanced technology and economic rationality. This document aims to ensure the sustainable development as well as safe and stable operation and maintenance of utility tunnels. This document is applicable to communities of any size that have utility tunnels. | E80: BIM + GIS | F80: https://www.iso.org/standard/82837.html | G80: 2024.08 | H80: 2024.08 | J80: 13.020.20 | L80: No | M80: n/a | N80: Yes | O80: ISO/TC 268/SC 1 | P80: =INDEX(Colours!$C$2:$C$14,MATCH(K80,Colours!$A$2:$A$14,0)) -> #N/A | T80: =3+TableStandards11[[#This Row],[Degree Centrality]]*17 -> 3
A81: 80 | B81: ISO/CD TS 19144-4 (NOT PUBLIC) | C81: Geographic information — Classification systems Part 4: Registration and implementation aspects | D81: n/a | F81: https://www.iso.org/standard/87033.html | G81: 2026.xx | H81: 2026.xx | J81: n/a | L81: No | M81: n/a | N81: Yes | O81: ISO/TC 211 | P81: =INDEX(Colours!$C$2:$C$14,MATCH(K81,Colours!$A$2:$A$14,0)) -> #N/A | T81: =3+TableStandards11[[#This Row],[Degree Centrality]]*17 -> 3
A82: 81 | B82: ISO/CD 23143-1 | C82: Information exchange between BIM and GIS — Part 1: Core principles and specifications | D82: This document establishes the core principles and specifications for enabling structured and semantically consistent information exchange between BIM and GIS. It provides a comprehensive framework for understanding, planning, and implementing information exchanges that span both the built asset domain and the geographic systems domain. This document provides a conceptual framework, built around eight perspectives on BIM-GIS information exchange: life cycle, process, product, data, exchange, actor, geospatial, and standards perspectives, how they shape, dictate, or constrain the structuring and execution of information exchanges, and the relationships between them and their application to specific use cases. It also addresses the following key elements: — Requirements definition and hierarchy for BIM-GIS information exchanges — Services enabling exchange and integration, transformation, query and analysis, and visualization and communication — Functions supporting spatial registration and georeferencing, data harmonization, linking, analytical operations, and workflow management — Resources including data and information types, formats, and their characteristics — Repositories for centralized data management, translation and integration, and specialized storage It provides guidance on: — Use case definition, services, and functions specification — Application schema considerations addressing fundamental differences between BIM and GIS data structures — Data resources management including objects, entities, and features — Position and location management including georeferencing levels, metadata requirements, and implementation tasks — Coordinate reference system selection and transformation parameters — Georeferencing, including levels of georeferencing, metadata requirements and georeferencing tasks | E82: BIM + GIS | F82: https://www.iso.org/standard/87373.html | G82: 2026.xx | H82: 2026.xx | J82: n/a | L82: No | M82: n/a | N82: Yes | O82: ISO/TC 59/SC 13 | P82: =INDEX(Colours!$C$2:$C$14,MATCH(K82,Colours!$A$2:$A$14,0)) -> #N/A | T82: =3+TableStandards11[[#This Row],[Degree Centrality]]*17 -> 3
A83: 82 | B83: ISO/CD 23143-2 | C83: Information exchange between BIM and GIS — Part 2: Facilitating data exchange through metadata. | D83: This document provides guidelines for the exchange of information between BIM and GIS through metadata. This document explains the role that metadata plays in facilitating data exchange within the framework of the standards referenced in ISO(AWI 23143-1, Clause 6. This document offers a perspective on leveraging metadata to ensure interoperability between BIM and GIS. It builds on the core principles established in ISO/AWI 23143-1 by presenting how metadata supports communication between the two domains, thereby facilitating seamless data exchange This document defines a framework for facilitating information exchange between Building Information Modelling (BIM) and Geographic Information Systems (GIS) through metadata-driven interoperability. It specifies methods for identifying, cross-mapping, and semantically aligning metadata elements defined in the IDM Data Schema (ISO 29481-3:2022[1]) and the GIS Metadata Schema (ISO 19115-1:2014[2]), enabling structured transformation between the two domains. The scope of this part includes: 1) Establishing metadata-based cross-mapping rules to support the semantic translation of information between BIM and GIS; 2) Supporting bidirectional information requests and responses, where each domain (BIM or GIS) can serve as either information provider or consumer; 3) Utilizing a metadata registry according to the ISO/IEC 11179 series to manage and align metadata vocabularies, value domains, and mappings; 4) Enabling metadata-driven exchange of geospatial and construction-related information across heterogeneous application schemas (e.g., IFC, CityGML, InfraGML); 5) Supporting Level of Information Need (LoIN)-based request that can be interpreted across domains via mapped metadata. | E83: BIM + GIS | F83: https://www.iso.org/standard/87376.html | G83: 2026.xx | H83: 2026.xx | J83: n/a | L83: No | M83: n/a | N83: Yes | O83: ISO/TC 59/SC 13 | P83: =INDEX(Colours!$C$2:$C$14,MATCH(K83,Colours!$A$2:$A$14,0)) -> #N/A | T83: =3+TableStandards11[[#This Row],[Degree Centrality]]*17 -> 3
A84: 83 | B84: ISO/CD 23143-3 | C84: Information exchange between BIM and GIS — Part 3: Linking abstract concepts in BIM and GIS standards | D84: This document establishes a methodology for linking abstract concepts within Building Information Modelling (BIM) and Geographic Information System (GIS) standards and specifies structural mechanisms for organizing their interconnected relationships, aiming to facilitate cross-domain information exchange. Methodologies for the development of RDF that relate to BIM and GIS are not within the scope of this document. | E84: BIM + GIS | F84: https://www.iso.org/standard/89397.html | G84: 2026.xx | H84: 2026.xx | J84: n/a | L84: No | M84: n/a | N84: Yes | O84: ISO/TC 59/SC 13 | P84: =INDEX(Colours!$C$2:$C$14,MATCH(K84,Colours!$A$2:$A$14,0)) -> #N/A | T84: =3+TableStandards11[[#This Row],[Degree Centrality]]*17 -> 3
A85: 84 | B85: ISO/DIS 37187 | C85: Smart community infrastructures — Guidelines on data exchange and sharing of city information modelling platform (UNDER DEVELOPMENT) | D85: This document specifies the requirements of the City Information Modelling (CIM) platform for the information modelling process of smart city construction, operation and maintenance. This document applies to both building and infrastructure assets and management of the CIM platform and its related applications and scenarios, including community infrastructures such as transportation, communication, energy, roads, logistics, and the activities of stakeholders both organizations and citizens, apply for governments, enterprises, schools, health care, and families, etc. NOTE Annex A outlines case studies of data exchange and sharing of CIM platform in smart community. | E85: BIM + GIS | F85: https://www.iso.org/standard/69273.html | G85: 2026.xx | H85: 2026.xx | J85: 91.020; 35.240.99 | L85: No | M85: n/a | N85: Yes | O85: ISO/TC 268/SC 1 | P85: =INDEX(Colours!$C$2:$C$14,MATCH(K85,Colours!$A$2:$A$14,0)) -> #N/A | T85: =3+TableStandards11[[#This Row],[Degree Centrality]]*17 -> 3
A86: 85 | B86: ISO/DIS 37189 | C86: Smart community infrastructure — Guidance for data-driven visualization in newly developing areas (UNDER DEVELOPMENT) | D86: This document gives guidance for applying data-driven approach to visualize infrastructures in newly developing areas. | E86: BIM + GIS | F86: https://www.iso.org/standard/69275.html | G86: 2026.xx | H86: 2026.xx | J86: 13.020.20 | L86: No | M86: n/a | N86: Yes | O86: ISO/TC 268/SC 1 | P86: =INDEX(Colours!$C$2:$C$14,MATCH(K86,Colours!$A$2:$A$14,0)) -> #N/A | T86: =3+TableStandards11[[#This Row],[Degree Centrality]]*17 -> 3
A87: 86 | B87: ISO/IEC 15444-2 | C87: Information technology — JPEG 2000 image coding system — Part 2: Extensions | D87: This Recommendation | International Standard defines a set of lossless (bit-preserving) and lossy compression methods for coding continuous-tone, bi-level, grey-scale, colour digital still images, or multi-component images. This Recommendation | International Standard: — specifies extended decoding processes for converting compressed image data to reconstructed image data; — specifies an extended codestream syntax containing information for interpreting the compressed image data; — specifies an extended file format; — specifies a container to store image metadata; — defines a standard set of image metadata; — provides guidance on extended encoding processes for converting source image data to compressed image data; — provides guidance on how to implement these processes in practice. | E87: BIM + GIS | F87: https://www.iso.org/standard/84573.html | G87: 2004.05 | H87: 2023.11 | J87: 35.040.30 | L87: No | M87: n/a | N87: Yes | O87: ISO/IEC JTC 1/SC 29 | P87: =INDEX(Colours!$C$2:$C$14,MATCH(K87,Colours!$A$2:$A$14,0)) -> #N/A | T87: =3+TableStandards11[[#This Row],[Degree Centrality]]*17 -> 3
A88: 87 | B88: ISO/IEC TS 5147 | C88: Information technology — Computer graphics, image processing and environmental data representation — Guidelines for representation and visualization of smart cities | D88: This document specifies guidelines for the representation and visualization of smart cities. This document: a) describes the concepts of a smart city, smart city object and smart city data, b) describes categories of data associated with smart cities, c) provides guidance for representation of smart cities, d) describes guidance for visualization of smart cities, e) provides guidance in selecting the appropriate representation and visualization technique for different categories of smart city data using standards, and f) provides use cases for applying standards to the representation and visualization of smart cities. | E88: BIM + GIS | F88: https://www.iso.org/standard/80918.html | G88: 2023.07 | H88: 2023.07 | J88: 35.14 | L88: No | M88: n/a | N88: Yes | O88: ISO/IEC JTC 1/SC 24 | P88: =INDEX(Colours!$C$2:$C$14,MATCH(K88,Colours!$A$2:$A$14,0)) -> #N/A | T88: =3+TableStandards11[[#This Row],[Degree Centrality]]*17 -> 3
A89: 88 | B89: ISO/TR 16214 | C89: Review of geospatial and building information modelling (BIM) terminological entries | D89: This document provides an overview of terminological entries relating to building information modelling (BIM) as well as those relating to geographic information or geomatics. This document identifies terminological entries which are identical, equivalent (i.e. synonyms), homonymous, and entries which are unique to their respective domains. This document does not provide recommendations to resolve terminology homonyms. | E89: BIM + GIS | F89: https://www.iso.org/standard/84517.html | G89: 2025.05 | H89: 2025.05 | J89: 01.040.35; 01.040.91; 35.240.67; 35.240.70 | L89: No | M89: n/a | N89: Yes | O89: ISO/TC 59/SC 13 | P89: =INDEX(Colours!$C$2:$C$14,MATCH(K89,Colours!$A$2:$A$14,0)) -> #N/A | T89: =3+TableStandards11[[#This Row],[Degree Centrality]]*17 -> 3
A90: 89 | B90: ISO/TR 19121 | C90: Geographic information -- Imagery and gridded data | D90: This Technical Report reviews the manner in which raster and gridded data is currently being handled in the Geomatics community in order to propose how this type of data should be supported by geographic information standards. This Technical Report identifies those aspects of imagery and gridded data that have been standardized or are being standardized in other ISO committees and external standards organizations, and that influence or support the establishment of raster and gridded data standards for geographic information. It also describes the components of those identified ISO and external imagery and gridded data standards that can be harmonized with the ISO 19100 series of geographic information/geomatics standards. A plan is presented for ISO/TC 211 to address imagery and gridded data in an integrated manner, within the ISO 19100 series of geographic information standards. | F90: https://www.iso.org/standard/29775.html | G90: 2000.10 | H90: 2000.10 | J90: 35.240.70 | L90: No | M90: n/a | N90: Yes | O90: ISO/TC 211 | P90: =INDEX(Colours!$C$2:$C$14,MATCH(K90,Colours!$A$2:$A$14,0)) -> #N/A | T90: =3+TableStandards11[[#This Row],[Degree Centrality]]*17 -> 3
A91: 90 | B91: ISO/TR 19167 | C91: Application of ubiquitous public access to-geographic information to an air quality information service | D91: This document facilitates an understanding of the Ubiquitous Public Access (UPA) context information model, as defined in ISO 19154, to establish a UPA-to-Geographic Information (GI) environment. In addition, this document illustrates how the UPA context information model is designed and implemented to provide an air quality information service from a geographic information system (GIS)-based air quality information system. The UPA context information model for air quality information is only a sample of all possible examples to realize the UPA-to-GI that could satisfy the requirements of ISO 19154. | F91: https://www.iso.org/standard/75148.html | G91: 2019.12 | H91: 2019.12 | J91: 35.240.70 | L91: No | M91: n/a | N91: Yes | O91: ISO/TC 211 | P91: =INDEX(Colours!$C$2:$C$14,MATCH(K91,Colours!$A$2:$A$14,0)) -> #N/A | T91: =3+TableStandards11[[#This Row],[Degree Centrality]]*17 -> 3
A92: 91 | B92: ISO/TR 19169 | C92: Geographic Information — Gap-analysis: mapping and describing the differences between the current GDF and ISO/TC 211 conceptual models to suggest ways to harmonize and resolve conflicting issues | D92: This document maps and describes the differences between GDF (ISO 20524 series), from ISO/TC 204, and conceptual models from the ISO 19100 family, from ISO/TC 211, and suggests ways to harmonize and resolve issues of conflict. Throughout this document, reference to GDF refers to GDF v5.1, ISO 20524-1 and ISO 20524-2, unless expressly identified otherwise. Where necessary, reference will be made to Part 1 or Part 2. | F92: https://www.iso.org/standard/32587.html | G92: 2021.06 | H92: 2021.06 | J92: 35.240.70 | L92: No | M92: n/a | N92: Yes | O92: ISO/TC 211 | P92: =INDEX(Colours!$C$2:$C$14,MATCH(K92,Colours!$A$2:$A$14,0)) -> #N/A | T92: =3+TableStandards11[[#This Row],[Degree Centrality]]*17 -> 3
A93: 92 | B93: ISO/TR 19174 | C93: Geographic information — Securing interoperability among heterogeneous city domain information models | D93: This document analyses a feasible way to accommodate interoperability elements for the data component of a spatial data infrastructure (SDI) and extend the meta model framework for interoperability (MFI) in securing interoperability among heterogeneous domain information models under the smart city context. This document: a) outlines the interoperability issues for city domain information models; b) reviews relevant standards and best practices and examines methodologies or solutions to tackle the interoperability issues; c) supposes a use case and provides an example to secure interoperability among different domain information models using model registry; d) specifies technical requirements in concern about how to apply the interoperability elements of the meta model framework to support the interoperability of smart city services; e) highlights the standardization items to be developed to secure interoperability. | E93: BIM + GIS | F93: https://www.iso.org/standard/32592.html | G93: 2025.05 | H93: 2025.05 | J93: 13.020.20; 35.240.01 | L93: Yes | M93: CEN/TC 287 | N93: Yes | O93: ISO/TC 211; ISO/TC 287 | P93: =INDEX(Colours!$C$2:$C$14,MATCH(K93,Colours!$A$2:$A$14,0)) -> #N/A | T93: =3+TableStandards11[[#This Row],[Degree Centrality]]*17 -> 3
A94: 93 | B94: ISO/TR 19175 | C94: Geographic information — Gap analysis of geospatial standards for indoor-outdoor seamless navigation | D94: The objective of this document is to analyse gaps in geospatial standards for indoor-outdoor seamless navigation. This document is intended to be used by designers, developers and providers of outdoor or indoor navigation services. This document: a) specifies the concepts for the indoor-outdoor seamless navigation; b) outlines conceptual architecture and scenarios (or use-cases) for indoor-outdoor seamless navigation; c) analyses the gap of the current geospatial standards for implementing the indoor-outdoor seamless navigation; d) highlights standardization items to be proceeded to get more interoperability. | E94: BIM + GIS | F94: https://www.iso.org/standard/86329.html | G94: 2025.06 | H94: 2025.06 | J94: 33.070.40; 35.240.70 | L94: Yes | M94: CEN/TC 287 | N94: Yes | O94: ISO/TC 211; ISO/TC 287 | P94: =INDEX(Colours!$C$2:$C$14,MATCH(K94,Colours!$A$2:$A$14,0)) -> #N/A | T94: =3+TableStandards11[[#This Row],[Degree Centrality]]*17 -> 3
A95: 94 | B95: ISO/TR 20123 | C95: Automation systems and integration — Industrial data — Nuclear digital ecosystem specifications | D95: This document provides: — a review and summary of the adoption of digital methods and technology in the national nuclear sectors; — a summary of the state of the art of some of the standards supporting the digital representation and interoperability of industrial data; — orientation on the use of these standards for model-based systems engineering (MBSE) in order to achieve a nuclear digital ecosystem (NDE); — a high-level roadmap of the stages by which this ecosystem can be achieved, taking into account the maturity of the actors of the ecosystem, their relationships and the added value of using advanced standards. NOTE The complete reports from the participating entities are presented in Annexes A to G. This document includes the following: — the systems composing the nuclear facilities and their input, output, and other products resulting from interactions in the nuclear system or with its environment; — the material accounting and the corresponding requirements; — waste management: all types of nuclear waste produced during processes and activities, and their properties are considered for a seamless management of information in the whole value chain of the nuclear ecosystem. | E95: BIM + GIS | F95: https://www.iso.org/standard/86092.html | G95: 2023.09 | H95: 2023.09 | J95: 25.040.40 | L95: No | M95: n/a | N95: Yes | O95: ISO/TC 184 | P95: =INDEX(Colours!$C$2:$C$14,MATCH(K95,Colours!$A$2:$A$14,0)) -> #N/A | T95: =3+TableStandards11[[#This Row],[Degree Centrality]]*17 -> 3
A96: 95 | B96: ISO/TR 23262 | C96: GIS (geospatial) / BIM interoperability | D96: This document investigates barriers and proposes measures to improve interoperability between geospatial and BIM domains, namely, to align GIS standards developed by ISO/TC 211 and BIM standards developed by ISO/TC 59/SC 13. Where relevant this document takes into account work and documents from other organizations and committees, such as buildingSMART, International (bSI), Open Geospatial Consortium (OGC) and Comité Européen de Normalisation (CEN). The focus is to identify future topics for standardization and possible revision needs of existing standards. This document investigates conceptual and technological barriers between GIS and BIM domains at the data, service and process levels, as defined by ISO 11354 (all parts). | E96: BIM + GIS | F96: https://www.iso.org/standard/75105.html | G96: 2021.05 | H96: 2021.05 | J96: 35.240.67; 35.240.70 | L96: No | M96: n/a | N96: Yes | O96: ISO/TC 59/SC 13 | P96: =INDEX(Colours!$C$2:$C$14,MATCH(K96,Colours!$A$2:$A$14,0)) -> #N/A | T96: =3+TableStandards11[[#This Row],[Degree Centrality]]*17 -> 3
A97: 96 | B97: ISO/TR 37112 | C97: Sustainable cities and communities — Case studies in how smart city operating models support an effective public-health emergency response | D97: This document identifies good practice case studies of smart city responses to COVID-19 through the use of smart technologies, smart data, smart decision-making and smart ways of working. In particular, it aims to demonstrate how the principles for smart city operating models recommended in ISO 37106 can deliver improved outcomes in public-health emergency management (PHEM), at every stage of the command-and-control process for emergency management and incident response set out in ISO 22320. This document is intended to inform ISO 371131, which recommends a framework of good practices that can be used in responding to future public-health emergencies. | E97: BIM + GIS | F97: https://www.iso.org/standard/80335.html | G97: 2024.03 | H97: 2024.03 | J97: 03.100.01; 13.020.20 | L97: No | M97: n/a | N97: Yes | O97: ISO/TC 268 | P97: =INDEX(Colours!$C$2:$C$14,MATCH(K97,Colours!$A$2:$A$14,0)) -> #N/A | T97: =3+TableStandards11[[#This Row],[Degree Centrality]]*17 -> 3
A98: 97 | B98: ISO/TR 41016 | C98: Facility management — Overview of available technologies | D98: This document provides an overview of the available facility management (FM) technologies. This document is applicable to facility managers, their teams and their stakeholders. It aligns specifically with ISO/TR 41013, the ISO 19650 series and the ISO 41000 family of standards as part of an integrated framework to achieve FM best practice. This document outlines various long-term benefits and enhanced value that can be derived progressively by the operators, occupants and owners of facilities, worldwide, via the effective application of technology. This document includes, defines and categorises systems, equipment, methodologies and software applications that are available. This framework defines how facility managers can understand and integrate digital practice and technologies in the built environment. | E98: BIM + GIS | F98: https://www.iso.org/standard/68172.html | G98: 2024.04 | H98: 2024.04 | J98: 03.080.10 | L98: No | M98: n/a | N98: Yes | O98: ISO/TC 267 | P98: =INDEX(Colours!$C$2:$C$14,MATCH(K98,Colours!$A$2:$A$14,0)) -> #N/A | T98: =3+TableStandards11[[#This Row],[Degree Centrality]]*17 -> 3
A99: 98 | B99: ISO/TS 19124-1 | C99: Geographic information — Calibration and validation of remote sensing data and derived products — Part 1: Fundamentals | D99: The ISO 19124 series is focused on calibration and validation (Cal/Val) of remote sensing data, which are collected by a sensor on-board a platform in a mission, and products derived in part or whole from the data. The ISO 19124 series defines the metadata related to the calibration and validation process that has not been defined in other ISO/TC 211 International Standards. The metadata allows the data providers to provide a standardized description of the Cal/Val process they have applied to the data. It allows the data users to get the same forms of metadata from different data providers. This document addresses the overall framework and common calibration and validation processes related to Earth observation data and derived products from different types of remote sensors. Subsequent parts in the ISO 19124 series will target data from specific sensors, for example, infrared, ultraviolet/visible/near-infrared, microwave, or broadband, products derived from those data, and calibration and validation sites. Calibration addresses a geometric, radiometric, or spectral correction of the data. Validation addresses an evaluation of the quality and the accuracy of the data and the derived products. | F99: https://www.iso.org/standard/79352.html | G99: 2023.04 | H99: 2023.04 | J99: 35.240.70 | L99: No | M99: n/a | N99: Yes | O99: ISO/TC 211 | P99: =INDEX(Colours!$C$2:$C$14,MATCH(K99,Colours!$A$2:$A$14,0)) -> #N/A | T99: =3+TableStandards11[[#This Row],[Degree Centrality]]*17 -> 3
A100: 99 | B100: ISO/TS 19129 | C100: Geographic information -- Imagery, gridded and coverage data framework | D100: ISO/TS 19129:2009 defines the framework for imagery, gridded and coverage data. This framework defines a content model for the content type imagery and for other specific content types that can be represented as coverage data. These content models are represented as a set of generic UML patterns for application schemas. | F100: https://www.iso.org/standard/43041.html | G100: 2009.04 | H100: 2009.04 | J100: 35.240.70 | L100: No | M100: n/a | N100: Yes | O100: ISO/TC 211 | P100: =INDEX(Colours!$C$2:$C$14,MATCH(K100,Colours!$A$2:$A$14,0)) -> #N/A | T100: =3+TableStandards11[[#This Row],[Degree Centrality]]*17 -> 3
A101: 100 | B101: ISO/TS 19130-2 | C101: Geographic information -- Imagery sensor models for geopositioning -- Part 2: SAR, InSAR, lidar and sonar | D101: ISO/TS 19130-2:2014 supports exploitation of remotely sensed images. It specifies the sensor models and metadata for geopositioning images remotely sensed by Synthetic Aperture Radar (SAR), Interferometric Synthetic Aperture Radar (InSAR), LIght Detection And Ranging (lidar), and SOund Navigation And Ranging (sonar) sensors. The specification also defines the metadata needed for the aerial triangulation of airborne and spaceborne images. ISO/TS 19130-2:2014 specifies the detailed information that shall be provided for a sensor description of SAR, InSAR, lidar, and sonar sensors with the associated physical and geometric information necessary to rigorously construct a physical sensor model. For the case where precise geoposition information is needed, this Technical Specification identifies the mathematical formulae for rigorously constructing physical sensor models that relate two-dimensional image space to three-dimensional ground space and the calculation of the associated propagated error. ISO/TS 19130-2:2014 does not specify either how users derive geoposition data or the format or content of the data the users generate. | F101: https://www.iso.org/standard/56113.html | G101: 2014.01 | H101: 2014.01 | J101: 35.240.70 | L101: No | M101: n/a | N101: Yes | O101: ISO/TC 211 | P101: =INDEX(Colours!$C$2:$C$14,MATCH(K101,Colours!$A$2:$A$14,0)) -> #N/A | T101: =3+TableStandards11[[#This Row],[Degree Centrality]]*17 -> 3
A102: 101 | B102: ISO/TS 19130-3 | C102: Geographic information — Imagery sensor models for geopositioning — Part 3: Implementation schema | D102: This document defines the XML Schema implementation of imagery sensor geopositioning models defined in ISO 19130-1 and ISO/TS 19130-2. It applies XML Schema inheritance and extension based on the OGC SensorML and OGC SWE Common Data Model. Instead of introducing an XML Schema based on the UML models defined in ISO 19130-1 and ISO/TS 19130-2, it leverages the existing OGC SensorML by first introducing a semantic mapping from the model elements defined in ISO 19130-1 and ISO/TS 19130-2 to OGC SensorML, and then defining the detailed schema inheritance and extensions based on OGC SensorML to fully support encoding of the imagery sensor models for geopositioning defined in ISO 19130-1 and ISO/TS 19130-2. | F102: https://www.iso.org/standard/74074.html | G102: 2022.03 | H102: 2022.03 | J102: 35.240.70 | L102: No | M102: n/a | N102: Yes | O102: ISO/TC 211 | P102: =INDEX(Colours!$C$2:$C$14,MATCH(K102,Colours!$A$2:$A$14,0)) -> #N/A | T102: =3+TableStandards11[[#This Row],[Degree Centrality]]*17 -> 3
A103: 102 | B103: ISO/TS 19139-1 | C103: Geographic information - XML schema implementation - Part 1: Encoding rules | D103: This document defines XML based encoding rules for conceptual schemas specifying types that describe geographic resources. The encoding rules support the UML profile as used in the UML models commonly used in the standards developed by ISO/TC 211. The encoding rules use XML schema for the output data structure schema. The encoding rules described in this document are not applicable for encoding UML application schema for geographic features (see ISO 19136 for those rules). | F103: https://www.iso.org/standard/67253.html | G103: 2007.04 | H103: 2019.03 | J103: 35.240.70 | L103: Yes | M103: CEN/TC 287 | N103: Yes | O103: ISO/TC 211 | P103: =INDEX(Colours!$C$2:$C$14,MATCH(K103,Colours!$A$2:$A$14,0)) -> #N/A | T103: =3+TableStandards11[[#This Row],[Degree Centrality]]*17 -> 3
A104: 103 | B104: ISO/TS 19144-3 | C104: Geographic information - Classification systems - Part 3: Land Use Meta Language (LUML) | D104: This document specifies a Land Use Meta Language (LUML) expressed as a UML metamodel that allows different Land Use classification systems to be described. This document recognizes that there are a number of Land Use classification systems in existence. It provides a common reference structure for the comparison and integration of data for any generic Land Use classification system, but does not intend to replace those classification systems. This document complements ISO 19144-2 on Land Cover Meta Language (LCML) and can be used independently to describe Land Use or together with ISO 19144-2 to describe a combined Land Cover Land Use. | F104: https://www.iso.org/standard/85091.html | G104: 2024.11 | H104: 2024.11 | J104: 35.240.70 | L104: Yes | M104: CEN/TC 287 | N104: Yes | O104: ISO/TC 211 | P104: =INDEX(Colours!$C$2:$C$14,MATCH(K104,Colours!$A$2:$A$14,0)) -> #N/A | T104: =3+TableStandards11[[#This Row],[Degree Centrality]]*17 -> 3
...

Sheet GIS-Relationships
A1: Id | B1: Source Standard Number | C1: Target Current Number | D1: Target NonCurrent Number | E1: Target First Year | F1: Target Current Year | G1: ICS | H1: Source Calculation | I1: Target Calculation | J1: Source Colour | K1: Target Colour | L1: Type | M1: Link | N1: Source Type | O1: Target Type | P1: Inter-BIM Relationship | Q1: Weight _calculation | R1: Rank Pedro | S1: Weight Pedro_calculation | T1: Category | U1: Category Colour | V1: timeset_calculation | W1: Colour_calculation | X1: Label
A2: 1 | B2: CEN ISO/TS 19139-1 | C2: GIS anchor | E2: 2007.04 | F2: 2019.03 | G2: 35.240.70 | H2: =INDEX('GIS-Standards'!$A$2:$A$305,MATCH(B2,'GIS-Standards'!$B$2:$B$305,0)) -> #N/A | I2: =INDEX('GIS-Standards'!$A$2:$A$305,MATCH(C2,'GIS-Standards'!$B$2:$B$305,0)) -> #N/A | J2: =INDEX('GIS-Standards'!$O$2:$O$305,MATCH(B2,'GIS-Standards'!$B$2:$B$305,0)) -> #N/A | K2: =INDEX('GIS-Standards'!$O$2:$O$305,MATCH(C2,'GIS-Standards'!$B$2:$B$305,0)) -> #N/A | M2: Anchor | N2: =INDEX('GIS-Standards'!$I$2:$I$305,MATCH(B2,'GIS-Standards'!$B$2:$B$305,0)) -> #N/A | O2: =INDEX('GIS-Standards'!$I$2:$I$305,MATCH(C2,'GIS-Standards'!$B$2:$B$305,0)) -> #N/A | P2: =AND(TableRelationships12[[#This Row],[Source Type]]="BIM",TableRelationships12[[#This Row],[Target Type]]="BIM") -> #N/A | Q2: =IF(M2="Normative",6,IF(M2="Secondary",4,IF(M2="Anchor",2,1))) -> 2 | S2: =IF(R2="High",10,IF(R2="Medium",6,IF(R2="Low",2,1))) -> 1 | T2: =IF(TableRelationships12[[#This Row],[Rank Pedro]]="Low","linkCategory1",IF(TableRelationships12[[#This Row],[Rank Pedro]]="Medium","linkCategory2",IF(TableRelationships12[[#This Row],[Rank Pedro]]="High","linkCategory3",""))) | U2: =IF(TableRelationships12[[#This Row],[Rank Pedro]]="Low","Pink",IF(TableRelationships12[[#This Row],[Rank Pedro]]="Medium","Purple",IF(TableRelationships12[[#This Row],[Rank Pedro]]="High","Brown",""))) | V2: =MAX(INDEX(Standards!$F$2:$F$296,MATCH(B2,Standards!$B$2:$B$296,0)),INDEX(Standards!$F$2:$F$296,MATCH(C2,Standards!$B$2:$B$296,0))) -> #N/A | W2: =IF(M2="Normative", "#d6bf2a", IF(M2="Informative", "#2f89d1", 1)) -> 1
A3: 2 | B3: CEN ISO/TS 19139-1 | C3: ISO 19118 | E3: 2005.07 | F3: 2011.1 | G3: 35.240.70 | H3: =INDEX('GIS-Standards'!$A$2:$A$305,MATCH(B3,'GIS-Standards'!$B$2:$B$305,0)) -> #N/A | I3: =INDEX('GIS-Standards'!$A$2:$A$305,MATCH(C3,'GIS-Standards'!$B$2:$B$305,0)) -> 27 | J3: =INDEX('GIS-Standards'!$O$2:$O$305,MATCH(B3,'GIS-Standards'!$B$2:$B$305,0)) -> #N/A | K3: =INDEX('GIS-Standards'!$O$2:$O$305,MATCH(C3,'GIS-Standards'!$B$2:$B$305,0)) -> ISO/TC 211 | M3: Normative | N3: =INDEX('GIS-Standards'!$I$2:$I$305,MATCH(B3,'GIS-Standards'!$B$2:$B$305,0)) -> #N/A | O3: =INDEX('GIS-Standards'!$I$2:$I$305,MATCH(C3,'GIS-Standards'!$B$2:$B$305,0)) -> 0 | P3: =AND(TableRelationships12[[#This Row],[Source Type]]="BIM",TableRelationships12[[#This Row],[Target Type]]="BIM") -> #N/A | Q3: =IF(M3="Normative",6,IF(M3="Secondary",4,IF(M3="Anchor",2,1))) -> 6 | S3: =IF(R3="High",10,IF(R3="Medium",6,IF(R3="Low",2,1))) -> 1 | T3: =IF(TableRelationships12[[#This Row],[Rank Pedro]]="Low","linkCategory1",IF(TableRelationships12[[#This Row],[Rank Pedro]]="Medium","linkCategory2",IF(TableRelationships12[[#This Row],[Rank Pedro]]="High","linkCategory3",""))) | U3: =IF(TableRelationships12[[#This Row],[Rank Pedro]]="Low","Pink",IF(TableRelationships12[[#This Row],[Rank Pedro]]="Medium","Purple",IF(TableRelationships12[[#This Row],[Rank Pedro]]="High","Brown",""))) | V3: =MAX(INDEX(Standards!$F$2:$F$296,MATCH(B3,Standards!$B$2:$B$296,0)),INDEX(Standards!$F$2:$F$296,MATCH(C3,Standards!$B$2:$B$296,0))) -> #N/A | W3: =IF(M3="Normative", "#d6bf2a", IF(M3="Informative", "#2f89d1", 1)) -> #d6bf2a
A4: 3 | B4: CEN ISO/TS 19139-1 | C4: W3C xml-names | H4: =INDEX('GIS-Standards'!$A$2:$A$305,MATCH(B4,'GIS-Standards'!$B$2:$B$305,0)) -> #N/A | I4: =INDEX('GIS-Standards'!$A$2:$A$305,MATCH(C4,'GIS-Standards'!$B$2:$B$305,0)) -> #N/A | J4: =INDEX('GIS-Standards'!$O$2:$O$305,MATCH(B4,'GIS-Standards'!$B$2:$B$305,0)) -> #N/A | K4: =INDEX('GIS-Standards'!$O$2:$O$305,MATCH(C4,'GIS-Standards'!$B$2:$B$305,0)) -> #N/A | M4: Normative | N4: =INDEX('GIS-Standards'!$I$2:$I$305,MATCH(B4,'GIS-Standards'!$B$2:$B$305,0)) -> #N/A | O4: =INDEX('GIS-Standards'!$I$2:$I$305,MATCH(C4,'GIS-Standards'!$B$2:$B$305,0)) -> #N/A | P4: =AND(TableRelationships12[[#This Row],[Source Type]]="BIM",TableRelationships12[[#This Row],[Target Type]]="BIM") -> #N/A | Q4: =IF(M4="Normative",6,IF(M4="Secondary",4,IF(M4="Anchor",2,1))) -> 6 | S4: =IF(R4="High",10,IF(R4="Medium",6,IF(R4="Low",2,1))) -> 1 | T4: =IF(TableRelationships12[[#This Row],[Rank Pedro]]="Low","linkCategory1",IF(TableRelationships12[[#This Row],[Rank Pedro]]="Medium","linkCategory2",IF(TableRelationships12[[#This Row],[Rank Pedro]]="High","linkCategory3",""))) | U4: =IF(TableRelationships12[[#This Row],[Rank Pedro]]="Low","Pink",IF(TableRelationships12[[#This Row],[Rank Pedro]]="Medium","Purple",IF(TableRelationships12[[#This Row],[Rank Pedro]]="High","Brown",""))) | V4: =MAX(INDEX(Standards!$F$2:$F$296,MATCH(B4,Standards!$B$2:$B$296,0)),INDEX(Standards!$F$2:$F$296,MATCH(C4,Standards!$B$2:$B$296,0))) -> #N/A | W4: =IF(M4="Normative", "#d6bf2a", IF(M4="Informative", "#2f89d1", 1)) -> #d6bf2a
A5: 4 | B5: CEN ISO/TS 19139-1 | C5: W3C xmlschema-1 | H5: =INDEX('GIS-Standards'!$A$2:$A$305,MATCH(B5,'GIS-Standards'!$B$2:$B$305,0)) -> #N/A | I5: =INDEX('GIS-Standards'!$A$2:$A$305,MATCH(C5,'GIS-Standards'!$B$2:$B$305,0)) -> #N/A | J5: =INDEX('GIS-Standards'!$O$2:$O$305,MATCH(B5,'GIS-Standards'!$B$2:$B$305,0)) -> #N/A | K5: =INDEX('GIS-Standards'!$O$2:$O$305,MATCH(C5,'GIS-Standards'!$B$2:$B$305,0)) -> #N/A | M5: Normative | N5: =INDEX('GIS-Standards'!$I$2:$I$305,MATCH(B5,'GIS-Standards'!$B$2:$B$305,0)) -> #N/A | O5: =INDEX('GIS-Standards'!$I$2:$I$305,MATCH(C5,'GIS-Standards'!$B$2:$B$305,0)) -> #N/A | P5: =AND(TableRelationships12[[#This Row],[Source Type]]="BIM",TableRelationships12[[#This Row],[Target Type]]="BIM") -> #N/A | Q5: =IF(M5="Normative",6,IF(M5="Secondary",4,IF(M5="Anchor",2,1))) -> 6 | S5: =IF(R5="High",10,IF(R5="Medium",6,IF(R5="Low",2,1))) -> 1 | T5: =IF(TableRelationships12[[#This Row],[Rank Pedro]]="Low","linkCategory1",IF(TableRelationships12[[#This Row],[Rank Pedro]]="Medium","linkCategory2",IF(TableRelationships12[[#This Row],[Rank Pedro]]="High","linkCategory3",""))) | U5: =IF(TableRelationships12[[#This Row],[Rank Pedro]]="Low","Pink",IF(TableRelationships12[[#This Row],[Rank Pedro]]="Medium","Purple",IF(TableRelationships12[[#This Row],[Rank Pedro]]="High","Brown",""))) | V5: =MAX(INDEX(Standards!$F$2:$F$296,MATCH(B5,Standards!$B$2:$B$296,0)),INDEX(Standards!$F$2:$F$296,MATCH(C5,Standards!$B$2:$B$296,0))) -> #N/A | W5: =IF(M5="Normative", "#d6bf2a", IF(M5="Informative", "#2f89d1", 1)) -> #d6bf2a
A6: 5 | B6: CEN ISO/TS 19139-1 | C6: W3C xmlschema-2 | H6: =INDEX('GIS-Standards'!$A$2:$A$305,MATCH(B6,'GIS-Standards'!$B$2:$B$305,0)) -> #N/A | I6: =INDEX('GIS-Standards'!$A$2:$A$305,MATCH(C6,'GIS-Standards'!$B$2:$B$305,0)) -> #N/A | J6: =INDEX('GIS-Standards'!$O$2:$O$305,MATCH(B6,'GIS-Standards'!$B$2:$B$305,0)) -> #N/A | K6: =INDEX('GIS-Standards'!$O$2:$O$305,MATCH(C6,'GIS-Standards'!$B$2:$B$305,0)) -> #N/A | M6: Normative | N6: =INDEX('GIS-Standards'!$I$2:$I$305,MATCH(B6,'GIS-Standards'!$B$2:$B$305,0)) -> #N/A | O6: =INDEX('GIS-Standards'!$I$2:$I$305,MATCH(C6,'GIS-Standards'!$B$2:$B$305,0)) -> #N/A | P6: =AND(TableRelationships12[[#This Row],[Source Type]]="BIM",TableRelationships12[[#This Row],[Target Type]]="BIM") -> #N/A | Q6: =IF(M6="Normative",6,IF(M6="Secondary",4,IF(M6="Anchor",2,1))) -> 6 | S6: =IF(R6="High",10,IF(R6="Medium",6,IF(R6="Low",2,1))) -> 1 | T6: =IF(TableRelationships12[[#This Row],[Rank Pedro]]="Low","linkCategory1",IF(TableRelationships12[[#This Row],[Rank Pedro]]="Medium","linkCategory2",IF(TableRelationships12[[#This Row],[Rank Pedro]]="High","linkCategory3",""))) | U6: =IF(TableRelationships12[[#This Row],[Rank Pedro]]="Low","Pink",IF(TableRelationships12[[#This Row],[Rank Pedro]]="Medium","Purple",IF(TableRelationships12[[#This Row],[Rank Pedro]]="High","Brown",""))) | V6: =MAX(INDEX(Standards!$F$2:$F$296,MATCH(B6,Standards!$B$2:$B$296,0)),INDEX(Standards!$F$2:$F$296,MATCH(C6,Standards!$B$2:$B$296,0))) -> #N/A | W6: =IF(M6="Normative", "#d6bf2a", IF(M6="Informative", "#2f89d1", 1)) -> #d6bf2a
A7: 6 | B7: CEN ISO/TS 19139-1 | C7: W3C xml-10 | H7: =INDEX('GIS-Standards'!$A$2:$A$305,MATCH(B7,'GIS-Standards'!$B$2:$B$305,0)) -> #N/A | I7: =INDEX('GIS-Standards'!$A$2:$A$305,MATCH(C7,'GIS-Standards'!$B$2:$B$305,0)) -> #N/A | J7: =INDEX('GIS-Standards'!$O$2:$O$305,MATCH(B7,'GIS-Standards'!$B$2:$B$305,0)) -> #N/A | K7: =INDEX('GIS-Standards'!$O$2:$O$305,MATCH(C7,'GIS-Standards'!$B$2:$B$305,0)) -> #N/A | M7: Normative | N7: =INDEX('GIS-Standards'!$I$2:$I$305,MATCH(B7,'GIS-Standards'!$B$2:$B$305,0)) -> #N/A | O7: =INDEX('GIS-Standards'!$I$2:$I$305,MATCH(C7,'GIS-Standards'!$B$2:$B$305,0)) -> #N/A | P7: =AND(TableRelationships12[[#This Row],[Source Type]]="BIM",TableRelationships12[[#This Row],[Target Type]]="BIM") -> #N/A | Q7: =IF(M7="Normative",6,IF(M7="Secondary",4,IF(M7="Anchor",2,1))) -> 6 | S7: =IF(R7="High",10,IF(R7="Medium",6,IF(R7="Low",2,1))) -> 1 | T7: =IF(TableRelationships12[[#This Row],[Rank Pedro]]="Low","linkCategory1",IF(TableRelationships12[[#This Row],[Rank Pedro]]="Medium","linkCategory2",IF(TableRelationships12[[#This Row],[Rank Pedro]]="High","linkCategory3",""))) | U7: =IF(TableRelationships12[[#This Row],[Rank Pedro]]="Low","Pink",IF(TableRelationships12[[#This Row],[Rank Pedro]]="Medium","Purple",IF(TableRelationships12[[#This Row],[Rank Pedro]]="High","Brown",""))) | V7: =MAX(INDEX(Standards!$F$2:$F$296,MATCH(B7,Standards!$B$2:$B$296,0)),INDEX(Standards!$F$2:$F$296,MATCH(C7,Standards!$B$2:$B$296,0))) -> #N/A | W7: =IF(M7="Normative", "#d6bf2a", IF(M7="Informative", "#2f89d1", 1)) -> #d6bf2a
A8: 7 | B8: CEN ISO/TS 19139-1 | C8: W3C xlink-10 | H8: =INDEX('GIS-Standards'!$A$2:$A$305,MATCH(B8,'GIS-Standards'!$B$2:$B$305,0)) -> #N/A | I8: =INDEX('GIS-Standards'!$A$2:$A$305,MATCH(C8,'GIS-Standards'!$B$2:$B$305,0)) -> #N/A | J8: =INDEX('GIS-Standards'!$O$2:$O$305,MATCH(B8,'GIS-Standards'!$B$2:$B$305,0)) -> #N/A | K8: =INDEX('GIS-Standards'!$O$2:$O$305,MATCH(C8,'GIS-Standards'!$B$2:$B$305,0)) -> #N/A | M8: Normative | N8: =INDEX('GIS-Standards'!$I$2:$I$305,MATCH(B8,'GIS-Standards'!$B$2:$B$305,0)) -> #N/A | O8: =INDEX('GIS-Standards'!$I$2:$I$305,MATCH(C8,'GIS-Standards'!$B$2:$B$305,0)) -> #N/A | P8: =AND(TableRelationships12[[#This Row],[Source Type]]="BIM",TableRelationships12[[#This Row],[Target Type]]="BIM") -> #N/A | Q8: =IF(M8="Normative",6,IF(M8="Secondary",4,IF(M8="Anchor",2,1))) -> 6 | S8: =IF(R8="High",10,IF(R8="Medium",6,IF(R8="Low",2,1))) -> 1 | T8: =IF(TableRelationships12[[#This Row],[Rank Pedro]]="Low","linkCategory1",IF(TableRelationships12[[#This Row],[Rank Pedro]]="Medium","linkCategory2",IF(TableRelationships12[[#This Row],[Rank Pedro]]="High","linkCategory3",""))) | U8: =IF(TableRelationships12[[#This Row],[Rank Pedro]]="Low","Pink",IF(TableRelationships12[[#This Row],[Rank Pedro]]="Medium","Purple",IF(TableRelationships12[[#This Row],[Rank Pedro]]="High","Brown",""))) | V8: =MAX(INDEX(Standards!$F$2:$F$296,MATCH(B8,Standards!$B$2:$B$296,0)),INDEX(Standards!$F$2:$F$296,MATCH(C8,Standards!$B$2:$B$296,0))) -> #N/A | W8: =IF(M8="Normative", "#d6bf2a", IF(M8="Informative", "#2f89d1", 1)) -> #d6bf2a
A9: 8 | B9: CEN ISO/TS 19139-1 | C9: ISO 19103 | E9: 2005.07 | F9: 2024.09 | G9: 35.240.70 | H9: =INDEX('GIS-Standards'!$A$2:$A$305,MATCH(B9,'GIS-Standards'!$B$2:$B$305,0)) -> #N/A | I9: =INDEX('GIS-Standards'!$A$2:$A$305,MATCH(C9,'GIS-Standards'!$B$2:$B$305,0)) -> 12 | J9: =INDEX('GIS-Standards'!$O$2:$O$305,MATCH(B9,'GIS-Standards'!$B$2:$B$305,0)) -> #N/A | K9: =INDEX('GIS-Standards'!$O$2:$O$305,MATCH(C9,'GIS-Standards'!$B$2:$B$305,0)) -> ISO/TC 211 | M9: Informative | N9: =INDEX('GIS-Standards'!$I$2:$I$305,MATCH(B9,'GIS-Standards'!$B$2:$B$305,0)) -> #N/A | O9: =INDEX('GIS-Standards'!$I$2:$I$305,MATCH(C9,'GIS-Standards'!$B$2:$B$305,0)) -> 0 | P9: =AND(TableRelationships12[[#This Row],[Source Type]]="BIM",TableRelationships12[[#This Row],[Target Type]]="BIM") -> #N/A | Q9: =IF(M9="Normative",6,IF(M9="Secondary",4,IF(M9="Anchor",2,1))) -> 1 | S9: =IF(R9="High",10,IF(R9="Medium",6,IF(R9="Low",2,1))) -> 1 | T9: =IF(TableRelationships12[[#This Row],[Rank Pedro]]="Low","linkCategory1",IF(TableRelationships12[[#This Row],[Rank Pedro]]="Medium","linkCategory2",IF(TableRelationships12[[#This Row],[Rank Pedro]]="High","linkCategory3",""))) | U9: =IF(TableRelationships12[[#This Row],[Rank Pedro]]="Low","Pink",IF(TableRelationships12[[#This Row],[Rank Pedro]]="Medium","Purple",IF(TableRelationships12[[#This Row],[Rank Pedro]]="High","Brown",""))) | V9: =MAX(INDEX(Standards!$F$2:$F$296,MATCH(B9,Standards!$B$2:$B$296,0)),INDEX(Standards!$F$2:$F$296,MATCH(C9,Standards!$B$2:$B$296,0))) -> #N/A | W9: =IF(M9="Normative", "#d6bf2a", IF(M9="Informative", "#2f89d1", 1)) -> #2f89d1
A10: 9 | B10: CEN ISO/TS 19139-1 | C10: ISO 19105 | E10: 2000.12 | F10: 2022.07 | G10: 35.240.70 | H10: =INDEX('GIS-Standards'!$A$2:$A$305,MATCH(B10,'GIS-Standards'!$B$2:$B$305,0)) -> #N/A | I10: =INDEX('GIS-Standards'!$A$2:$A$305,MATCH(C10,'GIS-Standards'!$B$2:$B$305,0)) -> 14 | J10: =INDEX('GIS-Standards'!$O$2:$O$305,MATCH(B10,'GIS-Standards'!$B$2:$B$305,0)) -> #N/A | K10: =INDEX('GIS-Standards'!$O$2:$O$305,MATCH(C10,'GIS-Standards'!$B$2:$B$305,0)) -> ISO/TC 211 | M10: Informative | N10: =INDEX('GIS-Standards'!$I$2:$I$305,MATCH(B10,'GIS-Standards'!$B$2:$B$305,0)) -> #N/A | O10: =INDEX('GIS-Standards'!$I$2:$I$305,MATCH(C10,'GIS-Standards'!$B$2:$B$305,0)) -> 0 | P10: =AND(TableRelationships12[[#This Row],[Source Type]]="BIM",TableRelationships12[[#This Row],[Target Type]]="BIM") -> #N/A | Q10: =IF(M10="Normative",6,IF(M10="Secondary",4,IF(M10="Anchor",2,1))) -> 1 | S10: =IF(R10="High",10,IF(R10="Medium",6,IF(R10="Low",2,1))) -> 1 | T10: =IF(TableRelationships12[[#This Row],[Rank Pedro]]="Low","linkCategory1",IF(TableRelationships12[[#This Row],[Rank Pedro]]="Medium","linkCategory2",IF(TableRelationships12[[#This Row],[Rank Pedro]]="High","linkCategory3",""))) | U10: =IF(TableRelationships12[[#This Row],[Rank Pedro]]="Low","Pink",IF(TableRelationships12[[#This Row],[Rank Pedro]]="Medium","Purple",IF(TableRelationships12[[#This Row],[Rank Pedro]]="High","Brown",""))) | V10: =MAX(INDEX(Standards!$F$2:$F$296,MATCH(B10,Standards!$B$2:$B$296,0)),INDEX(Standards!$F$2:$F$296,MATCH(C10,Standards!$B$2:$B$296,0))) -> #N/A | W10: =IF(M10="Normative", "#d6bf2a", IF(M10="Informative", "#2f89d1", 1)) -> #2f89d1
A11: 10 | B11: CEN ISO/TS 19139-1 | C11: ISO 19107 | E11: 2003.05 | F11: 2019.12 | G11: 35.240.70 | H11: =INDEX('GIS-Standards'!$A$2:$A$305,MATCH(B11,'GIS-Standards'!$B$2:$B$305,0)) -> #N/A | I11: =INDEX('GIS-Standards'!$A$2:$A$305,MATCH(C11,'GIS-Standards'!$B$2:$B$305,0)) -> 16 | J11: =INDEX('GIS-Standards'!$O$2:$O$305,MATCH(B11,'GIS-Standards'!$B$2:$B$305,0)) -> #N/A | K11: =INDEX('GIS-Standards'!$O$2:$O$305,MATCH(C11,'GIS-Standards'!$B$2:$B$305,0)) -> ISO/TC 211 | M11: Informative | N11: =INDEX('GIS-Standards'!$I$2:$I$305,MATCH(B11,'GIS-Standards'!$B$2:$B$305,0)) -> #N/A | O11: =INDEX('GIS-Standards'!$I$2:$I$305,MATCH(C11,'GIS-Standards'!$B$2:$B$305,0)) -> 0 | P11: =AND(TableRelationships12[[#This Row],[Source Type]]="BIM",TableRelationships12[[#This Row],[Target Type]]="BIM") -> #N/A | Q11: =IF(M11="Normative",6,IF(M11="Secondary",4,IF(M11="Anchor",2,1))) -> 1 | S11: =IF(R11="High",10,IF(R11="Medium",6,IF(R11="Low",2,1))) -> 1 | T11: =IF(TableRelationships12[[#This Row],[Rank Pedro]]="Low","linkCategory1",IF(TableRelationships12[[#This Row],[Rank Pedro]]="Medium","linkCategory2",IF(TableRelationships12[[#This Row],[Rank Pedro]]="High","linkCategory3",""))) | U11: =IF(TableRelationships12[[#This Row],[Rank Pedro]]="Low","Pink",IF(TableRelationships12[[#This Row],[Rank Pedro]]="Medium","Purple",IF(TableRelationships12[[#This Row],[Rank Pedro]]="High","Brown",""))) | V11: =MAX(INDEX(Standards!$F$2:$F$296,MATCH(B11,Standards!$B$2:$B$296,0)),INDEX(Standards!$F$2:$F$296,MATCH(C11,Standards!$B$2:$B$296,0))) -> #N/A | W11: =IF(M11="Normative", "#d6bf2a", IF(M11="Informative", "#2f89d1", 1)) -> #2f89d1
A12: 11 | B12: CEN ISO/TS 19139-1 | C12: ISO 19110 | E12: 2005.02 | F12: 2016.12 | G12: 35.240.70 | H12: =INDEX('GIS-Standards'!$A$2:$A$305,MATCH(B12,'GIS-Standards'!$B$2:$B$305,0)) -> #N/A | I12: =INDEX('GIS-Standards'!$A$2:$A$305,MATCH(C12,'GIS-Standards'!$B$2:$B$305,0)) -> 19 | J12: =INDEX('GIS-Standards'!$O$2:$O$305,MATCH(B12,'GIS-Standards'!$B$2:$B$305,0)) -> #N/A | K12: =INDEX('GIS-Standards'!$O$2:$O$305,MATCH(C12,'GIS-Standards'!$B$2:$B$305,0)) -> ISO/TC 211 | M12: Informative | N12: =INDEX('GIS-Standards'!$I$2:$I$305,MATCH(B12,'GIS-Standards'!$B$2:$B$305,0)) -> #N/A | O12: =INDEX('GIS-Standards'!$I$2:$I$305,MATCH(C12,'GIS-Standards'!$B$2:$B$305,0)) -> 0 | P12: =AND(TableRelationships12[[#This Row],[Source Type]]="BIM",TableRelationships12[[#This Row],[Target Type]]="BIM") -> #N/A | Q12: =IF(M12="Normative",6,IF(M12="Secondary",4,IF(M12="Anchor",2,1))) -> 1 | S12: =IF(R12="High",10,IF(R12="Medium",6,IF(R12="Low",2,1))) -> 1 | T12: =IF(TableRelationships12[[#This Row],[Rank Pedro]]="Low","linkCategory1",IF(TableRelationships12[[#This Row],[Rank Pedro]]="Medium","linkCategory2",IF(TableRelationships12[[#This Row],[Rank Pedro]]="High","linkCategory3",""))) | U12: =IF(TableRelationships12[[#This Row],[Rank Pedro]]="Low","Pink",IF(TableRelationships12[[#This Row],[Rank Pedro]]="Medium","Purple",IF(TableRelationships12[[#This Row],[Rank Pedro]]="High","Brown",""))) | V12: =MAX(INDEX(Standards!$F$2:$F$296,MATCH(B12,Standards!$B$2:$B$296,0)),INDEX(Standards!$F$2:$F$296,MATCH(C12,Standards!$B$2:$B$296,0))) -> #N/A | W12: =IF(M12="Normative", "#d6bf2a", IF(M12="Informative", "#2f89d1", 1)) -> #2f89d1
A13: 12 | B13: CEN ISO/TS 19139-1 | C13: ISO 19115-1 | E13: 2003.05 | F13: 2020.11 | G13: 35.240.70 | H13: =INDEX('GIS-Standards'!$A$2:$A$305,MATCH(B13,'GIS-Standards'!$B$2:$B$305,0)) -> #N/A | I13: =INDEX('GIS-Standards'!$A$2:$A$305,MATCH(C13,'GIS-Standards'!$B$2:$B$305,0)) -> 22 | J13: =INDEX('GIS-Standards'!$O$2:$O$305,MATCH(B13,'GIS-Standards'!$B$2:$B$305,0)) -> #N/A | K13: =INDEX('GIS-Standards'!$O$2:$O$305,MATCH(C13,'GIS-Standards'!$B$2:$B$305,0)) -> ISO/TC 211 | M13: Informative | N13: =INDEX('GIS-Standards'!$I$2:$I$305,MATCH(B13,'GIS-Standards'!$B$2:$B$305,0)) -> #N/A | O13: =INDEX('GIS-Standards'!$I$2:$I$305,MATCH(C13,'GIS-Standards'!$B$2:$B$305,0)) -> 12.2020 | P13: =AND(TableRelationships12[[#This Row],[Source Type]]="BIM",TableRelationships12[[#This Row],[Target Type]]="BIM") -> #N/A | Q13: =IF(M13="Normative",6,IF(M13="Secondary",4,IF(M13="Anchor",2,1))) -> 1 | S13: =IF(R13="High",10,IF(R13="Medium",6,IF(R13="Low",2,1))) -> 1 | T13: =IF(TableRelationships12[[#This Row],[Rank Pedro]]="Low","linkCategory1",IF(TableRelationships12[[#This Row],[Rank Pedro]]="Medium","linkCategory2",IF(TableRelationships12[[#This Row],[Rank Pedro]]="High","linkCategory3",""))) | U13: =IF(TableRelationships12[[#This Row],[Rank Pedro]]="Low","Pink",IF(TableRelationships12[[#This Row],[Rank Pedro]]="Medium","Purple",IF(TableRelationships12[[#This Row],[Rank Pedro]]="High","Brown",""))) | V13: =MAX(INDEX(Standards!$F$2:$F$296,MATCH(B13,Standards!$B$2:$B$296,0)),INDEX(Standards!$F$2:$F$296,MATCH(C13,Standards!$B$2:$B$296,0))) -> #N/A | W13: =IF(M13="Normative", "#d6bf2a", IF(M13="Informative", "#2f89d1", 1)) -> #2f89d1
A14: 13 | B14: CEN ISO/TS 19139-1 | C14: ISO 19115-3 | E14: 2016.08 | F14: 2023.08 | G14: 35.240.70 | H14: =INDEX('GIS-Standards'!$A$2:$A$305,MATCH(B14,'GIS-Standards'!$B$2:$B$305,0)) -> #N/A | I14: =INDEX('GIS-Standards'!$A$2:$A$305,MATCH(C14,'GIS-Standards'!$B$2:$B$305,0)) -> 24 | J14: =INDEX('GIS-Standards'!$O$2:$O$305,MATCH(B14,'GIS-Standards'!$B$2:$B$305,0)) -> #N/A | K14: =INDEX('GIS-Standards'!$O$2:$O$305,MATCH(C14,'GIS-Standards'!$B$2:$B$305,0)) -> ISO/TC 211 | M14: Informative | N14: =INDEX('GIS-Standards'!$I$2:$I$305,MATCH(B14,'GIS-Standards'!$B$2:$B$305,0)) -> #N/A | O14: =INDEX('GIS-Standards'!$I$2:$I$305,MATCH(C14,'GIS-Standards'!$B$2:$B$305,0)) -> 0 | P14: =AND(TableRelationships12[[#This Row],[Source Type]]="BIM",TableRelationships12[[#This Row],[Target Type]]="BIM") -> #N/A | Q14: =IF(M14="Normative",6,IF(M14="Secondary",4,IF(M14="Anchor",2,1))) -> 1 | S14: =IF(R14="High",10,IF(R14="Medium",6,IF(R14="Low",2,1))) -> 1 | T14: =IF(TableRelationships12[[#This Row],[Rank Pedro]]="Low","linkCategory1",IF(TableRelationships12[[#This Row],[Rank Pedro]]="Medium","linkCategory2",IF(TableRelationships12[[#This Row],[Rank Pedro]]="High","linkCategory3",""))) | U14: =IF(TableRelationships12[[#This Row],[Rank Pedro]]="Low","Pink",IF(TableRelationships12[[#This Row],[Rank Pedro]]="Medium","Purple",IF(TableRelationships12[[#This Row],[Rank Pedro]]="High","Brown",""))) | V14: =MAX(INDEX(Standards!$F$2:$F$296,MATCH(B14,Standards!$B$2:$B$296,0)),INDEX(Standards!$F$2:$F$296,MATCH(C14,Standards!$B$2:$B$296,0))) -> #N/A | W14: =IF(M14="Normative", "#d6bf2a", IF(M14="Informative", "#2f89d1", 1)) -> #2f89d1
A15: 14 | B15: CEN ISO/TS 19139-1 | C15: ISO 19119 | E15: 2005.02 | F15: 2016.01 | G15: 35.240.70 | H15: =INDEX('GIS-Standards'!$A$2:$A$305,MATCH(B15,'GIS-Standards'!$B$2:$B$305,0)) -> #N/A | I15: =INDEX('GIS-Standards'!$A$2:$A$305,MATCH(C15,'GIS-Standards'!$B$2:$B$305,0)) -> 28 | J15: =INDEX('GIS-Standards'!$O$2:$O$305,MATCH(B15,'GIS-Standards'!$B$2:$B$305,0)) -> #N/A | K15: =INDEX('GIS-Standards'!$O$2:$O$305,MATCH(C15,'GIS-Standards'!$B$2:$B$305,0)) -> ISO/TC 211 | M15: Informative | N15: =INDEX('GIS-Standards'!$I$2:$I$305,MATCH(B15,'GIS-Standards'!$B$2:$B$305,0)) -> #N/A | O15: =INDEX('GIS-Standards'!$I$2:$I$305,MATCH(C15,'GIS-Standards'!$B$2:$B$305,0)) -> 0 | P15: =AND(TableRelationships12[[#This Row],[Source Type]]="BIM",TableRelationships12[[#This Row],[Target Type]]="BIM") -> #N/A | Q15: =IF(M15="Normative",6,IF(M15="Secondary",4,IF(M15="Anchor",2,1))) -> 1 | S15: =IF(R15="High",10,IF(R15="Medium",6,IF(R15="Low",2,1))) -> 1 | T15: =IF(TableRelationships12[[#This Row],[Rank Pedro]]="Low","linkCategory1",IF(TableRelationships12[[#This Row],[Rank Pedro]]="Medium","linkCategory2",IF(TableRelationships12[[#This Row],[Rank Pedro]]="High","linkCategory3",""))) | U15: =IF(TableRelationships12[[#This Row],[Rank Pedro]]="Low","Pink",IF(TableRelationships12[[#This Row],[Rank Pedro]]="Medium","Purple",IF(TableRelationships12[[#This Row],[Rank Pedro]]="High","Brown",""))) | V15: =MAX(INDEX(Standards!$F$2:$F$296,MATCH(B15,Standards!$B$2:$B$296,0)),INDEX(Standards!$F$2:$F$296,MATCH(C15,Standards!$B$2:$B$296,0))) -> #N/A | W15: =IF(M15="Normative", "#d6bf2a", IF(M15="Informative", "#2f89d1", 1)) -> #2f89d1
A16: 15 | B16: CEN ISO/TS 19139-1 | C16: ISO 19136-1 | D16: ISO 19136 | E16: 2007.09 | F16: 2020.01 | G16: 35.240.70 | H16: =INDEX('GIS-Standards'!$A$2:$A$305,MATCH(B16,'GIS-Standards'!$B$2:$B$305,0)) -> #N/A | I16: =INDEX('GIS-Standards'!$A$2:$A$305,MATCH(C16,'GIS-Standards'!$B$2:$B$305,0)) -> 42 | J16: =INDEX('GIS-Standards'!$O$2:$O$305,MATCH(B16,'GIS-Standards'!$B$2:$B$305,0)) -> #N/A | K16: =INDEX('GIS-Standards'!$O$2:$O$305,MATCH(C16,'GIS-Standards'!$B$2:$B$305,0)) -> ISO/TC 211 | M16: Informative | N16: =INDEX('GIS-Standards'!$I$2:$I$305,MATCH(B16,'GIS-Standards'!$B$2:$B$305,0)) -> #N/A | O16: =INDEX('GIS-Standards'!$I$2:$I$305,MATCH(C16,'GIS-Standards'!$B$2:$B$305,0)) -> 0 | P16: =AND(TableRelationships12[[#This Row],[Source Type]]="BIM",TableRelationships12[[#This Row],[Target Type]]="BIM") -> #N/A | Q16: =IF(M16="Normative",6,IF(M16="Secondary",4,IF(M16="Anchor",2,1))) -> 1 | S16: =IF(R16="High",10,IF(R16="Medium",6,IF(R16="Low",2,1))) -> 1 | T16: =IF(TableRelationships12[[#This Row],[Rank Pedro]]="Low","linkCategory1",IF(TableRelationships12[[#This Row],[Rank Pedro]]="Medium","linkCategory2",IF(TableRelationships12[[#This Row],[Rank Pedro]]="High","linkCategory3",""))) | U16: =IF(TableRelationships12[[#This Row],[Rank Pedro]]="Low","Pink",IF(TableRelationships12[[#This Row],[Rank Pedro]]="Medium","Purple",IF(TableRelationships12[[#This Row],[Rank Pedro]]="High","Brown",""))) | V16: =MAX(INDEX(Standards!$F$2:$F$296,MATCH(B16,Standards!$B$2:$B$296,0)),INDEX(Standards!$F$2:$F$296,MATCH(C16,Standards!$B$2:$B$296,0))) -> #N/A | W16: =IF(M16="Normative", "#d6bf2a", IF(M16="Informative", "#2f89d1", 1)) -> #2f89d1
A17: 16 | B17: CEN ISO/TS 19139-1 | C17: ISO 19157-1 | D17: ISO 19157 | E17: 2013.12 | F17: 2023.04 | G17: 35.240.70 | H17: =INDEX('GIS-Standards'!$A$2:$A$305,MATCH(B17,'GIS-Standards'!$B$2:$B$305,0)) -> #N/A | I17: =INDEX('GIS-Standards'!$A$2:$A$305,MATCH(C17,'GIS-Standards'!$B$2:$B$305,0)) -> 66 | J17: =INDEX('GIS-Standards'!$O$2:$O$305,MATCH(B17,'GIS-Standards'!$B$2:$B$305,0)) -> #N/A | K17: =INDEX('GIS-Standards'!$O$2:$O$305,MATCH(C17,'GIS-Standards'!$B$2:$B$305,0)) -> ISO/TC 211 | M17: Informative | N17: =INDEX('GIS-Standards'!$I$2:$I$305,MATCH(B17,'GIS-Standards'!$B$2:$B$305,0)) -> #N/A | O17: =INDEX('GIS-Standards'!$I$2:$I$305,MATCH(C17,'GIS-Standards'!$B$2:$B$305,0)) -> 0 | P17: =AND(TableRelationships12[[#This Row],[Source Type]]="BIM",TableRelationships12[[#This Row],[Target Type]]="BIM") -> #N/A | Q17: =IF(M17="Normative",6,IF(M17="Secondary",4,IF(M17="Anchor",2,1))) -> 1 | S17: =IF(R17="High",10,IF(R17="Medium",6,IF(R17="Low",2,1))) -> 1 | T17: =IF(TableRelationships12[[#This Row],[Rank Pedro]]="Low","linkCategory1",IF(TableRelationships12[[#This Row],[Rank Pedro]]="Medium","linkCategory2",IF(TableRelationships12[[#This Row],[Rank Pedro]]="High","linkCategory3",""))) | U17: =IF(TableRelationships12[[#This Row],[Rank Pedro]]="Low","Pink",IF(TableRelationships12[[#This Row],[Rank Pedro]]="Medium","Purple",IF(TableRelationships12[[#This Row],[Rank Pedro]]="High","Brown",""))) | V17: =MAX(INDEX(Standards!$F$2:$F$296,MATCH(B17,Standards!$B$2:$B$296,0)),INDEX(Standards!$F$2:$F$296,MATCH(C17,Standards!$B$2:$B$296,0))) -> #N/A | W17: =IF(M17="Normative", "#d6bf2a", IF(M17="Informative", "#2f89d1", 1)) -> #2f89d1
A18: 17 | B18: CEN ISO/TS 19139-1 | C18: ISO/TS 19157-2 | E18: 2016.12 | F18: 2016.12 | G18: 35.240.70 | H18: =INDEX('GIS-Standards'!$A$2:$A$305,MATCH(B18,'GIS-Standards'!$B$2:$B$305,0)) -> #N/A | I18: =INDEX('GIS-Standards'!$A$2:$A$305,MATCH(C18,'GIS-Standards'!$B$2:$B$305,0)) -> 105 | J18: =INDEX('GIS-Standards'!$O$2:$O$305,MATCH(B18,'GIS-Standards'!$B$2:$B$305,0)) -> #N/A | K18: =INDEX('GIS-Standards'!$O$2:$O$305,MATCH(C18,'GIS-Standards'!$B$2:$B$305,0)) -> ISO/TC 211 | M18: Informative | N18: =INDEX('GIS-Standards'!$I$2:$I$305,MATCH(B18,'GIS-Standards'!$B$2:$B$305,0)) -> #N/A | O18: =INDEX('GIS-Standards'!$I$2:$I$305,MATCH(C18,'GIS-Standards'!$B$2:$B$305,0)) -> 0 | P18: =AND(TableRelationships12[[#This Row],[Source Type]]="BIM",TableRelationships12[[#This Row],[Target Type]]="BIM") -> #N/A | Q18: =IF(M18="Normative",6,IF(M18="Secondary",4,IF(M18="Anchor",2,1))) -> 1 | S18: =IF(R18="High",10,IF(R18="Medium",6,IF(R18="Low",2,1))) -> 1 | T18: =IF(TableRelationships12[[#This Row],[Rank Pedro]]="Low","linkCategory1",IF(TableRelationships12[[#This Row],[Rank Pedro]]="Medium","linkCategory2",IF(TableRelationships12[[#This Row],[Rank Pedro]]="High","linkCategory3",""))) | U18: =IF(TableRelationships12[[#This Row],[Rank Pedro]]="Low","Pink",IF(TableRelationships12[[#This Row],[Rank Pedro]]="Medium","Purple",IF(TableRelationships12[[#This Row],[Rank Pedro]]="High","Brown",""))) | V18: =MAX(INDEX(Standards!$F$2:$F$296,MATCH(B18,Standards!$B$2:$B$296,0)),INDEX(Standards!$F$2:$F$296,MATCH(C18,Standards!$B$2:$B$296,0))) -> #N/A | W18: =IF(M18="Normative", "#d6bf2a", IF(M18="Informative", "#2f89d1", 1)) -> #2f89d1
A19: 18 | B19: CEN ISO/TS 19144-3 | C19: GIS anchor | E19: 2024.11 | F19: 2024.11 | G19: 35.240.70 | H19: =INDEX('GIS-Standards'!$A$2:$A$305,MATCH(B19,'GIS-Standards'!$B$2:$B$305,0)) -> #N/A | I19: =INDEX('GIS-Standards'!$A$2:$A$305,MATCH(C19,'GIS-Standards'!$B$2:$B$305,0)) -> #N/A | J19: =INDEX('GIS-Standards'!$O$2:$O$305,MATCH(B19,'GIS-Standards'!$B$2:$B$305,0)) -> #N/A | K19: =INDEX('GIS-Standards'!$O$2:$O$305,MATCH(C19,'GIS-Standards'!$B$2:$B$305,0)) -> #N/A | M19: Anchor | N19: =INDEX('GIS-Standards'!$I$2:$I$305,MATCH(B19,'GIS-Standards'!$B$2:$B$305,0)) -> #N/A | O19: =INDEX('GIS-Standards'!$I$2:$I$305,MATCH(C19,'GIS-Standards'!$B$2:$B$305,0)) -> #N/A | P19: =AND(TableRelationships12[[#This Row],[Source Type]]="BIM",TableRelationships12[[#This Row],[Target Type]]="BIM") -> #N/A | Q19: =IF(M19="Normative",6,IF(M19="Secondary",4,IF(M19="Anchor",2,1))) -> 2 | S19: =IF(R19="High",10,IF(R19="Medium",6,IF(R19="Low",2,1))) -> 1 | T19: =IF(TableRelationships12[[#This Row],[Rank Pedro]]="Low","linkCategory1",IF(TableRelationships12[[#This Row],[Rank Pedro]]="Medium","linkCategory2",IF(TableRelationships12[[#This Row],[Rank Pedro]]="High","linkCategory3",""))) | U19: =IF(TableRelationships12[[#This Row],[Rank Pedro]]="Low","Pink",IF(TableRelationships12[[#This Row],[Rank Pedro]]="Medium","Purple",IF(TableRelationships12[[#This Row],[Rank Pedro]]="High","Brown",""))) | V19: =MAX(INDEX(Standards!$F$2:$F$296,MATCH(B19,Standards!$B$2:$B$296,0)),INDEX(Standards!$F$2:$F$296,MATCH(C19,Standards!$B$2:$B$296,0))) -> #N/A | W19: =IF(M19="Normative", "#d6bf2a", IF(M19="Informative", "#2f89d1", 1)) -> 1
A20: 19 | B20: CEN ISO/TS 19144-3 | C20: ISO 19103 | E20: 2005.07 | F20: 2024.09 | G20: 35.240.70 | H20: =INDEX('GIS-Standards'!$A$2:$A$305,MATCH(B20,'GIS-Standards'!$B$2:$B$305,0)) -> #N/A | I20: =INDEX('GIS-Standards'!$A$2:$A$305,MATCH(C20,'GIS-Standards'!$B$2:$B$305,0)) -> 12 | J20: =INDEX('GIS-Standards'!$O$2:$O$305,MATCH(B20,'GIS-Standards'!$B$2:$B$305,0)) -> #N/A | K20: =INDEX('GIS-Standards'!$O$2:$O$305,MATCH(C20,'GIS-Standards'!$B$2:$B$305,0)) -> ISO/TC 211 | M20: Normative | N20: =INDEX('GIS-Standards'!$I$2:$I$305,MATCH(B20,'GIS-Standards'!$B$2:$B$305,0)) -> #N/A | O20: =INDEX('GIS-Standards'!$I$2:$I$305,MATCH(C20,'GIS-Standards'!$B$2:$B$305,0)) -> 0 | P20: =AND(TableRelationships12[[#This Row],[Source Type]]="BIM",TableRelationships12[[#This Row],[Target Type]]="BIM") -> #N/A | Q20: =IF(M20="Normative",6,IF(M20="Secondary",4,IF(M20="Anchor",2,1))) -> 6 | S20: =IF(R20="High",10,IF(R20="Medium",6,IF(R20="Low",2,1))) -> 1 | T20: =IF(TableRelationships12[[#This Row],[Rank Pedro]]="Low","linkCategory1",IF(TableRelationships12[[#This Row],[Rank Pedro]]="Medium","linkCategory2",IF(TableRelationships12[[#This Row],[Rank Pedro]]="High","linkCategory3",""))) | U20: =IF(TableRelationships12[[#This Row],[Rank Pedro]]="Low","Pink",IF(TableRelationships12[[#This Row],[Rank Pedro]]="Medium","Purple",IF(TableRelationships12[[#This Row],[Rank Pedro]]="High","Brown",""))) | V20: =MAX(INDEX(Standards!$F$2:$F$296,MATCH(B20,Standards!$B$2:$B$296,0)),INDEX(Standards!$F$2:$F$296,MATCH(C20,Standards!$B$2:$B$296,0))) -> #N/A | W20: =IF(M20="Normative", "#d6bf2a", IF(M20="Informative", "#2f89d1", 1)) -> #d6bf2a
A21: 20 | B21: CEN ISO/TS 19144-3 | C21: ISO 19123-1 | E21: 2005.08 | F21: 2023.06 | G21: 35.240.70 | H21: =INDEX('GIS-Standards'!$A$2:$A$305,MATCH(B21,'GIS-Standards'!$B$2:$B$305,0)) -> #N/A | I21: =INDEX('GIS-Standards'!$A$2:$A$305,MATCH(C21,'GIS-Standards'!$B$2:$B$305,0)) -> 29 | J21: =INDEX('GIS-Standards'!$O$2:$O$305,MATCH(B21,'GIS-Standards'!$B$2:$B$305,0)) -> #N/A | K21: =INDEX('GIS-Standards'!$O$2:$O$305,MATCH(C21,'GIS-Standards'!$B$2:$B$305,0)) -> ISO/TC 211 | M21: Normative | N21: =INDEX('GIS-Standards'!$I$2:$I$305,MATCH(B21,'GIS-Standards'!$B$2:$B$305,0)) -> #N/A | O21: =INDEX('GIS-Standards'!$I$2:$I$305,MATCH(C21,'GIS-Standards'!$B$2:$B$305,0)) -> 0 | P21: =AND(TableRelationships12[[#This Row],[Source Type]]="BIM",TableRelationships12[[#This Row],[Target Type]]="BIM") -> #N/A | Q21: =IF(M21="Normative",6,IF(M21="Secondary",4,IF(M21="Anchor",2,1))) -> 6 | S21: =IF(R21="High",10,IF(R21="Medium",6,IF(R21="Low",2,1))) -> 1 | T21: =IF(TableRelationships12[[#This Row],[Rank Pedro]]="Low","linkCategory1",IF(TableRelationships12[[#This Row],[Rank Pedro]]="Medium","linkCategory2",IF(TableRelationships12[[#This Row],[Rank Pedro]]="High","linkCategory3",""))) | U21: =IF(TableRelationships12[[#This Row],[Rank Pedro]]="Low","Pink",IF(TableRelationships12[[#This Row],[Rank Pedro]]="Medium","Purple",IF(TableRelationships12[[#This Row],[Rank Pedro]]="High","Brown",""))) | V21: =MAX(INDEX(Standards!$F$2:$F$296,MATCH(B21,Standards!$B$2:$B$296,0)),INDEX(Standards!$F$2:$F$296,MATCH(C21,Standards!$B$2:$B$296,0))) -> #N/A | W21: =IF(M21="Normative", "#d6bf2a", IF(M21="Informative", "#2f89d1", 1)) -> #d6bf2a
A22: 21 | B22: CEN ISO/TS 19144-3 | C22: ISO 19144-1 | E22: 2009.09 | F22: 2012.08 | G22: 35.240.70 | H22: =INDEX('GIS-Standards'!$A$2:$A$305,MATCH(B22,'GIS-Standards'!$B$2:$B$305,0)) -> #N/A | I22: =INDEX('GIS-Standards'!$A$2:$A$305,MATCH(C22,'GIS-Standards'!$B$2:$B$305,0)) -> 48 | J22: =INDEX('GIS-Standards'!$O$2:$O$305,MATCH(B22,'GIS-Standards'!$B$2:$B$305,0)) -> #N/A | K22: =INDEX('GIS-Standards'!$O$2:$O$305,MATCH(C22,'GIS-Standards'!$B$2:$B$305,0)) -> ISO/TC 211 | M22: Normative | N22: =INDEX('GIS-Standards'!$I$2:$I$305,MATCH(B22,'GIS-Standards'!$B$2:$B$305,0)) -> #N/A | O22: =INDEX('GIS-Standards'!$I$2:$I$305,MATCH(C22,'GIS-Standards'!$B$2:$B$305,0)) -> 08.2012 | P22: =AND(TableRelationships12[[#This Row],[Source Type]]="BIM",TableRelationships12[[#This Row],[Target Type]]="BIM") -> #N/A | Q22: =IF(M22="Normative",6,IF(M22="Secondary",4,IF(M22="Anchor",2,1))) -> 6 | S22: =IF(R22="High",10,IF(R22="Medium",6,IF(R22="Low",2,1))) -> 1 | T22: =IF(TableRelationships12[[#This Row],[Rank Pedro]]="Low","linkCategory1",IF(TableRelationships12[[#This Row],[Rank Pedro]]="Medium","linkCategory2",IF(TableRelationships12[[#This Row],[Rank Pedro]]="High","linkCategory3",""))) | U22: =IF(TableRelationships12[[#This Row],[Rank Pedro]]="Low","Pink",IF(TableRelationships12[[#This Row],[Rank Pedro]]="Medium","Purple",IF(TableRelationships12[[#This Row],[Rank Pedro]]="High","Brown",""))) | V22: =MAX(INDEX(Standards!$F$2:$F$296,MATCH(B22,Standards!$B$2:$B$296,0)),INDEX(Standards!$F$2:$F$296,MATCH(C22,Standards!$B$2:$B$296,0))) -> #N/A | W22: =IF(M22="Normative", "#d6bf2a", IF(M22="Informative", "#2f89d1", 1)) -> #d6bf2a
A23: 22 | B23: CEN ISO/TS 19144-3 | C23: ISO 19144-2 | E23: 2012.07 | F23: 2023.12 | G23: 35.240.70 | H23: =INDEX('GIS-Standards'!$A$2:$A$305,MATCH(B23,'GIS-Standards'!$B$2:$B$305,0)) -> #N/A | I23: =INDEX('GIS-Standards'!$A$2:$A$305,MATCH(C23,'GIS-Standards'!$B$2:$B$305,0)) -> 49 | J23: =INDEX('GIS-Standards'!$O$2:$O$305,MATCH(B23,'GIS-Standards'!$B$2:$B$305,0)) -> #N/A | K23: =INDEX('GIS-Standards'!$O$2:$O$305,MATCH(C23,'GIS-Standards'!$B$2:$B$305,0)) -> ISO/TC 211 | M23: Normative | N23: =INDEX('GIS-Standards'!$I$2:$I$305,MATCH(B23,'GIS-Standards'!$B$2:$B$305,0)) -> #N/A | O23: =INDEX('GIS-Standards'!$I$2:$I$305,MATCH(C23,'GIS-Standards'!$B$2:$B$305,0)) -> 0 | P23: =AND(TableRelationships12[[#This Row],[Source Type]]="BIM",TableRelationships12[[#This Row],[Target Type]]="BIM") -> #N/A | Q23: =IF(M23="Normative",6,IF(M23="Secondary",4,IF(M23="Anchor",2,1))) -> 6 | S23: =IF(R23="High",10,IF(R23="Medium",6,IF(R23="Low",2,1))) -> 1 | T23: =IF(TableRelationships12[[#This Row],[Rank Pedro]]="Low","linkCategory1",IF(TableRelationships12[[#This Row],[Rank Pedro]]="Medium","linkCategory2",IF(TableRelationships12[[#This Row],[Rank Pedro]]="High","linkCategory3",""))) | U23: =IF(TableRelationships12[[#This Row],[Rank Pedro]]="Low","Pink",IF(TableRelationships12[[#This Row],[Rank Pedro]]="Medium","Purple",IF(TableRelationships12[[#This Row],[Rank Pedro]]="High","Brown",""))) | V23: =MAX(INDEX(Standards!$F$2:$F$296,MATCH(B23,Standards!$B$2:$B$296,0)),INDEX(Standards!$F$2:$F$296,MATCH(C23,Standards!$B$2:$B$296,0))) -> #N/A | W23: =IF(M23="Normative", "#d6bf2a", IF(M23="Informative", "#2f89d1", 1)) -> #d6bf2a
A24: 23 | B24: CEN ISO/TS 19144-3 | C24: ISO 19101-1 | E24: 2002.07 | F24: 2014.11 | G24: 35.240.70 | H24: =INDEX('GIS-Standards'!$A$2:$A$305,MATCH(B24,'GIS-Standards'!$B$2:$B$305,0)) -> #N/A | I24: =INDEX('GIS-Standards'!$A$2:$A$305,MATCH(C24,'GIS-Standards'!$B$2:$B$305,0)) -> 10 | J24: =INDEX('GIS-Standards'!$O$2:$O$305,MATCH(B24,'GIS-Standards'!$B$2:$B$305,0)) -> #N/A | K24: =INDEX('GIS-Standards'!$O$2:$O$305,MATCH(C24,'GIS-Standards'!$B$2:$B$305,0)) -> ISO/TC 211 | M24: Informative | N24: =INDEX('GIS-Standards'!$I$2:$I$305,MATCH(B24,'GIS-Standards'!$B$2:$B$305,0)) -> #N/A | O24: =INDEX('GIS-Standards'!$I$2:$I$305,MATCH(C24,'GIS-Standards'!$B$2:$B$305,0)) -> 0 | P24: =AND(TableRelationships12[[#This Row],[Source Type]]="BIM",TableRelationships12[[#This Row],[Target Type]]="BIM") -> #N/A | Q24: =IF(M24="Normative",6,IF(M24="Secondary",4,IF(M24="Anchor",2,1))) -> 1 | S24: =IF(R24="High",10,IF(R24="Medium",6,IF(R24="Low",2,1))) -> 1 | T24: =IF(TableRelationships12[[#This Row],[Rank Pedro]]="Low","linkCategory1",IF(TableRelationships12[[#This Row],[Rank Pedro]]="Medium","linkCategory2",IF(TableRelationships12[[#This Row],[Rank Pedro]]="High","linkCategory3",""))) | U24: =IF(TableRelationships12[[#This Row],[Rank Pedro]]="Low","Pink",IF(TableRelationships12[[#This Row],[Rank Pedro]]="Medium","Purple",IF(TableRelationships12[[#This Row],[Rank Pedro]]="High","Brown",""))) | V24: =MAX(INDEX(Standards!$F$2:$F$296,MATCH(B24,Standards!$B$2:$B$296,0)),INDEX(Standards!$F$2:$F$296,MATCH(C24,Standards!$B$2:$B$296,0))) -> #N/A | W24: =IF(M24="Normative", "#d6bf2a", IF(M24="Informative", "#2f89d1", 1)) -> #2f89d1
A25: 24 | B25: CEN ISO/TS 19144-3 | C25: ISO 19105 | E25: 2000.12 | F25: 2022.07 | G25: 35.240.70 | H25: =INDEX('GIS-Standards'!$A$2:$A$305,MATCH(B25,'GIS-Standards'!$B$2:$B$305,0)) -> #N/A | I25: =INDEX('GIS-Standards'!$A$2:$A$305,MATCH(C25,'GIS-Standards'!$B$2:$B$305,0)) -> 14 | J25: =INDEX('GIS-Standards'!$O$2:$O$305,MATCH(B25,'GIS-Standards'!$B$2:$B$305,0)) -> #N/A | K25: =INDEX('GIS-Standards'!$O$2:$O$305,MATCH(C25,'GIS-Standards'!$B$2:$B$305,0)) -> ISO/TC 211 | M25: Informative | N25: =INDEX('GIS-Standards'!$I$2:$I$305,MATCH(B25,'GIS-Standards'!$B$2:$B$305,0)) -> #N/A | O25: =INDEX('GIS-Standards'!$I$2:$I$305,MATCH(C25,'GIS-Standards'!$B$2:$B$305,0)) -> 0 | P25: =AND(TableRelationships12[[#This Row],[Source Type]]="BIM",TableRelationships12[[#This Row],[Target Type]]="BIM") -> #N/A | Q25: =IF(M25="Normative",6,IF(M25="Secondary",4,IF(M25="Anchor",2,1))) -> 1 | S25: =IF(R25="High",10,IF(R25="Medium",6,IF(R25="Low",2,1))) -> 1 | T25: =IF(TableRelationships12[[#This Row],[Rank Pedro]]="Low","linkCategory1",IF(TableRelationships12[[#This Row],[Rank Pedro]]="Medium","linkCategory2",IF(TableRelationships12[[#This Row],[Rank Pedro]]="High","linkCategory3",""))) | U25: =IF(TableRelationships12[[#This Row],[Rank Pedro]]="Low","Pink",IF(TableRelationships12[[#This Row],[Rank Pedro]]="Medium","Purple",IF(TableRelationships12[[#This Row],[Rank Pedro]]="High","Brown",""))) | V25: =MAX(INDEX(Standards!$F$2:$F$296,MATCH(B25,Standards!$B$2:$B$296,0)),INDEX(Standards!$F$2:$F$296,MATCH(C25,Standards!$B$2:$B$296,0))) -> #N/A | W25: =IF(M25="Normative", "#d6bf2a", IF(M25="Informative", "#2f89d1", 1)) -> #2f89d1
A26: 25 | B26: CEN ISO/TS 19144-3 | C26: ISO 19135-1 | E26: 2005.1 | F26: 2021.02 | G26: 35.240.70 | H26: =INDEX('GIS-Standards'!$A$2:$A$305,MATCH(B26,'GIS-Standards'!$B$2:$B$305,0)) -> #N/A | I26: =INDEX('GIS-Standards'!$A$2:$A$305,MATCH(C26,'GIS-Standards'!$B$2:$B$305,0)) -> 41 | J26: =INDEX('GIS-Standards'!$O$2:$O$305,MATCH(B26,'GIS-Standards'!$B$2:$B$305,0)) -> #N/A | K26: =INDEX('GIS-Standards'!$O$2:$O$305,MATCH(C26,'GIS-Standards'!$B$2:$B$305,0)) -> ISO/TC 211 | M26: Informative | N26: =INDEX('GIS-Standards'!$I$2:$I$305,MATCH(B26,'GIS-Standards'!$B$2:$B$305,0)) -> #N/A | O26: =INDEX('GIS-Standards'!$I$2:$I$305,MATCH(C26,'GIS-Standards'!$B$2:$B$305,0)) -> 03.2021 | P26: =AND(TableRelationships12[[#This Row],[Source Type]]="BIM",TableRelationships12[[#This Row],[Target Type]]="BIM") -> #N/A | Q26: =IF(M26="Normative",6,IF(M26="Secondary",4,IF(M26="Anchor",2,1))) -> 1 | S26: =IF(R26="High",10,IF(R26="Medium",6,IF(R26="Low",2,1))) -> 1 | T26: =IF(TableRelationships12[[#This Row],[Rank Pedro]]="Low","linkCategory1",IF(TableRelationships12[[#This Row],[Rank Pedro]]="Medium","linkCategory2",IF(TableRelationships12[[#This Row],[Rank Pedro]]="High","linkCategory3",""))) | U26: =IF(TableRelationships12[[#This Row],[Rank Pedro]]="Low","Pink",IF(TableRelationships12[[#This Row],[Rank Pedro]]="Medium","Purple",IF(TableRelationships12[[#This Row],[Rank Pedro]]="High","Brown",""))) | V26: =MAX(INDEX(Standards!$F$2:$F$296,MATCH(B26,Standards!$B$2:$B$296,0)),INDEX(Standards!$F$2:$F$296,MATCH(C26,Standards!$B$2:$B$296,0))) -> #N/A | W26: =IF(M26="Normative", "#d6bf2a", IF(M26="Informative", "#2f89d1", 1)) -> #2f89d1
A27: 26 | B27: CEN ISO/TS 19144-3 | C27: ISO/CD TS 19144-4 | D27: under development | E27: 2026.xx | F27: 2026.xx | G27: 35.240.70 | H27: =INDEX('GIS-Standards'!$A$2:$A$305,MATCH(B27,'GIS-Standards'!$B$2:$B$305,0)) -> #N/A | I27: =INDEX('GIS-Standards'!$A$2:$A$305,MATCH(C27,'GIS-Standards'!$B$2:$B$305,0)) -> #N/A | J27: =INDEX('GIS-Standards'!$O$2:$O$305,MATCH(B27,'GIS-Standards'!$B$2:$B$305,0)) -> #N/A | K27: =INDEX('GIS-Standards'!$O$2:$O$305,MATCH(C27,'GIS-Standards'!$B$2:$B$305,0)) -> #N/A | M27: Informative | N27: =INDEX('GIS-Standards'!$I$2:$I$305,MATCH(B27,'GIS-Standards'!$B$2:$B$305,0)) -> #N/A | O27: =INDEX('GIS-Standards'!$I$2:$I$305,MATCH(C27,'GIS-Standards'!$B$2:$B$305,0)) -> #N/A | P27: =AND(TableRelationships12[[#This Row],[Source Type]]="BIM",TableRelationships12[[#This Row],[Target Type]]="BIM") -> #N/A | Q27: =IF(M27="Normative",6,IF(M27="Secondary",4,IF(M27="Anchor",2,1))) -> 1 | S27: =IF(R27="High",10,IF(R27="Medium",6,IF(R27="Low",2,1))) -> 1 | T27: =IF(TableRelationships12[[#This Row],[Rank Pedro]]="Low","linkCategory1",IF(TableRelationships12[[#This Row],[Rank Pedro]]="Medium","linkCategory2",IF(TableRelationships12[[#This Row],[Rank Pedro]]="High","linkCategory3",""))) | U27: =IF(TableRelationships12[[#This Row],[Rank Pedro]]="Low","Pink",IF(TableRelationships12[[#This Row],[Rank Pedro]]="Medium","Purple",IF(TableRelationships12[[#This Row],[Rank Pedro]]="High","Brown",""))) | V27: =MAX(INDEX(Standards!$F$2:$F$296,MATCH(B27,Standards!$B$2:$B$296,0)),INDEX(Standards!$F$2:$F$296,MATCH(C27,Standards!$B$2:$B$296,0))) -> #N/A | W27: =IF(M27="Normative", "#d6bf2a", IF(M27="Informative", "#2f89d1", 1)) -> #2f89d1
A28: 27 | B28: CEN ISO/TS 19144-3 | C28: ISO 19152-1 | E28: 2012.12 | F28: 2024.01 | G28: 35.240.70 | H28: =INDEX('GIS-Standards'!$A$2:$A$305,MATCH(B28,'GIS-Standards'!$B$2:$B$305,0)) -> #N/A | I28: =INDEX('GIS-Standards'!$A$2:$A$305,MATCH(C28,'GIS-Standards'!$B$2:$B$305,0)) -> 57 | J28: =INDEX('GIS-Standards'!$O$2:$O$305,MATCH(B28,'GIS-Standards'!$B$2:$B$305,0)) -> #N/A | K28: =INDEX('GIS-Standards'!$O$2:$O$305,MATCH(C28,'GIS-Standards'!$B$2:$B$305,0)) -> ISO/TC 211 | M28: Informative | N28: =INDEX('GIS-Standards'!$I$2:$I$305,MATCH(B28,'GIS-Standards'!$B$2:$B$305,0)) -> #N/A | O28: =INDEX('GIS-Standards'!$I$2:$I$305,MATCH(C28,'GIS-Standards'!$B$2:$B$305,0)) -> 0 | P28: =AND(TableRelationships12[[#This Row],[Source Type]]="BIM",TableRelationships12[[#This Row],[Target Type]]="BIM") -> #N/A | Q28: =IF(M28="Normative",6,IF(M28="Secondary",4,IF(M28="Anchor",2,1))) -> 1 | S28: =IF(R28="High",10,IF(R28="Medium",6,IF(R28="Low",2,1))) -> 1 | T28: =IF(TableRelationships12[[#This Row],[Rank Pedro]]="Low","linkCategory1",IF(TableRelationships12[[#This Row],[Rank Pedro]]="Medium","linkCategory2",IF(TableRelationships12[[#This Row],[Rank Pedro]]="High","linkCategory3",""))) | U28: =IF(TableRelationships12[[#This Row],[Rank Pedro]]="Low","Pink",IF(TableRelationships12[[#This Row],[Rank Pedro]]="Medium","Purple",IF(TableRelationships12[[#This Row],[Rank Pedro]]="High","Brown",""))) | V28: =MAX(INDEX(Standards!$F$2:$F$296,MATCH(B28,Standards!$B$2:$B$296,0)),INDEX(Standards!$F$2:$F$296,MATCH(C28,Standards!$B$2:$B$296,0))) -> #N/A | W28: =IF(M28="Normative", "#d6bf2a", IF(M28="Informative", "#2f89d1", 1)) -> #2f89d1
A29: 28 | B29: CEN ISO/TS 19144-3 | C29: APA LBCS | H29: =INDEX('GIS-Standards'!$A$2:$A$305,MATCH(B29,'GIS-Standards'!$B$2:$B$305,0)) -> #N/A | I29: =INDEX('GIS-Standards'!$A$2:$A$305,MATCH(C29,'GIS-Standards'!$B$2:$B$305,0)) -> #N/A | J29: =INDEX('GIS-Standards'!$O$2:$O$305,MATCH(B29,'GIS-Standards'!$B$2:$B$305,0)) -> #N/A | K29: =INDEX('GIS-Standards'!$O$2:$O$305,MATCH(C29,'GIS-Standards'!$B$2:$B$305,0)) -> #N/A | M29: Informative | N29: =INDEX('GIS-Standards'!$I$2:$I$305,MATCH(B29,'GIS-Standards'!$B$2:$B$305,0)) -> #N/A | O29: =INDEX('GIS-Standards'!$I$2:$I$305,MATCH(C29,'GIS-Standards'!$B$2:$B$305,0)) -> #N/A | P29: =AND(TableRelationships12[[#This Row],[Source Type]]="BIM",TableRelationships12[[#This Row],[Target Type]]="BIM") -> #N/A | Q29: =IF(M29="Normative",6,IF(M29="Secondary",4,IF(M29="Anchor",2,1))) -> 1 | S29: =IF(R29="High",10,IF(R29="Medium",6,IF(R29="Low",2,1))) -> 1 | T29: =IF(TableRelationships12[[#This Row],[Rank Pedro]]="Low","linkCategory1",IF(TableRelationships12[[#This Row],[Rank Pedro]]="Medium","linkCategory2",IF(TableRelationships12[[#This Row],[Rank Pedro]]="High","linkCategory3",""))) | U29: =IF(TableRelationships12[[#This Row],[Rank Pedro]]="Low","Pink",IF(TableRelationships12[[#This Row],[Rank Pedro]]="Medium","Purple",IF(TableRelationships12[[#This Row],[Rank Pedro]]="High","Brown",""))) | V29: =MAX(INDEX(Standards!$F$2:$F$296,MATCH(B29,Standards!$B$2:$B$296,0)),INDEX(Standards!$F$2:$F$296,MATCH(C29,Standards!$B$2:$B$296,0))) -> #N/A | W29: =IF(M29="Normative", "#d6bf2a", IF(M29="Informative", "#2f89d1", 1)) -> #2f89d1
A30: 29 | B30: CEN ISO/TS 19144-3 | C30: OMG UML 2.5.1 | H30: =INDEX('GIS-Standards'!$A$2:$A$305,MATCH(B30,'GIS-Standards'!$B$2:$B$305,0)) -> #N/A | I30: =INDEX('GIS-Standards'!$A$2:$A$305,MATCH(C30,'GIS-Standards'!$B$2:$B$305,0)) -> #N/A | J30: =INDEX('GIS-Standards'!$O$2:$O$305,MATCH(B30,'GIS-Standards'!$B$2:$B$305,0)) -> #N/A | K30: =INDEX('GIS-Standards'!$O$2:$O$305,MATCH(C30,'GIS-Standards'!$B$2:$B$305,0)) -> #N/A | M30: Informative | N30: =INDEX('GIS-Standards'!$I$2:$I$305,MATCH(B30,'GIS-Standards'!$B$2:$B$305,0)) -> #N/A | O30: =INDEX('GIS-Standards'!$I$2:$I$305,MATCH(C30,'GIS-Standards'!$B$2:$B$305,0)) -> #N/A | P30: =AND(TableRelationships12[[#This Row],[Source Type]]="BIM",TableRelationships12[[#This Row],[Target Type]]="BIM") -> #N/A | Q30: =IF(M30="Normative",6,IF(M30="Secondary",4,IF(M30="Anchor",2,1))) -> 1 | S30: =IF(R30="High",10,IF(R30="Medium",6,IF(R30="Low",2,1))) -> 1 | T30: =IF(TableRelationships12[[#This Row],[Rank Pedro]]="Low","linkCategory1",IF(TableRelationships12[[#This Row],[Rank Pedro]]="Medium","linkCategory2",IF(TableRelationships12[[#This Row],[Rank Pedro]]="High","linkCategory3",""))) | U30: =IF(TableRelationships12[[#This Row],[Rank Pedro]]="Low","Pink",IF(TableRelationships12[[#This Row],[Rank Pedro]]="Medium","Purple",IF(TableRelationships12[[#This Row],[Rank Pedro]]="High","Brown",""))) | V30: =MAX(INDEX(Standards!$F$2:$F$296,MATCH(B30,Standards!$B$2:$B$296,0)),INDEX(Standards!$F$2:$F$296,MATCH(C30,Standards!$B$2:$B$296,0))) -> #N/A | W30: =IF(M30="Normative", "#d6bf2a", IF(M30="Informative", "#2f89d1", 1)) -> #2f89d1
A31: 30 | B31: CEN/TR 15449-1 | C31: GIS anchor | E31: 2012.10 | F31: 2012.10 | G31: 35.240.70; 07.040 | H31: =INDEX('GIS-Standards'!$A$2:$A$305,MATCH(B31,'GIS-Standards'!$B$2:$B$305,0)) -> 1 | I31: =INDEX('GIS-Standards'!$A$2:$A$305,MATCH(C31,'GIS-Standards'!$B$2:$B$305,0)) -> #N/A | J31: =INDEX('GIS-Standards'!$O$2:$O$305,MATCH(B31,'GIS-Standards'!$B$2:$B$305,0)) -> 0 | K31: =INDEX('GIS-Standards'!$O$2:$O$305,MATCH(C31,'GIS-Standards'!$B$2:$B$305,0)) -> #N/A | M31: Anchor | N31: =INDEX('GIS-Standards'!$I$2:$I$305,MATCH(B31,'GIS-Standards'!$B$2:$B$305,0)) -> 0 | O31: =INDEX('GIS-Standards'!$I$2:$I$305,MATCH(C31,'GIS-Standards'!$B$2:$B$305,0)) -> #N/A | P31: =AND(TableRelationships12[[#This Row],[Source Type]]="BIM",TableRelationships12[[#This Row],[Target Type]]="BIM") -> #N/A | Q31: =IF(M31="Normative",6,IF(M31="Secondary",4,IF(M31="Anchor",2,1))) -> 2 | S31: =IF(R31="High",10,IF(R31="Medium",6,IF(R31="Low",2,1))) -> 1 | T31: =IF(TableRelationships12[[#This Row],[Rank Pedro]]="Low","linkCategory1",IF(TableRelationships12[[#This Row],[Rank Pedro]]="Medium","linkCategory2",IF(TableRelationships12[[#This Row],[Rank Pedro]]="High","linkCategory3",""))) | U31: =IF(TableRelationships12[[#This Row],[Rank Pedro]]="Low","Pink",IF(TableRelationships12[[#This Row],[Rank Pedro]]="Medium","Purple",IF(TableRelationships12[[#This Row],[Rank Pedro]]="High","Brown",""))) | V31: =MAX(INDEX(Standards!$F$2:$F$296,MATCH(B31,Standards!$B$2:$B$296,0)),INDEX(Standards!$F$2:$F$296,MATCH(C31,Standards!$B$2:$B$296,0))) -> #N/A | W31: =IF(M31="Normative", "#d6bf2a", IF(M31="Informative", "#2f89d1", 1)) -> 1
A32: 31 | B32: CEN/TR 15449-2 | C32: GIS anchor | E32: 2012.10 | F32: 2012.10 | G32: 35.240.70; 07.040 | H32: =INDEX('GIS-Standards'!$A$2:$A$305,MATCH(B32,'GIS-Standards'!$B$2:$B$305,0)) -> 2 | I32: =INDEX('GIS-Standards'!$A$2:$A$305,MATCH(C32,'GIS-Standards'!$B$2:$B$305,0)) -> #N/A | J32: =INDEX('GIS-Standards'!$O$2:$O$305,MATCH(B32,'GIS-Standards'!$B$2:$B$305,0)) -> 0 | K32: =INDEX('GIS-Standards'!$O$2:$O$305,MATCH(C32,'GIS-Standards'!$B$2:$B$305,0)) -> #N/A | M32: Anchor | N32: =INDEX('GIS-Standards'!$I$2:$I$305,MATCH(B32,'GIS-Standards'!$B$2:$B$305,0)) -> 0 | O32: =INDEX('GIS-Standards'!$I$2:$I$305,MATCH(C32,'GIS-Standards'!$B$2:$B$305,0)) -> #N/A | P32: =AND(TableRelationships12[[#This Row],[Source Type]]="BIM",TableRelationships12[[#This Row],[Target Type]]="BIM") -> #N/A | Q32: =IF(M32="Normative",6,IF(M32="Secondary",4,IF(M32="Anchor",2,1))) -> 2 | S32: =IF(R32="High",10,IF(R32="Medium",6,IF(R32="Low",2,1))) -> 1 | T32: =IF(TableRelationships12[[#This Row],[Rank Pedro]]="Low","linkCategory1",IF(TableRelationships12[[#This Row],[Rank Pedro]]="Medium","linkCategory2",IF(TableRelationships12[[#This Row],[Rank Pedro]]="High","linkCategory3",""))) | U32: =IF(TableRelationships12[[#This Row],[Rank Pedro]]="Low","Pink",IF(TableRelationships12[[#This Row],[Rank Pedro]]="Medium","Purple",IF(TableRelationships12[[#This Row],[Rank Pedro]]="High","Brown",""))) | V32: =MAX(INDEX(Standards!$F$2:$F$296,MATCH(B32,Standards!$B$2:$B$296,0)),INDEX(Standards!$F$2:$F$296,MATCH(C32,Standards!$B$2:$B$296,0))) -> #N/A | W32: =IF(M32="Normative", "#d6bf2a", IF(M32="Informative", "#2f89d1", 1)) -> 1
A33: 32 | B33: CEN/TR 15449-2 | C33: ISO 19115-1 | D33: ISO 19115 | E33: 2003.05 | F33: 2020.11 | G33: 35.240.70 | H33: =INDEX('GIS-Standards'!$A$2:$A$305,MATCH(B33,'GIS-Standards'!$B$2:$B$305,0)) -> 2 | I33: =INDEX('GIS-Standards'!$A$2:$A$305,MATCH(D33,'GIS-Standards'!$B$2:$B$305,0)) -> #N/A | J33: =INDEX('GIS-Standards'!$O$2:$O$305,MATCH(B33,'GIS-Standards'!$B$2:$B$305,0)) -> 0 | K33: =INDEX('GIS-Standards'!$O$2:$O$305,MATCH(D33,'GIS-Standards'!$B$2:$B$305,0)) -> #N/A | M33: Normative | N33: =INDEX('GIS-Standards'!$I$2:$I$305,MATCH(B33,'GIS-Standards'!$B$2:$B$305,0)) -> 0 | O33: =INDEX('GIS-Standards'!$I$2:$I$305,MATCH(D33,'GIS-Standards'!$B$2:$B$305,0)) -> #N/A | P33: =AND(TableRelationships12[[#This Row],[Source Type]]="BIM",TableRelationships12[[#This Row],[Target Type]]="BIM") -> #N/A | Q33: =IF(M33="Normative",6,IF(M33="Secondary",4,IF(M33="Anchor",2,1))) -> 6 | S33: =IF(R33="High",10,IF(R33="Medium",6,IF(R33="Low",2,1))) -> 1 | T33: =IF(TableRelationships12[[#This Row],[Rank Pedro]]="Low","linkCategory1",IF(TableRelationships12[[#This Row],[Rank Pedro]]="Medium","linkCategory2",IF(TableRelationships12[[#This Row],[Rank Pedro]]="High","linkCategory3",""))) | U33: =IF(TableRelationships12[[#This Row],[Rank Pedro]]="Low","Pink",IF(TableRelationships12[[#This Row],[Rank Pedro]]="Medium","Purple",IF(TableRelationships12[[#This Row],[Rank Pedro]]="High","Brown",""))) | V33: =MAX(INDEX(Standards!$F$2:$F$296,MATCH(B33,Standards!$B$2:$B$296,0)),INDEX(Standards!$F$2:$F$296,MATCH(D33,Standards!$B$2:$B$296,0))) -> #N/A | W33: =IF(M33="Normative", "#d6bf2a", IF(M33="Informative", "#2f89d1", 1)) -> #d6bf2a
A34: 33 | B34: CEN/TR 15449-2 | C34: ISO 19135-1 | D34: ISO 19135 | E34: 2005.1 | F34: 2021.02 | G34: 35.240.70 | H34: =INDEX('GIS-Standards'!$A$2:$A$305,MATCH(B34,'GIS-Standards'!$B$2:$B$305,0)) -> 2 | I34: =INDEX('GIS-Standards'!$A$2:$A$305,MATCH(C34,'GIS-Standards'!$B$2:$B$305,0)) -> 41 | J34: =INDEX('GIS-Standards'!$O$2:$O$305,MATCH(B34,'GIS-Standards'!$B$2:$B$305,0)) -> 0 | K34: =INDEX('GIS-Standards'!$O$2:$O$305,MATCH(C34,'GIS-Standards'!$B$2:$B$305,0)) -> ISO/TC 211 | M34: Normative | N34: =INDEX('GIS-Standards'!$I$2:$I$305,MATCH(B34,'GIS-Standards'!$B$2:$B$305,0)) -> 0 | O34: =INDEX('GIS-Standards'!$I$2:$I$305,MATCH(C34,'GIS-Standards'!$B$2:$B$305,0)) -> 03.2021 | P34: =AND(TableRelationships12[[#This Row],[Source Type]]="BIM",TableRelationships12[[#This Row],[Target Type]]="BIM") -> FALSE | Q34: =IF(M34="Normative",6,IF(M34="Secondary",4,IF(M34="Anchor",2,1))) -> 6 | S34: =IF(R34="High",10,IF(R34="Medium",6,IF(R34="Low",2,1))) -> 1 | T34: =IF(TableRelationships12[[#This Row],[Rank Pedro]]="Low","linkCategory1",IF(TableRelationships12[[#This Row],[Rank Pedro]]="Medium","linkCategory2",IF(TableRelationships12[[#This Row],[Rank Pedro]]="High","linkCategory3",""))) | U34: =IF(TableRelationships12[[#This Row],[Rank Pedro]]="Low","Pink",IF(TableRelationships12[[#This Row],[Rank Pedro]]="Medium","Purple",IF(TableRelationships12[[#This Row],[Rank Pedro]]="High","Brown",""))) | V34: =MAX(INDEX(Standards!$F$2:$F$296,MATCH(B34,Standards!$B$2:$B$296,0)),INDEX(Standards!$F$2:$F$296,MATCH(C34,Standards!$B$2:$B$296,0))) -> #N/A | W34: =IF(M34="Normative", "#d6bf2a", IF(M34="Informative", "#2f89d1", 1)) -> #d6bf2a
A35: 34 | B35: CEN/TR 15449-3 | C35: GIS anchor | E35: 2012.10 | F35: 2012.10 | G35: 35.240.70; 07.040 | H35: =INDEX('GIS-Standards'!$A$2:$A$305,MATCH(B35,'GIS-Standards'!$B$2:$B$305,0)) -> 3 | I35: =INDEX('GIS-Standards'!$A$2:$A$305,MATCH(C35,'GIS-Standards'!$B$2:$B$305,0)) -> #N/A | J35: =INDEX('GIS-Standards'!$O$2:$O$305,MATCH(B35,'GIS-Standards'!$B$2:$B$305,0)) -> 0 | K35: =INDEX('GIS-Standards'!$O$2:$O$305,MATCH(C35,'GIS-Standards'!$B$2:$B$305,0)) -> #N/A | M35: Anchor | N35: =INDEX('GIS-Standards'!$I$2:$I$305,MATCH(B35,'GIS-Standards'!$B$2:$B$305,0)) -> 0 | O35: =INDEX('GIS-Standards'!$I$2:$I$305,MATCH(C35,'GIS-Standards'!$B$2:$B$305,0)) -> #N/A | P35: =AND(TableRelationships12[[#This Row],[Source Type]]="BIM",TableRelationships12[[#This Row],[Target Type]]="BIM") -> #N/A | Q35: =IF(M35="Normative",6,IF(M35="Secondary",4,IF(M35="Anchor",2,1))) -> 2 | S35: =IF(R35="High",10,IF(R35="Medium",6,IF(R35="Low",2,1))) -> 1 | T35: =IF(TableRelationships12[[#This Row],[Rank Pedro]]="Low","linkCategory1",IF(TableRelationships12[[#This Row],[Rank Pedro]]="Medium","linkCategory2",IF(TableRelationships12[[#This Row],[Rank Pedro]]="High","linkCategory3",""))) | U35: =IF(TableRelationships12[[#This Row],[Rank Pedro]]="Low","Pink",IF(TableRelationships12[[#This Row],[Rank Pedro]]="Medium","Purple",IF(TableRelationships12[[#This Row],[Rank Pedro]]="High","Brown",""))) | V35: =MAX(INDEX(Standards!$F$2:$F$296,MATCH(B35,Standards!$B$2:$B$296,0)),INDEX(Standards!$F$2:$F$296,MATCH(C35,Standards!$B$2:$B$296,0))) -> #N/A | W35: =IF(M35="Normative", "#d6bf2a", IF(M35="Informative", "#2f89d1", 1)) -> 1
A36: 35 | B36: CEN/TR 15449-3 | C36: ISO 19101-1 | D36: ISO 19101 | E36: 2002.07 | F36: 2014.11 | G36: 35.240.70 | H36: =INDEX('GIS-Standards'!$A$2:$A$305,MATCH(B36,'GIS-Standards'!$B$2:$B$305,0)) -> 3 | I36: =INDEX('GIS-Standards'!$A$2:$A$305,MATCH(D36,'GIS-Standards'!$B$2:$B$305,0)) -> #N/A | J36: =INDEX('GIS-Standards'!$O$2:$O$305,MATCH(B36,'GIS-Standards'!$B$2:$B$305,0)) -> 0 | K36: =INDEX('GIS-Standards'!$O$2:$O$305,MATCH(D36,'GIS-Standards'!$B$2:$B$305,0)) -> #N/A | M36: Informative | N36: =INDEX('GIS-Standards'!$I$2:$I$305,MATCH(B36,'GIS-Standards'!$B$2:$B$305,0)) -> 0 | O36: =INDEX('GIS-Standards'!$I$2:$I$305,MATCH(D36,'GIS-Standards'!$B$2:$B$305,0)) -> #N/A | P36: =AND(TableRelationships12[[#This Row],[Source Type]]="BIM",TableRelationships12[[#This Row],[Target Type]]="BIM") -> #N/A | Q36: =IF(M36="Normative",6,IF(M36="Secondary",4,IF(M36="Anchor",2,1))) -> 1 | S36: =IF(R36="High",10,IF(R36="Medium",6,IF(R36="Low",2,1))) -> 1 | T36: =IF(TableRelationships12[[#This Row],[Rank Pedro]]="Low","linkCategory1",IF(TableRelationships12[[#This Row],[Rank Pedro]]="Medium","linkCategory2",IF(TableRelationships12[[#This Row],[Rank Pedro]]="High","linkCategory3",""))) | U36: =IF(TableRelationships12[[#This Row],[Rank Pedro]]="Low","Pink",IF(TableRelationships12[[#This Row],[Rank Pedro]]="Medium","Purple",IF(TableRelationships12[[#This Row],[Rank Pedro]]="High","Brown",""))) | V36: =MAX(INDEX(Standards!$F$2:$F$296,MATCH(B36,Standards!$B$2:$B$296,0)),INDEX(Standards!$F$2:$F$296,MATCH(D36,Standards!$B$2:$B$296,0))) -> #N/A | W36: =IF(M36="Normative", "#d6bf2a", IF(M36="Informative", "#2f89d1", 1)) -> #2f89d1
A37: 36 | B37: CEN/TR 15449-3 | C37: ISO 19103 | E37: 2005.07 | F37: 2024.09 | G37: 35.240.70 | H37: =INDEX('GIS-Standards'!$A$2:$A$305,MATCH(B37,'GIS-Standards'!$B$2:$B$305,0)) -> 3 | I37: =INDEX('GIS-Standards'!$A$2:$A$305,MATCH(C37,'GIS-Standards'!$B$2:$B$305,0)) -> 12 | J37: =INDEX('GIS-Standards'!$O$2:$O$305,MATCH(B37,'GIS-Standards'!$B$2:$B$305,0)) -> 0 | K37: =INDEX('GIS-Standards'!$O$2:$O$305,MATCH(C37,'GIS-Standards'!$B$2:$B$305,0)) -> ISO/TC 211 | M37: Informative | N37: =INDEX('GIS-Standards'!$I$2:$I$305,MATCH(B37,'GIS-Standards'!$B$2:$B$305,0)) -> 0 | O37: =INDEX('GIS-Standards'!$I$2:$I$305,MATCH(C37,'GIS-Standards'!$B$2:$B$305,0)) -> 0 | P37: =AND(TableRelationships12[[#This Row],[Source Type]]="BIM",TableRelationships12[[#This Row],[Target Type]]="BIM") -> FALSE | Q37: =IF(M37="Normative",6,IF(M37="Secondary",4,IF(M37="Anchor",2,1))) -> 1 | S37: =IF(R37="High",10,IF(R37="Medium",6,IF(R37="Low",2,1))) -> 1 | T37: =IF(TableRelationships12[[#This Row],[Rank Pedro]]="Low","linkCategory1",IF(TableRelationships12[[#This Row],[Rank Pedro]]="Medium","linkCategory2",IF(TableRelationships12[[#This Row],[Rank Pedro]]="High","linkCategory3",""))) | U37: =IF(TableRelationships12[[#This Row],[Rank Pedro]]="Low","Pink",IF(TableRelationships12[[#This Row],[Rank Pedro]]="Medium","Purple",IF(TableRelationships12[[#This Row],[Rank Pedro]]="High","Brown",""))) | V37: =MAX(INDEX(Standards!$F$2:$F$296,MATCH(B37,Standards!$B$2:$B$296,0)),INDEX(Standards!$F$2:$F$296,MATCH(C37,Standards!$B$2:$B$296,0))) -> #N/A | W37: =IF(M37="Normative", "#d6bf2a", IF(M37="Informative", "#2f89d1", 1)) -> #2f89d1
A38: 37 | B38: CEN/TR 15449-3 | C38: ISO 19105 | E38: 2000.12 | F38: 2022.07 | G38: 35.240.70 | H38: =INDEX('GIS-Standards'!$A$2:$A$305,MATCH(B38,'GIS-Standards'!$B$2:$B$305,0)) -> 3 | I38: =INDEX('GIS-Standards'!$A$2:$A$305,MATCH(C38,'GIS-Standards'!$B$2:$B$305,0)) -> 14 | J38: =INDEX('GIS-Standards'!$O$2:$O$305,MATCH(B38,'GIS-Standards'!$B$2:$B$305,0)) -> 0 | K38: =INDEX('GIS-Standards'!$O$2:$O$305,MATCH(C38,'GIS-Standards'!$B$2:$B$305,0)) -> ISO/TC 211 | M38: Informative | N38: =INDEX('GIS-Standards'!$I$2:$I$305,MATCH(B38,'GIS-Standards'!$B$2:$B$305,0)) -> 0 | O38: =INDEX('GIS-Standards'!$I$2:$I$305,MATCH(C38,'GIS-Standards'!$B$2:$B$305,0)) -> 0 | P38: =AND(TableRelationships12[[#This Row],[Source Type]]="BIM",TableRelationships12[[#This Row],[Target Type]]="BIM") -> FALSE | Q38: =IF(M38="Normative",6,IF(M38="Secondary",4,IF(M38="Anchor",2,1))) -> 1 | S38: =IF(R38="High",10,IF(R38="Medium",6,IF(R38="Low",2,1))) -> 1 | T38: =IF(TableRelationships12[[#This Row],[Rank Pedro]]="Low","linkCategory1",IF(TableRelationships12[[#This Row],[Rank Pedro]]="Medium","linkCategory2",IF(TableRelationships12[[#This Row],[Rank Pedro]]="High","linkCategory3",""))) | U38: =IF(TableRelationships12[[#This Row],[Rank Pedro]]="Low","Pink",IF(TableRelationships12[[#This Row],[Rank Pedro]]="Medium","Purple",IF(TableRelationships12[[#This Row],[Rank Pedro]]="High","Brown",""))) | V38: =MAX(INDEX(Standards!$F$2:$F$296,MATCH(B38,Standards!$B$2:$B$296,0)),INDEX(Standards!$F$2:$F$296,MATCH(C38,Standards!$B$2:$B$296,0))) -> #N/A | W38: =IF(M38="Normative", "#d6bf2a", IF(M38="Informative", "#2f89d1", 1)) -> #2f89d1
A39: 38 | B39: CEN/TR 15449-3 | C39: ISO 19107 | E39: 2003.05 | F39: 2019.12 | G39: 35.240.70 | H39: =INDEX('GIS-Standards'!$A$2:$A$305,MATCH(B39,'GIS-Standards'!$B$2:$B$305,0)) -> 3 | I39: =INDEX('GIS-Standards'!$A$2:$A$305,MATCH(C39,'GIS-Standards'!$B$2:$B$305,0)) -> 16 | J39: =INDEX('GIS-Standards'!$O$2:$O$305,MATCH(B39,'GIS-Standards'!$B$2:$B$305,0)) -> 0 | K39: =INDEX('GIS-Standards'!$O$2:$O$305,MATCH(C39,'GIS-Standards'!$B$2:$B$305,0)) -> ISO/TC 211 | M39: Informative | N39: =INDEX('GIS-Standards'!$I$2:$I$305,MATCH(B39,'GIS-Standards'!$B$2:$B$305,0)) -> 0 | O39: =INDEX('GIS-Standards'!$I$2:$I$305,MATCH(C39,'GIS-Standards'!$B$2:$B$305,0)) -> 0 | P39: =AND(TableRelationships12[[#This Row],[Source Type]]="BIM",TableRelationships12[[#This Row],[Target Type]]="BIM") -> FALSE | Q39: =IF(M39="Normative",6,IF(M39="Secondary",4,IF(M39="Anchor",2,1))) -> 1 | S39: =IF(R39="High",10,IF(R39="Medium",6,IF(R39="Low",2,1))) -> 1 | T39: =IF(TableRelationships12[[#This Row],[Rank Pedro]]="Low","linkCategory1",IF(TableRelationships12[[#This Row],[Rank Pedro]]="Medium","linkCategory2",IF(TableRelationships12[[#This Row],[Rank Pedro]]="High","linkCategory3",""))) | U39: =IF(TableRelationships12[[#This Row],[Rank Pedro]]="Low","Pink",IF(TableRelationships12[[#This Row],[Rank Pedro]]="Medium","Purple",IF(TableRelationships12[[#This Row],[Rank Pedro]]="High","Brown",""))) | V39: =MAX(INDEX(Standards!$F$2:$F$296,MATCH(B39,Standards!$B$2:$B$296,0)),INDEX(Standards!$F$2:$F$296,MATCH(C39,Standards!$B$2:$B$296,0))) -> #N/A | W39: =IF(M39="Normative", "#d6bf2a", IF(M39="Informative", "#2f89d1", 1)) -> #2f89d1
A40: 39 | B40: CEN/TR 15449-3 | C40: ISO 19108 | E40: 2002.09 | F40: 2006.1 | G40: 35.240.70 | H40: =INDEX('GIS-Standards'!$A$2:$A$305,MATCH(B40,'GIS-Standards'!$B$2:$B$305,0)) -> 3 | I40: =INDEX('GIS-Standards'!$A$2:$A$305,MATCH(C40,'GIS-Standards'!$B$2:$B$305,0)) -> 17 | J40: =INDEX('GIS-Standards'!$O$2:$O$305,MATCH(B40,'GIS-Standards'!$B$2:$B$305,0)) -> 0 | K40: =INDEX('GIS-Standards'!$O$2:$O$305,MATCH(C40,'GIS-Standards'!$B$2:$B$305,0)) -> ISO/TC 211 | M40: Informative | N40: =INDEX('GIS-Standards'!$I$2:$I$305,MATCH(B40,'GIS-Standards'!$B$2:$B$305,0)) -> 0 | O40: =INDEX('GIS-Standards'!$I$2:$I$305,MATCH(C40,'GIS-Standards'!$B$2:$B$305,0)) -> 06.2008 | P40: =AND(TableRelationships12[[#This Row],[Source Type]]="BIM",TableRelationships12[[#This Row],[Target Type]]="BIM") -> FALSE | Q40: =IF(M40="Normative",6,IF(M40="Secondary",4,IF(M40="Anchor",2,1))) -> 1 | S40: =IF(R40="High",10,IF(R40="Medium",6,IF(R40="Low",2,1))) -> 1 | T40: =IF(TableRelationships12[[#This Row],[Rank Pedro]]="Low","linkCategory1",IF(TableRelationships12[[#This Row],[Rank Pedro]]="Medium","linkCategory2",IF(TableRelationships12[[#This Row],[Rank Pedro]]="High","linkCategory3",""))) | U40: =IF(TableRelationships12[[#This Row],[Rank Pedro]]="Low","Pink",IF(TableRelationships12[[#This Row],[Rank Pedro]]="Medium","Purple",IF(TableRelationships12[[#This Row],[Rank Pedro]]="High","Brown",""))) | V40: =MAX(INDEX(Standards!$F$2:$F$296,MATCH(B40,Standards!$B$2:$B$296,0)),INDEX(Standards!$F$2:$F$296,MATCH(C40,Standards!$B$2:$B$296,0))) -> #N/A | W40: =IF(M40="Normative", "#d6bf2a", IF(M40="Informative", "#2f89d1", 1)) -> #2f89d1
A41: 40 | B41: CEN/TR 15449-3 | C41: ISO 19109 | E41: 2005.06 | F41: 2025.07 | G41: 35.240.70 | H41: =INDEX('GIS-Standards'!$A$2:$A$305,MATCH(B41,'GIS-Standards'!$B$2:$B$305,0)) -> 3 | I41: =INDEX('GIS-Standards'!$A$2:$A$305,MATCH(C41,'GIS-Standards'!$B$2:$B$305,0)) -> 18 | J41: =INDEX('GIS-Standards'!$O$2:$O$305,MATCH(B41,'GIS-Standards'!$B$2:$B$305,0)) -> 0 | K41: =INDEX('GIS-Standards'!$O$2:$O$305,MATCH(C41,'GIS-Standards'!$B$2:$B$305,0)) -> ISO/TC 211 | M41: Informative | N41: =INDEX('GIS-Standards'!$I$2:$I$305,MATCH(B41,'GIS-Standards'!$B$2:$B$305,0)) -> 0 | O41: =INDEX('GIS-Standards'!$I$2:$I$305,MATCH(C41,'GIS-Standards'!$B$2:$B$305,0)) -> 0 | P41: =AND(TableRelationships12[[#This Row],[Source Type]]="BIM",TableRelationships12[[#This Row],[Target Type]]="BIM") -> FALSE | Q41: =IF(M41="Normative",6,IF(M41="Secondary",4,IF(M41="Anchor",2,1))) -> 1 | S41: =IF(R41="High",10,IF(R41="Medium",6,IF(R41="Low",2,1))) -> 1 | T41: =IF(TableRelationships12[[#This Row],[Rank Pedro]]="Low","linkCategory1",IF(TableRelationships12[[#This Row],[Rank Pedro]]="Medium","linkCategory2",IF(TableRelationships12[[#This Row],[Rank Pedro]]="High","linkCategory3",""))) | U41: =IF(TableRelationships12[[#This Row],[Rank Pedro]]="Low","Pink",IF(TableRelationships12[[#This Row],[Rank Pedro]]="Medium","Purple",IF(TableRelationships12[[#This Row],[Rank Pedro]]="High","Brown",""))) | V41: =MAX(INDEX(Standards!$F$2:$F$296,MATCH(B41,Standards!$B$2:$B$296,0)),INDEX(Standards!$F$2:$F$296,MATCH(C41,Standards!$B$2:$B$296,0))) -> #N/A | W41: =IF(M41="Normative", "#d6bf2a", IF(M41="Informative", "#2f89d1", 1)) -> #2f89d1
A42: 41 | B42: CEN/TR 15449-3 | C42: ISO 19110 | E42: 2005.02 | F42: 2016.12 | G42: 35.240.70 | H42: =INDEX('GIS-Standards'!$A$2:$A$305,MATCH(B42,'GIS-Standards'!$B$2:$B$305,0)) -> 3 | I42: =INDEX('GIS-Standards'!$A$2:$A$305,MATCH(C42,'GIS-Standards'!$B$2:$B$305,0)) -> 19 | J42: =INDEX('GIS-Standards'!$O$2:$O$305,MATCH(B42,'GIS-Standards'!$B$2:$B$305,0)) -> 0 | K42: =INDEX('GIS-Standards'!$O$2:$O$305,MATCH(C42,'GIS-Standards'!$B$2:$B$305,0)) -> ISO/TC 211 | M42: Informative | N42: =INDEX('GIS-Standards'!$I$2:$I$305,MATCH(B42,'GIS-Standards'!$B$2:$B$305,0)) -> 0 | O42: =INDEX('GIS-Standards'!$I$2:$I$305,MATCH(C42,'GIS-Standards'!$B$2:$B$305,0)) -> 0 | P42: =AND(TableRelationships12[[#This Row],[Source Type]]="BIM",TableRelationships12[[#This Row],[Target Type]]="BIM") -> FALSE | Q42: =IF(M42="Normative",6,IF(M42="Secondary",4,IF(M42="Anchor",2,1))) -> 1 | S42: =IF(R42="High",10,IF(R42="Medium",6,IF(R42="Low",2,1))) -> 1 | T42: =IF(TableRelationships12[[#This Row],[Rank Pedro]]="Low","linkCategory1",IF(TableRelationships12[[#This Row],[Rank Pedro]]="Medium","linkCategory2",IF(TableRelationships12[[#This Row],[Rank Pedro]]="High","linkCategory3",""))) | U42: =IF(TableRelationships12[[#This Row],[Rank Pedro]]="Low","Pink",IF(TableRelationships12[[#This Row],[Rank Pedro]]="Medium","Purple",IF(TableRelationships12[[#This Row],[Rank Pedro]]="High","Brown",""))) | V42: =MAX(INDEX(Standards!$F$2:$F$296,MATCH(B42,Standards!$B$2:$B$296,0)),INDEX(Standards!$F$2:$F$296,MATCH(C42,Standards!$B$2:$B$296,0))) -> #N/A | W42: =IF(M42="Normative", "#d6bf2a", IF(M42="Informative", "#2f89d1", 1)) -> #2f89d1
